Workbook

Sheet ROI
A1: Year | B1: Month | C1: Month Num | D1: Contact Forms | E1: RAQ | F1: CTM
A2: =IF(ISBLANK(C2),,2026) -> 2026 | B2: January | C2: 1 | D2: =SUMIFS('Yelp Sandbox Forms (2)'!M:M,'Yelp Sandbox Forms (2)'!T:T,ROI!A2,'Yelp Sandbox Forms (2)'!S:S,ROI!C2,'Yelp Sandbox Forms (2)'!Q:Q,1) -> 0 | E2: =SUMIFS('YELP RAQ - Lead Tracking (2)'!J:J,'YELP RAQ - Lead Tracking (2)'!AA:AA,ROI!A2,'YELP RAQ - Lead Tracking (2)'!Z:Z,ROI!C2) -> 0 | F2: =SUMIFS('Yelp CTM'!C:C,'Yelp CTM'!B:B,ROI!C2,'Yelp CTM'!A:A,ROI!A2) -> 2167
A3: =IF(ISBLANK(C3),,2026) -> 2026 | B3: February | C3: 2 | D3: =SUMIFS('Yelp Sandbox Forms (2)'!M:M,'Yelp Sandbox Forms (2)'!T:T,ROI!A3,'Yelp Sandbox Forms (2)'!S:S,ROI!C3,'Yelp Sandbox Forms (2)'!Q:Q,1) -> 29823 | E3: =SUMIFS('YELP RAQ - Lead Tracking (2)'!J:J,'YELP RAQ - Lead Tracking (2)'!AA:AA,ROI!A3,'YELP RAQ - Lead Tracking (2)'!Z:Z,ROI!C3) -> 0 | F3: =SUMIFS('Yelp CTM'!C:C,'Yelp CTM'!B:B,ROI!C3,'Yelp CTM'!A:A,ROI!A3) -> 1814
A4: =IF(ISBLANK(C4),,2026) -> 2026 | B4: March | C4: 3 | D4: =SUMIFS('Yelp Sandbox Forms (2)'!M:M,'Yelp Sandbox Forms (2)'!T:T,ROI!A4,'Yelp Sandbox Forms (2)'!S:S,ROI!C4,'Yelp Sandbox Forms (2)'!Q:Q,1) -> 0 | E4: =SUMIFS('YELP RAQ - Lead Tracking (2)'!J:J,'YELP RAQ - Lead Tracking (2)'!AA:AA,ROI!A4,'YELP RAQ - Lead Tracking (2)'!Z:Z,ROI!C4) -> 2935 | F4: =SUMIFS('Yelp CTM'!C:C,'Yelp CTM'!B:B,ROI!C4,'Yelp CTM'!A:A,ROI!A4) -> 755
A5: =IF(ISBLANK(C5),,2026) -> 2026 | B5: April | C5: 4 | D5: =SUMIFS('Yelp Sandbox Forms (2)'!M:M,'Yelp Sandbox Forms (2)'!T:T,ROI!A5,'Yelp Sandbox Forms (2)'!S:S,ROI!C5,'Yelp Sandbox Forms (2)'!Q:Q,1) -> 0 | E5: =SUMIFS('YELP RAQ - Lead Tracking (2)'!J:J,'YELP RAQ - Lead Tracking (2)'!AA:AA,ROI!A5,'YELP RAQ - Lead Tracking (2)'!Z:Z,ROI!C5) -> 14277 | F5: =SUMIFS('Yelp CTM'!C:C,'Yelp CTM'!B:B,ROI!C5,'Yelp CTM'!A:A,ROI!A5) -> 26821
A6: =IF(ISBLANK(C6),,2026) -> 2026 | B6: May | C6: 5 | D6: =SUMIFS('Yelp Sandbox Forms (2)'!M:M,'Yelp Sandbox Forms (2)'!T:T,ROI!A6,'Yelp Sandbox Forms (2)'!S:S,ROI!C6,'Yelp Sandbox Forms (2)'!Q:Q,1) -> 0 | E6: =SUMIFS('YELP RAQ - Lead Tracking (2)'!J:J,'YELP RAQ - Lead Tracking (2)'!AA:AA,ROI!A6,'YELP RAQ - Lead Tracking (2)'!Z:Z,ROI!C6) -> 4924 | F6: =SUMIFS('Yelp CTM'!C:C,'Yelp CTM'!B:B,ROI!C6,'Yelp CTM'!A:A,ROI!A6) -> 8274
A7: =IF(ISBLANK(C7),,2026) -> 2026 | B7: June | C7: 6 | D7: =SUMIFS('Yelp Sandbox Forms (2)'!M:M,'Yelp Sandbox Forms (2)'!T:T,ROI!A7,'Yelp Sandbox Forms (2)'!S:S,ROI!C7,'Yelp Sandbox Forms (2)'!Q:Q,1) -> 0 | E7: =SUMIFS('YELP RAQ - Lead Tracking (2)'!J:J,'YELP RAQ - Lead Tracking (2)'!AA:AA,ROI!A7,'YELP RAQ - Lead Tracking (2)'!Z:Z,ROI!C7) -> 0 | F7: =SUMIFS('Yelp CTM'!C:C,'Yelp CTM'!B:B,ROI!C7,'Yelp CTM'!A:A,ROI!A7) -> 0
A8: =IF(ISBLANK(C8),,2026) -> 2026 | B8: July | C8: 7 | D8: =SUMIFS('Yelp Sandbox Forms (2)'!M:M,'Yelp Sandbox Forms (2)'!T:T,ROI!A8,'Yelp Sandbox Forms (2)'!S:S,ROI!C8,'Yelp Sandbox Forms (2)'!Q:Q,1) -> 0 | E8: =SUMIFS('YELP RAQ - Lead Tracking (2)'!J:J,'YELP RAQ - Lead Tracking (2)'!AA:AA,ROI!A8,'YELP RAQ - Lead Tracking (2)'!Z:Z,ROI!C8) -> 0 | F8: =SUMIFS('Yelp CTM'!C:C,'Yelp CTM'!B:B,ROI!C8,'Yelp CTM'!A:A,ROI!A8) -> 0
A9: =IF(ISBLANK(C9),,2026) -> 2026 | B9: August | C9: 8 | D9: =SUMIFS('Yelp Sandbox Forms (2)'!M:M,'Yelp Sandbox Forms (2)'!T:T,ROI!A9,'Yelp Sandbox Forms (2)'!S:S,ROI!C9,'Yelp Sandbox Forms (2)'!Q:Q,1) -> 0 | E9: =SUMIFS('YELP RAQ - Lead Tracking (2)'!J:J,'YELP RAQ - Lead Tracking (2)'!AA:AA,ROI!A9,'YELP RAQ - Lead Tracking (2)'!Z:Z,ROI!C9) -> 0 | F9: =SUMIFS('Yelp CTM'!C:C,'Yelp CTM'!B:B,ROI!C9,'Yelp CTM'!A:A,ROI!A9) -> 0
A10: =IF(ISBLANK(C10),,2026) -> 2026 | B10: September | C10: 9 | D10: =SUMIFS('Yelp Sandbox Forms (2)'!M:M,'Yelp Sandbox Forms (2)'!T:T,ROI!A10,'Yelp Sandbox Forms (2)'!S:S,ROI!C10,'Yelp Sandbox Forms (2)'!Q:Q,1) -> 0 | E10: =SUMIFS('YELP RAQ - Lead Tracking (2)'!J:J,'YELP RAQ - Lead Tracking (2)'!AA:AA,ROI!A10,'YELP RAQ - Lead Tracking (2)'!Z:Z,ROI!C10) -> 0 | F10: =SUMIFS('Yelp CTM'!C:C,'Yelp CTM'!B:B,ROI!C10,'Yelp CTM'!A:A,ROI!A10) -> 0
A11: =IF(ISBLANK(C11),,2026) -> 2026 | B11: October | C11: 10 | D11: =SUMIFS('Yelp Sandbox Forms (2)'!M:M,'Yelp Sandbox Forms (2)'!T:T,ROI!A11,'Yelp Sandbox Forms (2)'!S:S,ROI!C11,'Yelp Sandbox Forms (2)'!Q:Q,1) -> 0 | E11: =SUMIFS('YELP RAQ - Lead Tracking (2)'!J:J,'YELP RAQ - Lead Tracking (2)'!AA:AA,ROI!A11,'YELP RAQ - Lead Tracking (2)'!Z:Z,ROI!C11) -> 0 | F11: =SUMIFS('Yelp CTM'!C:C,'Yelp CTM'!B:B,ROI!C11,'Yelp CTM'!A:A,ROI!A11) -> 0
A12: =IF(ISBLANK(C12),,2026) -> 2026 | B12: November | C12: 11 | D12: =SUMIFS('Yelp Sandbox Forms (2)'!M:M,'Yelp Sandbox Forms (2)'!T:T,ROI!A12,'Yelp Sandbox Forms (2)'!S:S,ROI!C12,'Yelp Sandbox Forms (2)'!Q:Q,1) -> 0 | E12: =SUMIFS('YELP RAQ - Lead Tracking (2)'!J:J,'YELP RAQ - Lead Tracking (2)'!AA:AA,ROI!A12,'YELP RAQ - Lead Tracking (2)'!Z:Z,ROI!C12) -> 0 | F12: =SUMIFS('Yelp CTM'!C:C,'Yelp CTM'!B:B,ROI!C12,'Yelp CTM'!A:A,ROI!A12) -> 0
A13: =IF(ISBLANK(C13),,2026) -> 2026 | B13: December | C13: 12 | D13: =SUMIFS('Yelp Sandbox Forms (2)'!M:M,'Yelp Sandbox Forms (2)'!T:T,ROI!A13,'Yelp Sandbox Forms (2)'!S:S,ROI!C13,'Yelp Sandbox Forms (2)'!Q:Q,1) -> 0 | E13: =SUMIFS('YELP RAQ - Lead Tracking (2)'!J:J,'YELP RAQ - Lead Tracking (2)'!AA:AA,ROI!A13,'YELP RAQ - Lead Tracking (2)'!Z:Z,ROI!C13) -> 0 | F13: =SUMIFS('Yelp CTM'!C:C,'Yelp CTM'!B:B,ROI!C13,'Yelp CTM'!A:A,ROI!A13) -> 0
A14: Total | D14: =SUM(D2:D13) -> 29823 | E14: =SUM(E2:E13) -> 22136 | F14: =SUM(F2:F13) -> 39831 | G14: =SUM(D14:F14) -> 91790

Sheet Yelp Sandbox Forms (2)
A1: Phone Number | B1: Date of Message | C1: Message Contents | D1: Message Source | E1: IM Lead | F1: Potential Sales Lead | G1: Customer ID | H1: Subscription is Active | I1: Customer record start date | J1: Customer unix cxl date | K1: Subscription Id | L1: Completed Initial | M1: Contract Value | N1: Subscription Start Date | O1: Subscription unix cxl date | P1: Service Type | Q1: Sale | R1: Corn Id | S1: Custom | T1: Custom.1
A2: 2014760436 | B2: 46073.501 | C2: {_x000D_ "id": 4037316584,_x000D_ "sid": "log-call-no-answer-230fb629cb51652d",_x000D_ "account_id": 441826,_x000D_ "name": "test mc testy",_x000D_ "cnam": "test mc testy",_x000D_ "search": "",_x000D_ "referrer": "",_x000D_ "visitor_sid": "",_x000D_ "location": "",_x000D_ "source": "Sandbox",_x000D_ "source_id": 1814974,_x000D_ "source_sid": "TSOF6FC2D2594D22C5288F2F91D669A9D5B9BE7FEE3C6EF44F4A9EA1A63913ECD83",_x000D_ "tgid": 5681974,_x000D_ "likelihood": null,_x000D_ "duration": 0,_x000D_ "direction": "form",_x000D_ "talk_time": 0,_x000D_ "ring_time": 0,_x000D_ "hold_time": 0,_x000D_ "wait_time": 0,_x000D_ "parent_id": null,_x000D_ "email": "chris.keenan@fox-pest.com",_x000D_ "street": null,_x000D_ "city": null,_x000D_ "state": null,_x000D_ "country": null,_x000D_ "postal_code": "07642",_x000D_ "called_at": "2026-02-20 06:02 AM -06:00",_x000D_ "unix_time": 1771592535,_x000D_ "tracking_number_id": 3476065,_x000D_ "tracking_number_sid": "TPNC3C4B23C348AEC2EE54EFD301979CD2EFFBA32881B159867D3F4ED59E6F0B56367EFF2993536685F",_x000D_ "tracking_number": "\u002B14352541043",_x000D_ "tracking_label": "Testing Number",_x000D_ "dial_status": "no-answer",_x000D_ "is_new_caller": true,_x000D_ "indexed_at": 1.7715931E+09,_x000D_ "agent_insights": false,_x000D_ "duration_period": {_x000D_ "gte": 1771592535000,_x000D_ "lte": 1771592535000_x000D_ },_x000D_ "inbound_rate_center": {_x000D_ "country": "US",_x000D_ "prefix": "1",_x000D_ "tollfree": false_x000D_ },_x000D_ "business_number": null,_x000D_ "business_label": null,_x000D_ "receiving_number_id": null,_x000D_ "receiving_number_sid": null,_x000D_ "billed_amount": 0,_x000D_ "billed_at": "0001-01-01T00:00:00",_x000D_ "excluded": false,_x000D_ "redacted": false,_x000D_ "tracking_number_format": "(435) 254-1043",_x000D_ "business_number_format": null,_x000D_ "alternative_number": "2014760436",_x000D_ "tracking_number_bare": "4352541043",_x000D_ "caller_number_format": "(201) 476-0436",_x000D_ "caller_number_complete": "\u002B12014760436",_x000D_ "caller_number_bare": "2014760436",_x000D_ "caller_number": "\u002B12014760436",_x000D_ "caller_number_split": [_x000D_ "1",_x000D_ "201",_x000D_ "476",_x000D_ "0436"_x000D_ ],_x000D_ "contact_number": "\u002B12014760436",_x000D_ "visitor": false,_x000D_ "call_path": [_x000D_ {_x000D_ "route_name": "_OnHangup_CallSync",_x000D_ "route_id": "640990",_x000D_ "route_type": "RoutingRule",_x000D_ "started_at": "2026-02-20T06:02:16Z"_x000D_ }_x000D_ ],_x000D_ "left_talk_time": 0,_x000D_ "right_talk_time": 0,_x000D_ "transfers": [],_x000D_ "call_status": "completed",_x000D_ "status": "completed",_x000D_ "spotted": [],_x000D_ "salesforce": {},_x000D_ "audio": null,_x000D_ "is_s3_link": false,_x000D_ "callbacks": [],_x000D_ "emails": [],_x000D_ "day": "Friday",_x000D_ "month": "February",_x000D_ "hour": "06AM",_x000D_ "paid": {_x000D_ "source": null,_x000D_ "medium": null_x000D_ },_x000D_ "ga": {_x000D_ "cid": "441826.4037316584",_x000D_ "ga4": []_x000D_ },_x000D_ "tag_list": [],_x000D_ "latitude": 41.0369,_x000D_ "longitude": -74.0405,_x000D_ "extended_lookup_on": true,_x000D_ "form": {_x000D_ "number_to_call": "log-call-no-answer-436038320fcfa469",_x000D_ "customer_number_to_dial": "\u002B12014760436",_x000D_ "name": "test mc testy",_x000D_ "email": "chris.keenan@fox-pest.com",_x000D_ "trackback_id": "trackback-441826.1771592535.2455",_x000D_ "form_id": 213071,_x000D_ "form_name": "Contact Us",_x000D_ "custom": [_x000D_ {_x000D_ "label": "Referral Source",_x000D_ "value": "",_x000D_ "id": "referral_source"_x000D_ },_x000D_ {_x000D_ "label": "UTM Source",_x000D_ "value": "",_x000D_ "id": "utm_source"_x000D_ },_x000D_ {_x000D_ "label": "UTM Medium",_x000D_ "value": "",_x000D_ "id": "utm_medium"_x000D_ },_x000D_ {_x000D_ "label": "UTM Campaign",_x000D_ "value": "",_x000D_ "id": "utm_campaign"_x000D_ },_x000D_ {_x000D_ "label": "UTM Term",_x000D_ "value": "",_x000D_ "id": "utm_term"_x000D_ },_x000D_ {_x000D_ "label": "UTM Content",_x000D_ "value": "",_x000D_ "id": "utm_content"_x000D_ }_x000D_ ]_x000D_ },_x000D_ "legs": [],_x000D_ "touchpoints": null,_x000D_ "last_touch": null,_x000D_ "geo": {_x000D_ "lon": -74.0405,_x000D_ "lat": 41.0369_x000D_ },_x000D_ "timestamp": "0001-01-01T00:00:00"_x000D_ } | E2: 0 | F2: 1 | Q2: 0 | R2: 4037316584 | S2: 2 | T2: 2026
A3: 2015552012 | B3: 46073.116 | C3: {_x000D_ "id": 4037107502,_x000D_ "sid": "log-call-no-answer-2fec2fe1231a4499",_x000D_ "account_id": 441826,_x000D_ "name": "Shirley Desimone",_x000D_ "cnam": "Shirley Desimone",_x000D_ "search": "",_x000D_ "referrer": "",_x000D_ "visitor_sid": "",_x000D_ "location": "",_x000D_ "source": "Sandbox",_x000D_ "source_id": 1814974,_x000D_ "source_sid": "TSOF6FC2D2594D22C5288F2F91D669A9D5B9BE7FEE3C6EF44F4A9EA1A63913ECD83",_x000D_ "tgid": 5681974,_x000D_ "likelihood": null,_x000D_ "duration": 0,_x000D_ "direction": "form",_x000D_ "talk_time": 0,_x000D_ "ring_time": 0,_x000D_ "hold_time": 0,_x000D_ "wait_time": 0,_x000D_ "parent_id": null,_x000D_ "email": "shirleydesimone.mkt@gmail.com",_x000D_ "street": null,_x000D_ "city": null,_x000D_ "state": null,_x000D_ "country": null,_x000D_ "postal_code": null,_x000D_ "called_at": "2026-02-19 08:47 PM -06:00",_x000D_ "unix_time": 1771559249,_x000D_ "tracking_number_id": 3476065,_x000D_ "tracking_number_sid": "TPNC3C4B23C348AEC2EE54EFD301979CD2EFFBA32881B159867D3F4ED59E6F0B56367EFF2993536685F",_x000D_ "tracking_number": "\u002B14352541043",_x000D_ "tracking_label": "Testing Number",_x000D_ "dial_status": "no-answer",_x000D_ "is_new_caller": true,_x000D_ "indexed_at": 1.7715598E+09,_x000D_ "agent_insights": false,_x000D_ "duration_period": {_x000D_ "gte": 1771559249000,_x000D_ "lte": 1771559249000_x000D_ },_x000D_ "inbound_rate_center": {_x000D_ "country": "US",_x000D_ "prefix": "1",_x000D_ "tollfree": false_x000D_ },_x000D_ "business_number": null,_x000D_ "business_label": null,_x000D_ "receiving_number_id": null,_x000D_ "receiving_number_sid": null,_x000D_ "billed_amount": 0,_x000D_ "billed_at": "0001-01-01T00:00:00",_x000D_ "excluded": false,_x000D_ "redacted": false,_x000D_ "tracking_number_format": "(435) 254-1043",_x000D_ "business_number_format": null,_x000D_ "alternative_number": "2015552012",_x000D_ "tracking_number_bare": "4352541043",_x000D_ "caller_number_format": "(201) 555-2012",_x000D_ "caller_number_complete": "\u002B12015552012",_x000D_ "caller_number_bare": "2015552012",_x000D_ "caller_number": "\u002B12015552012",_x000D_ "caller_number_split": [_x000D_ "1",_x000D_ "201",_x000D_ "555",_x000D_ "2012"_x000D_ ],_x000D_ "contact_number": "\u002B12015552012",_x000D_ "visitor": false,_x000D_ "call_path": [_x000D_ {_x000D_ "route_name": "_OnHangup_CallSync",_x000D_ "route_id": "640990",_x000D_ "route_type": "RoutingRule",_x000D_ "started_at": "2026-02-19T20:47:30Z"_x000D_ }_x000D_ ],_x000D_ "left_talk_time": 0,_x000D_ "right_talk_time": 0,_x000D_ "transfers": [],_x000D_ "call_status": "completed",_x000D_ "status": "completed",_x000D_ "spotted": [],_x000D_ "salesforce": {},_x000D_ "audio": null,_x000D_ "is_s3_link": false,_x000D_ "callbacks": [],_x000D_ "emails": [],_x000D_ "day": "Thursday",_x000D_ "month": "February",_x000D_ "hour": "08PM",_x000D_ "paid": {_x000D_ "source": null,_x000D_ "medium": null_x000D_ },_x000D_ "ga": {_x000D_ "cid": "441826.4037107502",_x000D_ "ga4": []_x000D_ },_x000D_ "tag_list": [],_x000D_ "latitude": 0,_x000D_ "longitude": 0,_x000D_ "extended_lookup_on": true,_x000D_ "form": {_x000D_ "number_to_call": "log-call-no-answer-797e6992881f801e",_x000D_ "customer_number_to_dial": "\u002B12015552012",_x000D_ "name": "Shirley Desimone",_x000D_ "email": "shirleydesimone.mkt@gmail.com",_x000D_ "trackback_id": "trackback-441826.1771559248.976668",_x000D_ "form_id": 213071,_x000D_ "form_name": "Contact Us",_x000D_ "custom": [_x000D_ {_x000D_ "label": "Referral Source",_x000D_ "value": "",_x000D_ "id": "referral_source"_x000D_ },_x000D_ {_x000D_ "label": "UTM Source",_x000D_ "value": "",_x000D_ "id": "utm_source"_x000D_ },_x000D_ {_x000D_ "label": "UTM Medium",_x000D_ "value": "",_x000D_ "id": "utm_medium"_x000D_ },_x000D_ {_x000D_ "label": "UTM Campaign",_x000D_ "value": "",_x000D_ "id": "utm_campaign"_x000D_ },_x000D_ {_x000D_ "label": "UTM Term",_x000D_ "value": "",_x000D_ "id": "utm_term"_x000D_ },_x000D_ {_x000D_ "label": "UTM Content",_x000D_ "value": "",_x000D_ "id": "utm_content"_x000D_ }_x000D_ ]_x000D_ },_x000D_ "legs": [],_x000D_ "touchpoints": null,_x000D_ "last_touch": null,_x000D_ "geo": {_x000D_ "lon": 0,_x000D_ "lat": 0_x000D_ },_x000D_ "timestamp": "0001-01-01T00:00:00"_x000D_ } | E3: 0 | F3: 1 | Q3: 0 | R3: 4037107502 | S3: 2 | T3: 2026
A4: 2019540776 | B4: 46077.745 | C4: {_x000D_ "id": 4045325210,_x000D_ "sid": "log-call-no-answer-d52a60c5df94ade0",_x000D_ "account_id": 441826,_x000D_ "name": "NOOR JANJUA",_x000D_ "cnam": "NOOR JANJUA",_x000D_ "search": "",_x000D_ "referrer": "",_x000D_ "visitor_sid": "",_x000D_ "location": "",_x000D_ "source": "Sandbox",_x000D_ "source_id": 1814974,_x000D_ "source_sid": "TSOF6FC2D2594D22C5288F2F91D669A9D5B9BE7FEE3C6EF44F4A9EA1A63913ECD83",_x000D_ "tgid": 5681974,_x000D_ "likelihood": null,_x000D_ "duration": 0,_x000D_ "direction": "form",_x000D_ "talk_time": 0,_x000D_ "ring_time": 0,_x000D_ "hold_time": 0,_x000D_ "wait_time": 0,_x000D_ "parent_id": null,_x000D_ "email": "NOORJANJUA@FEDERONSOLUTIONS.COM",_x000D_ "street": null,_x000D_ "city": "Caldwell",_x000D_ "state": "NJ",_x000D_ "country": null,_x000D_ "postal_code": "07004",_x000D_ "called_at": "2026-02-24 11:53 AM -06:00",_x000D_ "unix_time": 1771959218,_x000D_ "tracking_number_id": 3476065,_x000D_ "tracking_number_sid": "TPNC3C4B23C348AEC2EE54EFD301979CD2EFFBA32881B159867D3F4ED59E6F0B56367EFF2993536685F",_x000D_ "tracking_number": "\u002B14352541043",_x000D_ "tracking_label": "Testing Number",_x000D_ "dial_status": "no-answer",_x000D_ "is_new_caller": true,_x000D_ "indexed_at": 1.7719598E+09,_x000D_ "agent_insights": false,_x000D_ "duration_period": {_x000D_ "gte": 1771959218000,_x000D_ "lte": 1771959218000_x000D_ },_x000D_ "inbound_rate_center": {_x000D_ "country": "US",_x000D_ "prefix": "1",_x000D_ "tollfree": false_x000D_ },_x000D_ "business_number": null,_x000D_ "business_label": null,_x000D_ "receiving_number_id": null,_x000D_ "receiving_number_sid": null,_x000D_ "billed_amount": 0,_x000D_ "billed_at": "0001-01-01T00:00:00",_x000D_ "excluded": false,_x000D_ "redacted": false,_x000D_ "tracking_number_format": "(435) 254-1043",_x000D_ "business_number_format": null,_x000D_ "alternative_number": "2019540776",_x000D_ "tracking_number_bare": "4352541043",_x000D_ "caller_number_format": "(201) 954-0776",_x000D_ "caller_number_complete": "\u002B12019540776",_x000D_ "caller_number_bare": "2019540776",_x000D_ "caller_number": "\u002B12019540776",_x000D_ "caller_number_split": [_x000D_ "1",_x000D_ "201",_x000D_ "954",_x000D_ "0776"_x000D_ ],_x000D_ "contact_number": "\u002B12019540776",_x000D_ "visitor": false,_x000D_ "call_path": [_x000D_ {_x000D_ "route_name": "_OnHangup_CallSync",_x000D_ "route_id": "640990",_x000D_ "route_type": "RoutingRule",_x000D_ "started_at": "2026-02-24T11:53:39Z"_x000D_ }_x000D_ ],_x000D_ "left_talk_time": 0,_x000D_ "right_talk_time": 0,_x000D_ "transfers": [],_x000D_ "call_status": "completed",_x000D_ "status": "completed",_x000D_ "spotted": [],_x000D_ "salesforce": {},_x000D_ "audio": null,_x000D_ "is_s3_link": false,_x000D_ "callbacks": [],_x000D_ "emails": [],_x000D_ "day": "Tuesday",_x000D_ "month": "February",_x000D_ "hour": "11AM",_x000D_ "paid": {_x000D_ "source": null,_x000D_ "medium": null_x000D_ },_x000D_ "ga": {_x000D_ "cid": "441826.4045325210",_x000D_ "ga4": []_x000D_ },_x000D_ "tag_list": [],_x000D_ "latitude": 40.8421,_x000D_ "longitude": -74.2742,_x000D_ "extended_lookup_on": true,_x000D_ "form": {_x000D_ "number_to_call": "log-call-no-answer-846aa5f9c9480080",_x000D_ "customer_number_to_dial": "\u002B12019540776",_x000D_ "name": "NOOR JANJUA",_x000D_ "email": "NOORJANJUA@FEDERONSOLUTIONS.COM",_x000D_ "trackback_id": "trackback-441826.1771959218.238851",_x000D_ "form_id": 213071,_x000D_ "form_name": "Contact Us",_x000D_ "custom": [_x000D_ {_x000D_ "label": "Referral Source",_x000D_ "value": "",_x000D_ "id": "referral_source"_x000D_ },_x000D_ {_x000D_ "label": "UTM Source",_x000D_ "value": "",_x000D_ "id": "utm_source"_x000D_ },_x000D_ {_x000D_ "label": "UTM Medium",_x000D_ "value": "",_x000D_ "id": "utm_medium"_x000D_ },_x000D_ {_x000D_ "label": "UTM Campaign",_x000D_ "value": "",_x000D_ "id": "utm_campaign"_x000D_ },_x000D_ {_x000D_ "label": "UTM Term",_x000D_ "value": "",_x000D_ "id": "utm_term"_x000D_ },_x000D_ {_x000D_ "label": "UTM Content",_x000D_ "value": "",_x000D_ "id": "utm_content"_x000D_ }_x000D_ ]_x000D_ },_x000D_ "legs": [],_x000D_ "touchpoints": null,_x000D_ "last_touch": null,_x000D_ "geo": {_x000D_ "lon": -74.2742,_x000D_ "lat": 40.8421_x000D_ },_x000D_ "timestamp": "0001-01-01T00:00:00"_x000D_ } | E4: 0 | F4: 1 | Q4: 0 | R4: 4045325210 | S4: 2 | T4: 2026
A5: 2019540776 | B5: 46077.745 | C5: {_x000D_ "id": 4045325453,_x000D_ "sid": "log-call-no-answer-6d53d95e96da5b3e",_x000D_ "account_id": 441826,_x000D_ "name": "NOOR JANJUA",_x000D_ "cnam": "NOOR JANJUA",_x000D_ "search": "",_x000D_ "referrer": "",_x000D_ "visitor_sid": "",_x000D_ "location": "",_x000D_ "source": "Sandbox",_x000D_ "source_id": 1814974,_x000D_ "source_sid": "TSOF6FC2D2594D22C5288F2F91D669A9D5B9BE7FEE3C6EF44F4A9EA1A63913ECD83",_x000D_ "tgid": 5681974,_x000D_ "likelihood": null,_x000D_ "duration": 0,_x000D_ "direction": "form",_x000D_ "talk_time": 0,_x000D_ "ring_time": 0,_x000D_ "hold_time": 0,_x000D_ "wait_time": 0,_x000D_ "parent_id": null,_x000D_ "email": "NOORJANJUA@FEDERONSOLUTIONS.COM",_x000D_ "street": null,_x000D_ "city": "Caldwell",_x000D_ "state": "NJ",_x000D_ "country": null,_x000D_ "postal_code": "07004",_x000D_ "called_at": "2026-02-24 11:53 AM -06:00",_x000D_ "unix_time": 1771959221,_x000D_ "tracking_number_id": 3476065,_x000D_ "tracking_number_sid": "TPNC3C4B23C348AEC2EE54EFD301979CD2EFFBA32881B159867D3F4ED59E6F0B56367EFF2993536685F",_x000D_ "tracking_number": "\u002B14352541043",_x000D_ "tracking_label": "Testing Number",_x000D_ "dial_status": "no-answer",_x000D_ "is_new_caller": false,_x000D_ "indexed_at": 1.7719598E+09,_x000D_ "agent_insights": false,_x000D_ "duration_period": {_x000D_ "gte": 1771959221000,_x000D_ "lte": 1771959221000_x000D_ },_x000D_ "inbound_rate_center": {_x000D_ "country": "US",_x000D_ "prefix": "1",_x000D_ "tollfree": false_x000D_ },_x000D_ "business_number": null,_x000D_ "business_label": null,_x000D_ "receiving_number_id": null,_x000D_ "receiving_number_sid": null,_x000D_ "billed_amount": 0,_x000D_ "billed_at": "0001-01-01T00:00:00",_x000D_ "excluded": false,_x000D_ "redacted": false,_x000D_ "tracking_number_format": "(435) 254-1043",_x000D_ "business_number_format": null,_x000D_ "alternative_number": "2019540776",_x000D_ "tracking_number_bare": "4352541043",_x000D_ "caller_number_format": "(201) 954-0776",_x000D_ "caller_number_complete": "\u002B12019540776",_x000D_ "caller_number_bare": "2019540776",_x000D_ "caller_number": "\u002B12019540776",_x000D_ "caller_number_split": [_x000D_ "1",_x000D_ "201",_x000D_ "954",_x000D_ "0776"_x000D_ ],_x000D_ "contact_number": "\u002B12019540776",_x000D_ "visitor": false,_x000D_ "call_path": [_x000D_ {_x000D_ "route_name": "_OnHangup_CallSync",_x000D_ "route_id": "640990",_x000D_ "route_type": "RoutingRule",_x000D_ "started_at": "2026-02-24T11:53:42Z"_x000D_ }_x000D_ ],_x000D_ "left_talk_time": 0,_x000D_ "right_talk_time": 0,_x000D_ "transfers": [],_x000D_ "call_status": "completed",_x000D_ "status": "completed",_x000D_ "spotted": [],_x000D_ "salesforce": {},_x000D_ "audio": null,_x000D_ "is_s3_link": false,_x000D_ "callbacks": [],_x000D_ "emails": [],_x000D_ "day": "Tuesday",_x000D_ "month": "February",_x000D_ "hour": "11AM",_x000D_ "paid": {_x000D_ "source": null,_x000D_ "medium": null_x000D_ },_x000D_ "ga": {_x000D_ "cid": "441826.4045325453",_x000D_ "ga4": []_x000D_ },_x000D_ "tag_list": [],_x000D_ "latitude": 40.8421,_x000D_ "longitude": -74.2742,_x000D_ "extended_lookup_on": true,_x000D_ "form": {_x000D_ "number_to_call": "log-call-no-answer-942947867fe93594",_x000D_ "customer_number_to_dial": "\u002B12019540776",_x000D_ "name": "NOOR JANJUA",_x000D_ "email": "NOORJANJUA@FEDERONSOLUTIONS.COM",_x000D_ "trackback_id": "trackback-441826.1771959221.2178426",_x000D_ "form_id": 213071,_x000D_ "form_name": "Contact Us",_x000D_ "custom": [_x000D_ {_x000D_ "label": "Referral Source",_x000D_ "value": "",_x000D_ "id": "referral_source"_x000D_ },_x000D_ {_x000D_ "label": "UTM Source",_x000D_ "value": "",_x000D_ "id": "utm_source"_x000D_ },_x000D_ {_x000D_ "label": "UTM Medium",_x000D_ "value": "",_x000D_ "id": "utm_medium"_x000D_ },_x000D_ {_x000D_ "label": "UTM Campaign",_x000D_ "value": "",_x000D_ "id": "utm_campaign"_x000D_ },_x000D_ {_x000D_ "label": "UTM Term",_x000D_ "value": "",_x000D_ "id": "utm_term"_x000D_ },_x000D_ {_x000D_ "label": "UTM Content",_x000D_ "value": "",_x000D_ "id": "utm_content"_x000D_ }_x000D_ ]_x000D_ },_x000D_ "legs": [],_x000D_ "touchpoints": null,_x000D_ "last_touch": null,_x000D_ "geo": {_x000D_ "lon": -74.2742,_x000D_ "lat": 40.8421_x000D_ },_x000D_ "timestamp": "0001-01-01T00:00:00"_x000D_ } | E5: 0 | F5: 1 | Q5: 0 | R5: 4045325453 | S5: 2 | T5: 2026
A6: 2032475134 | B6: 46078.858 | C6: {_x000D_ "id": 4048720598,_x000D_ "sid": "log-call-no-answer-b407f04eca782aab",_x000D_ "account_id": 441826,_x000D_ "name": "Nancye Fritz",_x000D_ "cnam": "Nancye Fritz",_x000D_ "search": "",_x000D_ "referrer": "",_x000D_ "visitor_sid": "",_x000D_ "location": "",_x000D_ "source": "Sandbox",_x000D_ "source_id": 1814974,_x000D_ "source_sid": "TSOF6FC2D2594D22C5288F2F91D669A9D5B9BE7FEE3C6EF44F4A9EA1A63913ECD83",_x000D_ "tgid": 5681974,_x000D_ "likelihood": null,_x000D_ "duration": 0,_x000D_ "direction": "form",_x000D_ "talk_time": 0,_x000D_ "ring_time": 0,_x000D_ "hold_time": 0,_x000D_ "wait_time": 0,_x000D_ "parent_id": null,_x000D_ "email": "nancyefritz1980@gmail.com",_x000D_ "street": null,_x000D_ "city": "Norwalk",_x000D_ "state": "CT",_x000D_ "country": null,_x000D_ "postal_code": "06850",_x000D_ "called_at": "2026-02-25 02:36 PM -06:00",_x000D_ "unix_time": 1772055365,_x000D_ "tracking_number_id": 3476065,_x000D_ "tracking_number_sid": "TPNC3C4B23C348AEC2EE54EFD301979CD2EFFBA32881B159867D3F4ED59E6F0B56367EFF2993536685F",_x000D_ "tracking_number": "\u002B14352541043",_x000D_ "tracking_label": "Testing Number",_x000D_ "dial_status": "no-answer",_x000D_ "is_new_caller": true,_x000D_ "indexed_at": 1.7720559E+09,_x000D_ "agent_insights": false,_x000D_ "duration_period": {_x000D_ "gte": 1772055365000,_x000D_ "lte": 1772055365000_x000D_ },_x000D_ "inbound_rate_center": {_x000D_ "country": "US",_x000D_ "prefix": "1",_x000D_ "tollfree": false_x000D_ },_x000D_ "business_number": null,_x000D_ "business_label": null,_x000D_ "receiving_number_id": null,_x000D_ "receiving_number_sid": null,_x000D_ "billed_amount": 0,_x000D_ "billed_at": "0001-01-01T00:00:00",_x000D_ "excluded": false,_x000D_ "redacted": false,_x000D_ "tracking_number_format": "(435) 254-1043",_x000D_ "business_number_format": null,_x000D_ "alternative_number": "2032475134",_x000D_ "tracking_number_bare": "4352541043",_x000D_ "caller_number_format": "(203) 247-5134",_x000D_ "caller_number_complete": "\u002B12032475134",_x000D_ "caller_number_bare": "2032475134",_x000D_ "caller_number": "\u002B12032475134",_x000D_ "caller_number_split": [_x000D_ "1",_x000D_ "203",_x000D_ "247",_x000D_ "5134"_x000D_ ],_x000D_ "contact_number": "\u002B12032475134",_x000D_ "visitor": false,_x000D_ "call_path": [_x000D_ {_x000D_ "route_name": "_OnHangup_CallSync",_x000D_ "route_id": "640990",_x000D_ "route_type": "RoutingRule",_x000D_ "started_at": "2026-02-25T14:36:06Z"_x000D_ }_x000D_ ],_x000D_ "left_talk_time": 0,_x000D_ "right_talk_time": 0,_x000D_ "transfers": [],_x000D_ "call_status": "completed",_x000D_ "status": "completed",_x000D_ "spotted": [],_x000D_ "salesforce": {},_x000D_ "audio": null,_x000D_ "is_s3_link": false,_x000D_ "callbacks": [],_x000D_ "emails": [],_x000D_ "day": "Wednesday",_x000D_ "month": "February",_x000D_ "hour": "02PM",_x000D_ "paid": {_x000D_ "source": null,_x000D_ "medium": null_x000D_ },_x000D_ "ga": {_x000D_ "cid": "441826.4048720598",_x000D_ "ga4": []_x000D_ },_x000D_ "tag_list": [],_x000D_ "latitude": 41.1144,_x000D_ "longitude": -73.4054,_x000D_ "extended_lookup_on": true,_x000D_ "form": {_x000D_ "number_to_call": "log-call-no-answer-9adb8cfc697ea8dc",_x000D_ "customer_number_to_dial": "\u002B12032475134",_x000D_ "name": "Nancye Fritz",_x000D_ "email": "nancyefritz1980@gmail.com",_x000D_ "trackback_id": "trackback-441826.1772055365.2770667",_x000D_ "form_id": 213071,_x000D_ "form_name": "Contact Us",_x000D_ "custom": [_x000D_ {_x000D_ "label": "Referral Source",_x000D_ "value": "",_x000D_ "id": "referral_source"_x000D_ },_x000D_ {_x000D_ "label": "UTM Source",_x000D_ "value": "",_x000D_ "id": "utm_source"_x000D_ },_x000D_ {_x000D_ "label": "UTM Medium",_x000D_ "value": "",_x000D_ "id": "utm_medium"_x000D_ },_x000D_ {_x000D_ "label": "UTM Campaign",_x000D_ "value": "",_x000D_ "id": "utm_campaign"_x000D_ },_x000D_ {_x000D_ "label": "UTM Term",_x000D_ "value": "",_x000D_ "id": "utm_term"_x000D_ },_x000D_ {_x000D_ "label": "UTM Content",_x000D_ "value": "",_x000D_ "id": "utm_content"_x000D_ }_x000D_ ]_x000D_ },_x000D_ "legs": [],_x000D_ "touchpoints": null,_x000D_ "last_touch": null,_x000D_ "geo": {_x000D_ "lon": -73.4054,_x000D_ "lat": 41.1144_x000D_ },_x000D_ "timestamp": "0001-01-01T00:00:00"_x000D_ } | E6: 1 | F6: 1 | G6: 1524101 | H6: 1 | I6: 46078.91 | K6: 1772200 | L6: 1 | M6: 990 | N6: 46078.91 | P6: Fox Home Protection Plan | Q6: 1 | R6: 4048720598 | S6: 2 | T6: 2026
A7: 2032579728 | B7: 46073.606 | C7: {_x000D_ "id": 4037656223,_x000D_ "sid": "log-call-no-answer-584bcd0113e12e57",_x000D_ "account_id": 441826,_x000D_ "name": "KING ROGERS",_x000D_ "cnam": "KING ROGERS",_x000D_ "search": "",_x000D_ "referrer": "",_x000D_ "visitor_sid": "",_x000D_ "location": "",_x000D_ "source": "Sandbox",_x000D_ "source_id": 1814974,_x000D_ "source_sid": "TSOF6FC2D2594D22C5288F2F91D669A9D5B9BE7FEE3C6EF44F4A9EA1A63913ECD83",_x000D_ "tgid": 5681974,_x000D_ "likelihood": null,_x000D_ "duration": 0,_x000D_ "direction": "form",_x000D_ "talk_time": 0,_x000D_ "ring_time": 0,_x000D_ "hold_time": 0,_x000D_ "wait_time": 0,_x000D_ "parent_id": null,_x000D_ "email": "kingerogers@gmail.com",_x000D_ "street": null,_x000D_ "city": null,_x000D_ "state": null,_x000D_ "country": null,_x000D_ "postal_code": "06601",_x000D_ "called_at": "2026-02-20 08:33 AM -06:00",_x000D_ "unix_time": 1771601584,_x000D_ "tracking_number_id": 3476065,_x000D_ "tracking_number_sid": "TPNC3C4B23C348AEC2EE54EFD301979CD2EFFBA32881B159867D3F4ED59E6F0B56367EFF2993536685F",_x000D_ "tracking_number": "\u002B14352541043",_x000D_ "tracking_label": "Testing Number",_x000D_ "dial_status": "no-answer",_x000D_ "is_new_caller": true,_x000D_ "indexed_at": 1.7716022E+09,_x000D_ "agent_insights": false,_x000D_ "duration_period": {_x000D_ "gte": 1771601584000,_x000D_ "lte": 1771601584000_x000D_ },_x000D_ "inbound_rate_center": {_x000D_ "country": "US",_x000D_ "prefix": "1",_x000D_ "tollfree": false_x000D_ },_x000D_ "business_number": null,_x000D_ "business_label": null,_x000D_ "receiving_number_id": null,_x000D_ "receiving_number_sid": null,_x000D_ "billed_amount": 0,_x000D_ "billed_at": "0001-01-01T00:00:00",_x000D_ "excluded": false,_x000D_ "redacted": false,_x000D_ "tracking_number_format": "(435) 254-1043",_x000D_ "business_number_format": null,_x000D_ "alternative_number": "2032579728",_x000D_ "tracking_number_bare": "4352541043",_x000D_ "caller_number_format": "(203) 257-9728",_x000D_ "caller_number_complete": "\u002B12032579728",_x000D_ "caller_number_bare": "2032579728",_x000D_ "caller_number": "\u002B12032579728",_x000D_ "caller_number_split": [_x000D_ "1",_x000D_ "203",_x000D_ "257",_x000D_ "9728"_x000D_ ],_x000D_ "contact_number": "\u002B12032579728",_x000D_ "visitor": false,_x000D_ "call_path": [_x000D_ {_x000D_ "route_name": "_OnHangup_CallSync",_x000D_ "route_id": "640990",_x000D_ "route_type": "RoutingRule",_x000D_ "started_at": "2026-02-20T08:33:06Z"_x000D_ }_x000D_ ],_x000D_ "left_talk_time": 0,_x000D_ "right_talk_time": 0,_x000D_ "transfers": [],_x000D_ "call_status": "completed",_x000D_ "status": "completed",_x000D_ "spotted": [],_x000D_ "salesforce": {},_x000D_ "audio": null,_x000D_ "is_s3_link": false,_x000D_ "callbacks": [],_x000D_ "emails": [],_x000D_ "day": "Friday",_x000D_ "month": "February",_x000D_ "hour": "08AM",_x000D_ "paid": {_x000D_ "source": null,_x000D_ "medium": null_x000D_ },_x000D_ "ga": {_x000D_ "cid": "441826.4037656223",_x000D_ "ga4": []_x000D_ },_x000D_ "tag_list": [],_x000D_ "latitude": 41.1854,_x000D_ "longitude": -73.1962,_x000D_ "extended_lookup_on": true,_x000D_ "form": {_x000D_ "number_to_call": "log-call-no-answer-9d5004bb25a3fb04",_x000D_ "customer_number_to_dial": "\u002B12032579728",_x000D_ "name": "KING ROGERS",_x000D_ "email": "kingerogers@gmail.com",_x000D_ "trackback_id": "trackback-441826.1771601584.903589",_x000D_ "form_id": 213071,_x000D_ "form_name": "Contact Us",_x000D_ "custom": [_x000D_ {_x000D_ "label": "Referral Source",_x000D_ "value": "",_x000D_ "id": "referral_source"_x000D_ },_x000D_ {_x000D_ "label": "UTM Source",_x000D_ "value": "",_x000D_ "id": "utm_source"_x000D_ },_x000D_ {_x000D_ "label": "UTM Medium",_x000D_ "value": "",_x000D_ "id": "utm_medium"_x000D_ },_x000D_ {_x000D_ "label": "UTM Campaign",_x000D_ "value": "",_x000D_ "id": "utm_campaign"_x000D_ },_x000D_ {_x000D_ "label": "UTM Term",_x000D_ "value": "",_x000D_ "id": "utm_term"_x000D_ },_x000D_ {_x000D_ "label": "UTM Content",_x000D_ "value": "",_x000D_ "id": "utm_content"_x000D_ }_x000D_ ]_x000D_ },_x000D_ "legs": [],_x000D_ "touchpoints": null,_x000D_ "last_touch": null,_x000D_ "geo": {_x000D_ "lon": -73.1962,_x000D_ "lat": 41.1854_x000D_ },_x000D_ "timestamp": "0001-01-01T00:00:00"_x000D_ } | E7: 1 | F7: 1 | G7: 1523620 | H7: 1 | I7: 46073.66 | K7: 1770124 | L7: 1 | M7: 922 | N7: 46073.815 | P7: Fox Home Protection Plan | Q7: 1 | R7: 4037656223 | S7: 2 | T7: 2026
A8: 2034170861 | B8: 46073.471 | C8: {_x000D_ "id": 4037301011,_x000D_ "sid": "log-call-no-answer-53677125109bc665",_x000D_ "account_id": 441826,_x000D_ "name": "Shellby Nelson",_x000D_ "cnam": "Shellby Nelson",_x000D_ "search": "",_x000D_ "referrer": "",_x000D_ "visitor_sid": "",_x000D_ "location": "",_x000D_ "source": "Sandbox",_x000D_ "source_id": 1814974,_x000D_ "source_sid": "TSOF6FC2D2594D22C5288F2F91D669A9D5B9BE7FEE3C6EF44F4A9EA1A63913ECD83",_x000D_ "tgid": 5681974,_x000D_ "likelihood": null,_x000D_ "duration": 0,_x000D_ "direction": "form",_x000D_ "talk_time": 0,_x000D_ "ring_time": 0,_x000D_ "hold_time": 0,_x000D_ "wait_time": 0,_x000D_ "parent_id": null,_x000D_ "email": "shellnele@yahoo.com",_x000D_ "street": null,_x000D_ "city": null,_x000D_ "state": null,_x000D_ "country": null,_x000D_ "postal_code": "06801",_x000D_ "called_at": "2026-02-20 05:18 AM -06:00",_x000D_ "unix_time": 1771589923,_x000D_ "tracking_number_id": 3476065,_x000D_ "tracking_number_sid": "TPNC3C4B23C348AEC2EE54EFD301979CD2EFFBA32881B159867D3F4ED59E6F0B56367EFF2993536685F",_x000D_ "tracking_number": "\u002B14352541043",_x000D_ "tracking_label": "Testing Number",_x000D_ "dial_status": "no-answer",_x000D_ "is_new_caller": true,_x000D_ "indexed_at": 1.7715905E+09,_x000D_ "agent_insights": false,_x000D_ "duration_period": {_x000D_ "gte": 1771589923000,_x000D_ "lte": 1771589923000_x000D_ },_x000D_ "inbound_rate_center": {_x000D_ "country": "US",_x000D_ "prefix": "1",_x000D_ "tollfree": false_x000D_ },_x000D_ "business_number": null,_x000D_ "business_label": null,_x000D_ "receiving_number_id": null,_x000D_ "receiving_number_sid": null,_x000D_ "billed_amount": 0,_x000D_ "billed_at": "0001-01-01T00:00:00",_x000D_ "excluded": false,_x000D_ "redacted": false,_x000D_ "tracking_number_format": "(435) 254-1043",_x000D_ "business_number_format": null,_x000D_ "alternative_number": "2034170861",_x000D_ "tracking_number_bare": "4352541043",_x000D_ "caller_number_format": "(203) 417-0861",_x000D_ "caller_number_complete": "\u002B12034170861",_x000D_ "caller_number_bare": "2034170861",_x000D_ "caller_number": "\u002B12034170861",_x000D_ "caller_number_split": [_x000D_ "1",_x000D_ "203",_x000D_ "417",_x000D_ "0861"_x000D_ ],_x000D_ "contact_number": "\u002B12034170861",_x000D_ "visitor": false,_x000D_ "call_path": [_x000D_ {_x000D_ "route_name": "_OnHangup_CallSync",_x000D_ "route_id": "640990",_x000D_ "route_type": "RoutingRule",_x000D_ "started_at": "2026-02-20T05:18:45Z"_x000D_ }_x000D_ ],_x000D_ "left_talk_time": 0,_x000D_ "right_talk_time": 0,_x000D_ "transfers": [],_x000D_ "call_status": "completed",_x000D_ "status": "completed",_x000D_ "spotted": [],_x000D_ "salesforce": {},_x000D_ "audio": null,_x000D_ "is_s3_link": false,_x000D_ "callbacks": [],_x000D_ "emails": [],_x000D_ "day": "Friday",_x000D_ "month": "February",_x000D_ "hour": "05AM",_x000D_ "paid": {_x000D_ "source": null,_x000D_ "medium": null_x000D_ },_x000D_ "ga": {_x000D_ "cid": "441826.4037301011",_x000D_ "ga4": []_x000D_ },_x000D_ "tag_list": [],_x000D_ "latitude": 41.3953,_x000D_ "longitude": -73.4549,_x000D_ "extended_lookup_on": true,_x000D_ "form": {_x000D_ "number_to_call": "log-call-no-answer-61fccda2e3f44d9b",_x000D_ "customer_number_to_dial": "\u002B12034170861",_x000D_ "name": "Shellby Nelson",_x000D_ "email": "shellnele@yahoo.com",_x000D_ "trackback_id": "trackback-441826.1771589923.9501972",_x000D_ "form_id": 213071,_x000D_ "form_name": "Contact Us",_x000D_ "custom": [_x000D_ {_x000D_ "label": "Referral Source",_x000D_ "value": "",_x000D_ "id": "referral_source"_x000D_ },_x000D_ {_x000D_ "label": "UTM Source",_x000D_ "value": "",_x000D_ "id": "utm_source"_x000D_ },_x000D_ {_x000D_ "label": "UTM Medium",_x000D_ "value": "",_x000D_ "id": "utm_medium"_x000D_ },_x000D_ {_x000D_ "label": "UTM Campaign",_x000D_ "value": "",_x000D_ "id": "utm_campaign"_x000D_ },_x000D_ {_x000D_ "label": "UTM Term",_x000D_ "value": "",_x000D_ "id": "utm_term"_x000D_ },_x000D_ {_x000D_ "label": "UTM Content",_x000D_ "value": "",_x000D_ "id": "utm_content"_x000D_ }_x000D_ ]_x000D_ },_x000D_ "legs": [],_x000D_ "touchpoints": null,_x000D_ "last_touch": null,_x000D_ "geo": {_x000D_ "lon": -73.4549,_x000D_ "lat": 41.3953_x000D_ },_x000D_ "timestamp": "0001-01-01T00:00:00"_x000D_ } | E8: 0 | F8: 1 | Q8: 0 | R8: 4037301011 | S8: 2 | T8: 2026
A9: 2037672791 | B9: 46072.642 | C9: {_x000D_ "id": 4035180260,_x000D_ "sid": "log-call-no-answer-eab917ad5defb933",_x000D_ "account_id": 441826,_x000D_ "name": "Stephanie Spinetti",_x000D_ "cnam": "Stephanie Spinetti",_x000D_ "search": "",_x000D_ "referrer": "",_x000D_ "visitor_sid": "",_x000D_ "location": "",_x000D_ "source": "Sandbox",_x000D_ "source_id": 1814974,_x000D_ "source_sid": "TSOF6FC2D2594D22C5288F2F91D669A9D5B9BE7FEE3C6EF44F4A9EA1A63913ECD83",_x000D_ "tgid": 5681974,_x000D_ "likelihood": null,_x000D_ "duration": 0,_x000D_ "direction": "form",_x000D_ "talk_time": 0,_x000D_ "ring_time": 0,_x000D_ "hold_time": 0,_x000D_ "wait_time": 0,_x000D_ "parent_id": null,_x000D_ "email": "stephanie.spinetti@gmail.com",_x000D_ "street": null,_x000D_ "city": null,_x000D_ "state": null,_x000D_ "country": null,_x000D_ "postal_code": "06601",_x000D_ "called_at": "2026-02-19 09:24 AM -06:00",_x000D_ "unix_time": 1771518247,_x000D_ "tracking_number_id": 3476065,_x000D_ "tracking_number_sid": "TPNC3C4B23C348AEC2EE54EFD301979CD2EFFBA32881B159867D3F4ED59E6F0B56367EFF2993536685F",_x000D_ "tracking_number": "\u002B14352541043",_x000D_ "tracking_label": "Testing Number",_x000D_ "dial_status": "no-answer",_x000D_ "is_new_caller": true,_x000D_ "indexed_at": 1.7715188E+09,_x000D_ "agent_insights": false,_x000D_ "duration_period": {_x000D_ "gte": 1771518247000,_x000D_ "lte": 1771518247000_x000D_ },_x000D_ "inbound_rate_center": {_x000D_ "country": "US",_x000D_ "prefix": "1",_x000D_ "tollfree": false_x000D_ },_x000D_ "business_number": null,_x000D_ "business_label": null,_x000D_ "receiving_number_id": null,_x000D_ "receiving_number_sid": null,_x000D_ "billed_amount": 0,_x000D_ "billed_at": "0001-01-01T00:00:00",_x000D_ "excluded": false,_x000D_ "redacted": false,_x000D_ "tracking_number_format": "(435) 254-1043",_x000D_ "business_number_format": null,_x000D_ "alternative_number": "2037672791",_x000D_ "tracking_number_bare": "4352541043",_x000D_ "caller_number_format": "(203) 767-2791",_x000D_ "caller_number_complete": "\u002B12037672791",_x000D_ "caller_number_bare": "2037672791",_x000D_ "caller_number": "\u002B12037672791",_x000D_ "caller_number_split": [_x000D_ "1",_x000D_ "203",_x000D_ "767",_x000D_ "2791"_x000D_ ],_x000D_ "contact_number": "\u002B12037672791",_x000D_ "visitor": false,_x000D_ "call_path": [_x000D_ {_x000D_ "route_name": "_OnHangup_CallSync",_x000D_ "route_id": "640990",_x000D_ "route_type": "RoutingRule",_x000D_ "started_at": "2026-02-19T09:24:08Z"_x000D_ }_x000D_ ],_x000D_ "left_talk_time": 0,_x000D_ "right_talk_time": 0,_x000D_ "transfers": [],_x000D_ "call_status": "completed",_x000D_ "status": "completed",_x000D_ "spotted": [],_x000D_ "salesforce": {},_x000D_ "audio": null,_x000D_ "is_s3_link": false,_x000D_ "callbacks": [],_x000D_ "emails": [],_x000D_ "day": "Thursday",_x000D_ "month": "February",_x000D_ "hour": "09AM",_x000D_ "paid": {_x000D_ "source": null,_x000D_ "medium": null_x000D_ },_x000D_ "ga": {_x000D_ "cid": "441826.4035180260",_x000D_ "ga4": []_x000D_ },_x000D_ "tag_list": [],_x000D_ "latitude": 41.1854,_x000D_ "longitude": -73.1962,_x000D_ "extended_lookup_on": true,_x000D_ "form": {_x000D_ "number_to_call": "log-call-no-answer-d517d295cda62feb",_x000D_ "customer_number_to_dial": "\u002B12037672791",_x000D_ "name": "Stephanie Spinetti",_x000D_ "email": "stephanie.spinetti@gmail.com",_x000D_ "trackback_id": "trackback-441826.1771518247.7941082",_x000D_ "form_id": 213071,_x000D_ "form_name": "Contact Us",_x000D_ "custom": [_x000D_ {_x000D_ "label": "Referral Source",_x000D_ "value": "",_x000D_ "id": "referral_source"_x000D_ },_x000D_ {_x000D_ "label": "UTM Source",_x000D_ "value": "",_x000D_ "id": "utm_source"_x000D_ },_x000D_ {_x000D_ "label": "UTM Medium",_x000D_ "value": "",_x000D_ "id": "utm_medium"_x000D_ },_x000D_ {_x000D_ "label": "UTM Campaign",_x000D_ "value": "",_x000D_ "id": "utm_campaign"_x000D_ },_x000D_ {_x000D_ "label": "UTM Term",_x000D_ "value": "",_x000D_ "id": "utm_term"_x000D_ },_x000D_ {_x000D_ "label": "UTM Content",_x000D_ "value": "",_x000D_ "id": "utm_content"_x000D_ }_x000D_ ]_x000D_ },_x000D_ "legs": [],_x000D_ "touchpoints": null,_x000D_ "last_touch": null,_x000D_ "geo": {_x000D_ "lon": -73.1962,_x000D_ "lat": 41.1854_x000D_ },_x000D_ "timestamp": "0001-01-01T00:00:00"_x000D_ } | E9: 0 | F9: 1 | G9: 1505326 | H9: 1 | I9: 45922.523 | K9: 1720068 | L9: 1 | M9: 773 | N9: 45922.523 | P9: Fox Home Protection Plan | Q9: 0 | R9: 4035180260 | S9: 2 | T9: 2026
A10: 2039215879 | B10: 46072.669 | C10: {_x000D_ "id": 4035349166,_x000D_ "sid": "log-call-no-answer-4789af6beac2f623",_x000D_ "account_id": 441826,_x000D_ "name": "Katie Cingari",_x000D_ "cnam": "Katie Cingari",_x000D_ "search": "",_x000D_ "referrer": "",_x000D_ "visitor_sid": "",_x000D_ "location": "",_x000D_ "source": "Sandbox",_x000D_ "source_id": 1814974,_x000D_ "source_sid": "TSOF6FC2D2594D22C5288F2F91D669A9D5B9BE7FEE3C6EF44F4A9EA1A63913ECD83",_x000D_ "tgid": 5681974,_x000D_ "likelihood": null,_x000D_ "duration": 0,_x000D_ "direction": "form",_x000D_ "talk_time": 0,_x000D_ "ring_time": 0,_x000D_ "hold_time": 0,_x000D_ "wait_time": 0,_x000D_ "parent_id": null,_x000D_ "email": "katie.cingari@gmail.com",_x000D_ "street": null,_x000D_ "city": null,_x000D_ "state": null,_x000D_ "country": null,_x000D_ "postal_code": "06901",_x000D_ "called_at": "2026-02-19 10:03 AM -06:00",_x000D_ "unix_time": 1771520611,_x000D_ "tracking_number_id": 3476065,_x000D_ "tracking_number_sid": "TPNC3C4B23C348AEC2EE54EFD301979CD2EFFBA32881B159867D3F4ED59E6F0B56367EFF2993536685F",_x000D_ "tracking_number": "\u002B14352541043",_x000D_ "tracking_label": "Testing Number",_x000D_ "dial_status": "no-answer",_x000D_ "is_new_caller": true,_x000D_ "indexed_at": 1.7715212E+09,_x000D_ "agent_insights": false,_x000D_ "duration_period": {_x000D_ "gte": 1771520611000,_x000D_ "lte": 1771520611000_x000D_ },_x000D_ "inbound_rate_center": {_x000D_ "country": "US",_x000D_ "prefix": "1",_x000D_ "tollfree": false_x000D_ },_x000D_ "business_number": null,_x000D_ "business_label": null,_x000D_ "receiving_number_id": null,_x000D_ "receiving_number_sid": null,_x000D_ "billed_amount": 0,_x000D_ "billed_at": "0001-01-01T00:00:00",_x000D_ "excluded": false,_x000D_ "redacted": false,_x000D_ "tracking_number_format": "(435) 254-1043",_x000D_ "business_number_format": null,_x000D_ "alternative_number": "2039215879",_x000D_ "tracking_number_bare": "4352541043",_x000D_ "caller_number_format": "(203) 921-5879",_x000D_ "caller_number_complete": "\u002B12039215879",_x000D_ "caller_number_bare": "2039215879",_x000D_ "caller_number": "\u002B12039215879",_x000D_ "caller_number_split": [_x000D_ "1",_x000D_ "203",_x000D_ "921",_x000D_ "5879"_x000D_ ],_x000D_ "contact_number": "\u002B12039215879",_x000D_ "visitor": false,_x000D_ "call_path": [_x000D_ {_x000D_ "route_name": "_OnHangup_CallSync",_x000D_ "route_id": "640990",_x000D_ "route_type": "RoutingRule",_x000D_ "started_at": "2026-02-19T10:03:33Z"_x000D_ }_x000D_ ],_x000D_ "left_talk_time": 0,_x000D_ "right_talk_time": 0,_x000D_ "transfers": [],_x000D_ "call_status": "completed",_x000D_ "status": "completed",_x000D_ "spotted": [],_x000D_ "salesforce": {},_x000D_ "audio": null,_x000D_ "is_s3_link": false,_x000D_ "callbacks": [],_x000D_ "emails": [],_x000D_ "day": "Thursday",_x000D_ "month": "February",_x000D_ "hour": "10AM",_x000D_ "paid": {_x000D_ "source": null,_x000D_ "medium": null_x000D_ },_x000D_ "ga": {_x000D_ "cid": "441826.4035349166",_x000D_ "ga4": []_x000D_ },_x000D_ "tag_list": [],_x000D_ "latitude": 41.0529,_x000D_ "longitude": -73.5375,_x000D_ "extended_lookup_on": true,_x000D_ "form": {_x000D_ "number_to_call": "log-call-no-answer-96669d4871939d13",_x000D_ "customer_number_to_dial": "\u002B12039215879",_x000D_ "name": "Katie Cingari",_x000D_ "email": "katie.cingari@gmail.com",_x000D_ "trackback_id": "trackback-441826.1771520611.7475693",_x000D_ "form_id": 213071,_x000D_ "form_name": "Contact Us",_x000D_ "custom": [_x000D_ {_x000D_ "label": "Referral Source",_x000D_ "value": "",_x000D_ "id": "referral_source"_x000D_ },_x000D_ {_x000D_ "label": "UTM Source",_x000D_ "value": "",_x000D_ "id": "utm_source"_x000D_ },_x000D_ {_x000D_ "label": "UTM Medium",_x000D_ "value": "",_x000D_ "id": "utm_medium"_x000D_ },_x000D_ {_x000D_ "label": "UTM Campaign",_x000D_ "value": "",_x000D_ "id": "utm_campaign"_x000D_ },_x000D_ {_x000D_ "label": "UTM Term",_x000D_ "value": "",_x000D_ "id": "utm_term"_x000D_ },_x000D_ {_x000D_ "label": "UTM Content",_x000D_ "value": "",_x000D_ "id": "utm_content"_x000D_ }_x000D_ ]_x000D_ },_x000D_ "legs": [],_x000D_ "touchpoints": null,_x000D_ "last_touch": null,_x000D_ "geo": {_x000D_ "lon": -73.5375,_x000D_ "lat": 41.0529_x000D_ },_x000D_ "timestamp": "0001-01-01T00:00:00"_x000D_ } | E10: 0 | F10: 1 | G10: 1364243 | H10: 1 | I10: 45776.536 | K10: 1529412 | L10: 1 | M10: 998 | N10: 45776.536 | P10: Fox Home Protection Plan | Q10: 0 | R10: 4035349166 | S10: 2 | T10: 2026
A11: 2072056930 | B11: 46072.103 | C11: {_x000D_ "id": 4034476589,_x000D_ "sid": "log-call-no-answer-2ae19e31f0028e67",_x000D_ "account_id": 441826,_x000D_ "name": "Quinn Cardale",_x000D_ "cnam": "Quinn Cardale",_x000D_ "search": "",_x000D_ "referrer": "",_x000D_ "visitor_sid": "",_x000D_ "location": "",_x000D_ "source": "Sandbox",_x000D_ "source_id": 1814974,_x000D_ "source_sid": "TSOF6FC2D2594D22C5288F2F91D669A9D5B9BE7FEE3C6EF44F4A9EA1A63913ECD83",_x000D_ "tgid": 5681974,_x000D_ "likelihood": null,_x000D_ "duration": 0,_x000D_ "direction": "form",_x000D_ "talk_time": 0,_x000D_ "ring_time": 0,_x000D_ "hold_time": 0,_x000D_ "wait_time": 0,_x000D_ "parent_id": null,_x000D_ "email": "quentinbcardale@icloud.com",_x000D_ "street": null,_x000D_ "city": null,_x000D_ "state": null,_x000D_ "country": null,_x000D_ "postal_code": "04005",_x000D_ "called_at": "2026-02-18 08:29 PM -06:00",_x000D_ "unix_time": 1771471786,_x000D_ "tracking_number_id": 3476065,_x000D_ "tracking_number_sid": "TPNC3C4B23C348AEC2EE54EFD301979CD2EFFBA32881B159867D3F4ED59E6F0B56367EFF2993536685F",_x000D_ "tracking_number": "\u002B14352541043",_x000D_ "tracking_label": "Testing Number",_x000D_ "dial_status": "no-answer",_x000D_ "is_new_caller": true,_x000D_ "indexed_at": 1.7714724E+09,_x000D_ "agent_insights": false,_x000D_ "duration_period": {_x000D_ "gte": 1771471786000,_x000D_ "lte": 1771471786000_x000D_ },_x000D_ "inbound_rate_center": {_x000D_ "country": "US",_x000D_ "prefix": "1",_x000D_ "tollfree": false_x000D_ },_x000D_ "business_number": null,_x000D_ "business_label": null,_x000D_ "receiving_number_id": null,_x000D_ "receiving_number_sid": null,_x000D_ "billed_amount": 0,_x000D_ "billed_at": "0001-01-01T00:00:00",_x000D_ "excluded": false,_x000D_ "redacted": false,_x000D_ "tracking_number_format": "(435) 254-1043",_x000D_ "business_number_format": null,_x000D_ "alternative_number": "2072056930",_x000D_ "tracking_number_bare": "4352541043",_x000D_ "caller_number_format": "(207) 205-6930",_x000D_ "caller_number_complete": "\u002B12072056930",_x000D_ "caller_number_bare": "2072056930",_x000D_ "caller_number": "\u002B12072056930",_x000D_ "caller_number_split": [_x000D_ "1",_x000D_ "207",_x000D_ "205",_x000D_ "6930"_x000D_ ],_x000D_ "contact_number": "\u002B12072056930",_x000D_ "visitor": false,_x000D_ "call_path": [_x000D_ {_x000D_ "route_name": "_OnHangup_CallSync",_x000D_ "route_id": "640990",_x000D_ "route_type": "RoutingRule",_x000D_ "started_at": "2026-02-18T20:29:47Z"_x000D_ }_x000D_ ],_x000D_ "left_talk_time": 0,_x000D_ "right_talk_time": 0,_x000D_ "transfers": [],_x000D_ "call_status": "completed",_x000D_ "status": "completed",_x000D_ "spotted": [],_x000D_ "salesforce": {},_x000D_ "audio": null,_x000D_ "is_s3_link": false,_x000D_ "callbacks": [],_x000D_ "emails": [],_x000D_ "day": "Wednesday",_x000D_ "month": "February",_x000D_ "hour": "08PM",_x000D_ "paid": {_x000D_ "source": null,_x000D_ "medium": null_x000D_ },_x000D_ "ga": {_x000D_ "cid": "441826.4034476589",_x000D_ "ga4": []_x000D_ },_x000D_ "tag_list": [],_x000D_ "latitude": 43.494,_x000D_ "longitude": -70.4594,_x000D_ "extended_lookup_on": true,_x000D_ "form": {_x000D_ "number_to_call": "log-call-no-answer-6ee4b4744bc16bdc",_x000D_ "customer_number_to_dial": "\u002B12072056930",_x000D_ "name": "Quinn Cardale",_x000D_ "email": "quentinbcardale@icloud.com",_x000D_ "trackback_id": "trackback-441826.1771471786.39154",_x000D_ "form_id": 213071,_x000D_ "form_name": "Contact Us",_x000D_ "custom": [_x000D_ {_x000D_ "label": "Referral Source",_x000D_ "value": "",_x000D_ "id": "referral_source"_x000D_ },_x000D_ {_x000D_ "label": "UTM Source",_x000D_ "value": "",_x000D_ "id": "utm_source"_x000D_ },_x000D_ {_x000D_ "label": "UTM Medium",_x000D_ "value": "",_x000D_ "id": "utm_medium"_x000D_ },_x000D_ {_x000D_ "label": "UTM Campaign",_x000D_ "value": "",_x000D_ "id": "utm_campaign"_x000D_ },_x000D_ {_x000D_ "label": "UTM Term",_x000D_ "value": "",_x000D_ "id": "utm_term"_x000D_ },_x000D_ {_x000D_ "label": "UTM Content",_x000D_ "value": "",_x000D_ "id": "utm_content"_x000D_ }_x000D_ ]_x000D_ },_x000D_ "legs": [],_x000D_ "touchpoints": null,_x000D_ "last_touch": null,_x000D_ "geo": {_x000D_ "lon": -70.4594,_x000D_ "lat": 43.494_x000D_ },_x000D_ "timestamp": "0001-01-01T00:00:00"_x000D_ } | E11: 1 | F11: 1 | G11: 1523517 | H11: 1 | I11: 46072.814 | K11: 1769803 | L11: 1 | M11: 996 | N11: 46072.814 | P11: Fox Home Protection Plan | Q11: 1 | R11: 4034476589 | S11: 2 | T11: 2026
A12: 2073754558 | B12: 46073.701 | C12: {_x000D_ "id": 4038213596,_x000D_ "sid": "log-call-no-answer-881e1159a979bb6c",_x000D_ "account_id": 441826,_x000D_ "name": "DEBORAH Meroff",_x000D_ "cnam": "DEBORAH Meroff",_x000D_ "search": "",_x000D_ "referrer": "",_x000D_ "visitor_sid": "",_x000D_ "location": "",_x000D_ "source": "Sandbox",_x000D_ "source_id": 1814974,_x000D_ "source_sid": "TSOF6FC2D2594D22C5288F2F91D669A9D5B9BE7FEE3C6EF44F4A9EA1A63913ECD83",_x000D_ "tgid": 5681974,_x000D_ "likelihood": null,_x000D_ "duration": 0,_x000D_ "direction": "form",_x000D_ "talk_time": 0,_x000D_ "ring_time": 0,_x000D_ "hold_time": 0,_x000D_ "wait_time": 0,_x000D_ "parent_id": null,_x000D_ "email": "mainewrtr48@gmail.com",_x000D_ "street": null,_x000D_ "city": "Sabattus",_x000D_ "state": "ME",_x000D_ "country": null,_x000D_ "postal_code": "04280",_x000D_ "called_at": "2026-02-20 10:50 AM -06:00",_x000D_ "unix_time": 1771609820,_x000D_ "tracking_number_id": 3476065,_x000D_ "tracking_number_sid": "TPNC3C4B23C348AEC2EE54EFD301979CD2EFFBA32881B159867D3F4ED59E6F0B56367EFF2993536685F",_x000D_ "tracking_number": "\u002B14352541043",_x000D_ "tracking_label": "Testing Number",_x000D_ "dial_status": "no-answer",_x000D_ "is_new_caller": true,_x000D_ "indexed_at": 1.7716104E+09,_x000D_ "agent_insights": false,_x000D_ "duration_period": {_x000D_ "gte": 1771609820000,_x000D_ "lte": 1771609820000_x000D_ },_x000D_ "inbound_rate_center": {_x000D_ "country": "US",_x000D_ "prefix": "1",_x000D_ "tollfree": false_x000D_ },_x000D_ "business_number": null,_x000D_ "business_label": null,_x000D_ "receiving_number_id": null,_x000D_ "receiving_number_sid": null,_x000D_ "billed_amount": 0,_x000D_ "billed_at": "0001-01-01T00:00:00",_x000D_ "excluded": false,_x000D_ "redacted": false,_x000D_ "tracking_number_format": "(435) 254-1043",_x000D_ "business_number_format": null,_x000D_ "alternative_number": "2073754558",_x000D_ "tracking_number_bare": "4352541043",_x000D_ "caller_number_format": "(207) 375-4558",_x000D_ "caller_number_complete": "\u002B12073754558",_x000D_ "caller_number_bare": "2073754558",_x000D_ "caller_number": "\u002B12073754558",_x000D_ "caller_number_split": [_x000D_ "1",_x000D_ "207",_x000D_ "375",_x000D_ "4558"_x000D_ ],_x000D_ "contact_number": "\u002B12073754558",_x000D_ "visitor": false,_x000D_ "call_path": [_x000D_ {_x000D_ "route_name": "_OnHangup_CallSync",_x000D_ "route_id": "640990",_x000D_ "route_type": "RoutingRule",_x000D_ "started_at": "2026-02-20T10:50:21Z"_x000D_ }_x000D_ ],_x000D_ "left_talk_time": 0,_x000D_ "right_talk_time": 0,_x000D_ "transfers": [],_x000D_ "call_status": "completed",_x000D_ "status": "completed",_x000D_ "spotted": [],_x000D_ "salesforce": {},_x000D_ "audio": null,_x000D_ "is_s3_link": false,_x000D_ "callbacks": [],_x000D_ "emails": [],_x000D_ "day": "Friday",_x000D_ "month": "February",_x000D_ "hour": "10AM",_x000D_ "paid": {_x000D_ "source": null,_x000D_ "medium": null_x000D_ },_x000D_ "ga": {_x000D_ "cid": "441826.4038213596",_x000D_ "ga4": []_x000D_ },_x000D_ "tag_list": [],_x000D_ "latitude": 44.1186,_x000D_ "longitude": -70.1062,_x000D_ "extended_lookup_on": true,_x000D_ "form": {_x000D_ "number_to_call": "log-call-no-answer-245efee4b3374c59",_x000D_ "customer_number_to_dial": "\u002B12073754558",_x000D_ "name": "DEBORAH Meroff",_x000D_ "email": "mainewrtr48@gmail.com",_x000D_ "trackback_id": "trackback-441826.1771609820.4256136",_x000D_ "form_id": 213071,_x000D_ "form_name": "Contact Us",_x000D_ "custom": [_x000D_ {_x000D_ "label": "Referral Source",_x000D_ "value": "",_x000D_ "id": "referral_source"_x000D_ },_x000D_ {_x000D_ "label": "UTM Source",_x000D_ "value": "",_x000D_ "id": "utm_source"_x000D_ },_x000D_ {_x000D_ "label": "UTM Medium",_x000D_ "value": "",_x000D_ "id": "utm_medium"_x000D_ },_x000D_ {_x000D_ "label": "UTM Campaign",_x000D_ "value": "",_x000D_ "id": "utm_campaign"_x000D_ },_x000D_ {_x000D_ "label": "UTM Term",_x000D_ "value": "",_x000D_ "id": "utm_term"_x000D_ },_x000D_ {_x000D_ "label": "UTM Content",_x000D_ "value": "",_x000D_ "id": "utm_content"_x000D_ }_x000D_ ]_x000D_ },_x000D_ "legs": [],_x000D_ "touchpoints": null,_x000D_ "last_touch": null,_x000D_ "geo": {_x000D_ "lon": -70.1062,_x000D_ "lat": 44.1186_x000D_ },_x000D_ "timestamp": "0001-01-01T00:00:00"_x000D_ } | E12: 0 | F12: 1 | G12: 1473005 | H12: 1 | I12: 45871.708 | K12: 1673489 | L12: 1 | M12: 759 | N12: 45871.715 | P12: Fox Home Protection Plan | Q12: 0 | R12: 4038213596 | S12: 2 | T12: 2026
A13: 2076498302 | B13: 46074.877 | C13: {_x000D_ "id": 4040306234,_x000D_ "sid": "log-call-no-answer-b2366cfc032426ed",_x000D_ "account_id": 441826,_x000D_ "name": "Sierra Linnell",_x000D_ "cnam": "Sierra Linnell",_x000D_ "search": "",_x000D_ "referrer": "",_x000D_ "visitor_sid": "",_x000D_ "location": "",_x000D_ "source": "Sandbox",_x000D_ "source_id": 1814974,_x000D_ "source_sid": "TSOF6FC2D2594D22C5288F2F91D669A9D5B9BE7FEE3C6EF44F4A9EA1A63913ECD83",_x000D_ "tgid": 5681974,_x000D_ "likelihood": null,_x000D_ "duration": 0,_x000D_ "direction": "form",_x000D_ "talk_time": 0,_x000D_ "ring_time": 0,_x000D_ "hold_time": 0,_x000D_ "wait_time": 0,_x000D_ "parent_id": null,_x000D_ "email": "sierradawn201494@gmail.com",_x000D_ "street": null,_x000D_ "city": null,_x000D_ "state": null,_x000D_ "country": null,_x000D_ "postal_code": "04901",_x000D_ "called_at": "2026-02-21 03:03 PM -06:00",_x000D_ "unix_time": 1771711383,_x000D_ "tracking_number_id": 3476065,_x000D_ "tracking_number_sid": "TPNC3C4B23C348AEC2EE54EFD301979CD2EFFBA32881B159867D3F4ED59E6F0B56367EFF2993536685F",_x000D_ "tracking_number": "\u002B14352541043",_x000D_ "tracking_label": "Testing Number",_x000D_ "dial_status": "no-answer",_x000D_ "is_new_caller": true,_x000D_ "indexed_at": 1.771712E+09,_x000D_ "agent_insights": false,_x000D_ "duration_period": {_x000D_ "gte": 1771711383000,_x000D_ "lte": 1771711383000_x000D_ },_x000D_ "inbound_rate_center": {_x000D_ "country": "US",_x000D_ "prefix": "1",_x000D_ "tollfree": false_x000D_ },_x000D_ "business_number": null,_x000D_ "business_label": null,_x000D_ "receiving_number_id": null,_x000D_ "receiving_number_sid": null,_x000D_ "billed_amount": 0,_x000D_ "billed_at": "0001-01-01T00:00:00",_x000D_ "excluded": false,_x000D_ "redacted": false,_x000D_ "tracking_number_format": "(435) 254-1043",_x000D_ "business_number_format": null,_x000D_ "alternative_number": "2076498302",_x000D_ "tracking_number_bare": "4352541043",_x000D_ "caller_number_format": "(207) 649-8302",_x000D_ "caller_number_complete": "\u002B12076498302",_x000D_ "caller_number_bare": "2076498302",_x000D_ "caller_number": "\u002B12076498302",_x000D_ "caller_number_split": [_x000D_ "1",_x000D_ "207",_x000D_ "649",_x000D_ "8302"_x000D_ ],_x000D_ "contact_number": "\u002B12076498302",_x000D_ "visitor": false,_x000D_ "call_path": [_x000D_ {_x000D_ "route_name": "_OnHangup_CallSync",_x000D_ "route_id": "640990",_x000D_ "route_type": "RoutingRule",_x000D_ "started_at": "2026-02-21T15:03:04Z"_x000D_ }_x000D_ ],_x000D_ "left_talk_time": 0,_x000D_ "right_talk_time": 0,_x000D_ "transfers": [],_x000D_ "call_status": "completed",_x000D_ "status": "completed",_x000D_ "spotted": [],_x000D_ "salesforce": {},_x000D_ "audio": null,_x000D_ "is_s3_link": false,_x000D_ "callbacks": [],_x000D_ "emails": [],_x000D_ "day": "Saturday",_x000D_ "month": "February",_x000D_ "hour": "03PM",_x000D_ "paid": {_x000D_ "source": null,_x000D_ "medium": null_x000D_ },_x000D_ "ga": {_x000D_ "cid": "441826.4040306234",_x000D_ "ga4": []_x000D_ },_x000D_ "tag_list": [],_x000D_ "latitude": 44.5528,_x000D_ "longitude": -69.63,_x000D_ "extended_lookup_on": true,_x000D_ "form": {_x000D_ "number_to_call": "log-call-no-answer-c372eaf35cdccafa",_x000D_ "customer_number_to_dial": "\u002B12076498302",_x000D_ "name": "Sierra Linnell",_x000D_ "email": "sierradawn201494@gmail.com",_x000D_ "trackback_id": "trackback-441826.1771711383.3176322",_x000D_ "form_id": 213071,_x000D_ "form_name": "Contact Us",_x000D_ "custom": [_x000D_ {_x000D_ "label": "Referral Source",_x000D_ "value": "",_x000D_ "id": "referral_source"_x000D_ },_x000D_ {_x000D_ "label": "UTM Source",_x000D_ "value": "",_x000D_ "id": "utm_source"_x000D_ },_x000D_ {_x000D_ "label": "UTM Medium",_x000D_ "value": "",_x000D_ "id": "utm_medium"_x000D_ },_x000D_ {_x000D_ "label": "UTM Campaign",_x000D_ "value": "",_x000D_ "id": "utm_campaign"_x000D_ },_x000D_ {_x000D_ "label": "UTM Term",_x000D_ "value": "",_x000D_ "id": "utm_term"_x000D_ },_x000D_ {_x000D_ "label": "UTM Content",_x000D_ "value": "",_x000D_ "id": "utm_content"_x000D_ }_x000D_ ]_x000D_ },_x000D_ "legs": [],_x000D_ "touchpoints": null,_x000D_ "last_touch": null,_x000D_ "geo": {_x000D_ "lon": -69.63,_x000D_ "lat": 44.5528_x000D_ },_x000D_ "timestamp": "0001-01-01T00:00:00"_x000D_ } | E13: 0 | F13: 1 | G13: 1523780 | I13: 46076.612 | J13: 1775221076000 | Q13: 0 | R13: 4040306234 | S13: 2 | T13: 2026
A14: 2077981641 | B14: 46077.817 | C14: {_x000D_ "id": 4045790387,_x000D_ "sid": "log-call-no-answer-4984fd5fe715718a",_x000D_ "account_id": 441826,_x000D_ "name": "Carreyann Koch",_x000D_ "cnam": "Carreyann Koch",_x000D_ "search": "",_x000D_ "referrer": "",_x000D_ "visitor_sid": "",_x000D_ "location": "",_x000D_ "source": "Sandbox",_x000D_ "source_id": 1814974,_x000D_ "source_sid": "TSOF6FC2D2594D22C5288F2F91D669A9D5B9BE7FEE3C6EF44F4A9EA1A63913ECD83",_x000D_ "tgid": 5681974,_x000D_ "likelihood": null,_x000D_ "duration": 0,_x000D_ "direction": "form",_x000D_ "talk_time": 0,_x000D_ "ring_time": 0,_x000D_ "hold_time": 0,_x000D_ "wait_time": 0,_x000D_ "parent_id": null,_x000D_ "email": "cncthurlow@yahoo.com",_x000D_ "street": null,_x000D_ "city": null,_x000D_ "state": null,_x000D_ "country": null,_x000D_ "postal_code": "04011",_x000D_ "called_at": "2026-02-24 01:36 PM -06:00",_x000D_ "unix_time": 1771965375,_x000D_ "tracking_number_id": 3476065,_x000D_ "tracking_number_sid": "TPNC3C4B23C348AEC2EE54EFD301979CD2EFFBA32881B159867D3F4ED59E6F0B56367EFF2993536685F",_x000D_ "tracking_number": "\u002B14352541043",_x000D_ "tracking_label": "Testing Number",_x000D_ "dial_status": "no-answer",_x000D_ "is_new_caller": true,_x000D_ "indexed_at": 1.771966E+09,_x000D_ "agent_insights": false,_x000D_ "duration_period": {_x000D_ "gte": 1771965375000,_x000D_ "lte": 1771965375000_x000D_ },_x000D_ "inbound_rate_center": {_x000D_ "country": "US",_x000D_ "prefix": "1",_x000D_ "tollfree": false_x000D_ },_x000D_ "business_number": null,_x000D_ "business_label": null,_x000D_ "receiving_number_id": null,_x000D_ "receiving_number_sid": null,_x000D_ "billed_amount": 0,_x000D_ "billed_at": "0001-01-01T00:00:00",_x000D_ "excluded": false,_x000D_ "redacted": false,_x000D_ "tracking_number_format": "(435) 254-1043",_x000D_ "business_number_format": null,_x000D_ "alternative_number": "2077981641",_x000D_ "tracking_number_bare": "4352541043",_x000D_ "caller_number_format": "(207) 798-1641",_x000D_ "caller_number_complete": "\u002B12077981641",_x000D_ "caller_number_bare": "2077981641",_x000D_ "caller_number": "\u002B12077981641",_x000D_ "caller_number_split": [_x000D_ "1",_x000D_ "207",_x000D_ "798",_x000D_ "1641"_x000D_ ],_x000D_ "contact_number": "\u002B12077981641",_x000D_ "visitor": false,_x000D_ "call_path": [_x000D_ {_x000D_ "route_name": "_OnHangup_CallSync",_x000D_ "route_id": "640990",_x000D_ "route_type": "RoutingRule",_x000D_ "started_at": "2026-02-24T13:36:17Z"_x000D_ }_x000D_ ],_x000D_ "left_talk_time": 0,_x000D_ "right_talk_time": 0,_x000D_ "transfers": [],_x000D_ "call_status": "completed",_x000D_ "status": "completed",_x000D_ "spotted": [],_x000D_ "salesforce": {},_x000D_ "audio": null,_x000D_ "is_s3_link": false,_x000D_ "callbacks": [],_x000D_ "emails": [],_x000D_ "day": "Tuesday",_x000D_ "month": "February",_x000D_ "hour": "01PM",_x000D_ "paid": {_x000D_ "source": null,_x000D_ "medium": null_x000D_ },_x000D_ "ga": {_x000D_ "cid": "441826.4045790387",_x000D_ "ga4": []_x000D_ },_x000D_ "tag_list": [],_x000D_ "latitude": 43.9142,_x000D_ "longitude": -69.9643,_x000D_ "extended_lookup_on": true,_x000D_ "form": {_x000D_ "number_to_call": "log-call-no-answer-fbbb58b9152e2e91",_x000D_ "customer_number_to_dial": "\u002B12077981641",_x000D_ "name": "Carreyann Koch",_x000D_ "email": "cncthurlow@yahoo.com",_x000D_ "trackback_id": "trackback-441826.1771965375.714188",_x000D_ "form_id": 213071,_x000D_ "form_name": "Contact Us",_x000D_ "custom": [_x000D_ {_x000D_ "label": "Referral Source",_x000D_ "value": "",_x000D_ "id": "referral_source"_x000D_ },_x000D_ {_x000D_ "label": "UTM Source",_x000D_ "value": "",_x000D_ "id": "utm_source"_x000D_ },_x000D_ {_x000D_ "label": "UTM Medium",_x000D_ "value": "",_x000D_ "id": "utm_medium"_x000D_ },_x000D_ {_x000D_ "label": "UTM Campaign",_x000D_ "value": "",_x000D_ "id": "utm_campaign"_x000D_ },_x000D_ {_x000D_ "label": "UTM Term",_x000D_ "value": "",_x000D_ "id": "utm_term"_x000D_ },_x000D_ {_x000D_ "label": "UTM Content",_x000D_ "value": "",_x000D_ "id": "utm_content"_x000D_ }_x000D_ ]_x000D_ },_x000D_ "legs": [],_x000D_ "touchpoints": null,_x000D_ "last_touch": null,_x000D_ "geo": {_x000D_ "lon": -69.9643,_x000D_ "lat": 43.9142_x000D_ },_x000D_ "timestamp": "0001-01-01T00:00:00"_x000D_ } | E14: 0 | F14: 1 | Q14: 0 | R14: 4045790387 | S14: 2 | T14: 2026
A15: 2085551212 | B15: 46069.329 | C15: {_x000D_ "id": 4026480362,_x000D_ "sid": "log-call-no-answer-7b3f9117919bb3d9",_x000D_ "account_id": 441826,_x000D_ "name": "Test User",_x000D_ "cnam": "Test User",_x000D_ "search": "",_x000D_ "referrer": "",_x000D_ "visitor_sid": "",_x000D_ "location": "",_x000D_ "source": "Sandbox",_x000D_ "source_id": 1814974,_x000D_ "source_sid": "TSOF6FC2D2594D22C5288F2F91D669A9D5B9BE7FEE3C6EF44F4A9EA1A63913ECD83",_x000D_ "tgid": 5681974,_x000D_ "likelihood": null,_x000D_ "duration": 0,_x000D_ "direction": "form",_x000D_ "talk_time": 0,_x000D_ "ring_time": 0,_x000D_ "hold_time": 0,_x000D_ "wait_time": 0,_x000D_ "parent_id": null,_x000D_ "email": "test@example.com",_x000D_ "street": null,_x000D_ "city": "Directory Assistance",_x000D_ "state": "ID",_x000D_ "country": null,_x000D_ "postal_code": null,_x000D_ "called_at": "2026-02-16 01:54 AM -06:00",_x000D_ "unix_time": 1771232097,_x000D_ "tracking_number_id": 3476065,_x000D_ "tracking_number_sid": "TPNC3C4B23C348AEC2EE54EFD301979CD2EFFBA32881B159867D3F4ED59E6F0B56367EFF2993536685F",_x000D_ "tracking_number": "\u002B14352541043",_x000D_ "tracking_label": "Testing Number",_x000D_ "dial_status": "no-answer",_x000D_ "is_new_caller": false,_x000D_ "indexed_at": 1.7712326E+09,_x000D_ "agent_insights": false,_x000D_ "duration_period": {_x000D_ "gte": 1771232097000,_x000D_ "lte": 1771232097000_x000D_ },_x000D_ "inbound_rate_center": {_x000D_ "country": "US",_x000D_ "prefix": "1",_x000D_ "tollfree": false_x000D_ },_x000D_ "business_number": null,_x000D_ "business_label": null,_x000D_ "receiving_number_id": null,_x000D_ "receiving_number_sid": null,_x000D_ "billed_amount": 0,_x000D_ "billed_at": "0001-01-01T00:00:00",_x000D_ "excluded": false,_x000D_ "redacted": false,_x000D_ "tracking_number_format": "(435) 254-1043",_x000D_ "business_number_format": null,_x000D_ "alternative_number": "2085551212",_x000D_ "tracking_number_bare": "4352541043",_x000D_ "caller_number_format": "(208) 555-1212",_x000D_ "caller_number_complete": "\u002B12085551212",_x000D_ "caller_number_bare": "2085551212",_x000D_ "caller_number": "\u002B12085551212",_x000D_ "caller_number_split": [_x000D_ "1",_x000D_ "208",_x000D_ "555",_x000D_ "1212"_x000D_ ],_x000D_ "contact_number": "\u002B12085551212",_x000D_ "visitor": false,_x000D_ "call_path": [_x000D_ {_x000D_ "route_name": "_OnHangup_CallSync",_x000D_ "route_id": "640990",_x000D_ "route_type": "RoutingRule",_x000D_ "started_at": "2026-02-16T01:54:59Z"_x000D_ }_x000D_ ],_x000D_ "left_talk_time": 0,_x000D_ "right_talk_time": 0,_x000D_ "transfers": [],_x000D_ "call_status": "completed",_x000D_ "status": "completed",_x000D_ "spotted": [],_x000D_ "salesforce": {},_x000D_ "audio": null,_x000D_ "is_s3_link": false,_x000D_ "callbacks": [],_x000D_ "emails": [],_x000D_ "day": "Monday",_x000D_ "month": "February",_x000D_ "hour": "01AM",_x000D_ "paid": {_x000D_ "source": null,_x000D_ "medium": null_x000D_ },_x000D_ "ga": {_x000D_ "cid": "441826.4026480362",_x000D_ "ga4": []_x000D_ },_x000D_ "tag_list": [],_x000D_ "latitude": 0,_x000D_ "longitude": 0,_x000D_ "extended_lookup_on": true,_x000D_ "form": {_x000D_ "number_to_call": "log-call-no-answer-7ad09ee09b822b75",_x000D_ "customer_number_to_dial": "\u002B12085551212",_x000D_ "name": "Test User",_x000D_ "email": "test@example.com",_x000D_ "trackback_id": "trackback-441826.1771232097.958191",_x000D_ "form_id": 213071,_x000D_ "form_name": "Contact Us",_x000D_ "custom": [_x000D_ {_x000D_ "label": "referral-source",_x000D_ "value": "",_x000D_ "id": "referralsource"_x000D_ },_x000D_ {_x000D_ "label": "utm_source",_x000D_ "value": "",_x000D_ "id": "utm_source"_x000D_ },_x000D_ {_x000D_ "label": null,_x000D_ "value": "cpc",_x000D_ "id": "utm_medium"_x000D_ },_x000D_ {_x000D_ "label": null,_x000D_ "value": "test",_x000D_ "id": "utm_campaign"_x000D_ },_x000D_ {_x000D_ "label": null,_x000D_ "value": "test",_x000D_ "id": "utm_term"_x000D_ },_x000D_ {_x000D_ "label": null,_x000D_ "value": "test",_x000D_ "id": "utm_content"_x000D_ }_x000D_ ]_x000D_ },_x000D_ "legs": [],_x000D_ "touchpoints": [_x000D_ {_x000D_ "call_id": 4026480362,_x000D_ "time": "2026-02-16T08:54:57Z",_x000D_ "touch_type": "form",_x000D_ "clickid": null,_x000D_ "type": null,_x000D_ "source": "Sandbox",_x000D_ "medium": null,_x000D_ "position": "last",_x000D_ "weight": 100_x000D_ }_x000D_ ],_x000D_ "last_touch": "Sandbox/",_x000D_ "geo": {_x000D_ "lon": 0,_x000D_ "lat": 0_x000D_ },_x000D_ "timestamp": "0001-01-01T00:00:00"_x000D_ } | E15: 0 | F15: 1 | Q15: 0 | R15: 4026480362 | S15: 2 | T15: 2026
A16: 2087182653 | B16: 46071.656 | C16: {_x000D_ "id": 4032590039,_x000D_ "sid": "log-call-no-answer-815507dc0fa9e013",_x000D_ "account_id": 441826,_x000D_ "name": "Mike Price",_x000D_ "cnam": "Mike Price",_x000D_ "search": "",_x000D_ "referrer": "",_x000D_ "visitor_sid": "",_x000D_ "location": "",_x000D_ "source": "Sandbox",_x000D_ "source_id": 1814974,_x000D_ "source_sid": "TSOF6FC2D2594D22C5288F2F91D669A9D5B9BE7FEE3C6EF44F4A9EA1A63913ECD83",_x000D_ "tgid": 5681974,_x000D_ "likelihood": null,_x000D_ "duration": 0,_x000D_ "direction": "form",_x000D_ "talk_time": 0,_x000D_ "ring_time": 0,_x000D_ "hold_time": 0,_x000D_ "wait_time": 0,_x000D_ "parent_id": null,_x000D_ "email": "test@boldelite.com",_x000D_ "street": null,_x000D_ "city": "Weiser",_x000D_ "state": "ID",_x000D_ "country": null,_x000D_ "postal_code": "83672",_x000D_ "called_at": "2026-02-18 09:44 AM -06:00",_x000D_ "unix_time": 1771433062,_x000D_ "tracking_number_id": 3476065,_x000D_ "tracking_number_sid": "TPNC3C4B23C348AEC2EE54EFD301979CD2EFFBA32881B159867D3F4ED59E6F0B56367EFF2993536685F",_x000D_ "tracking_number": "\u002B14352541043",_x000D_ "tracking_label": "Testing Number",_x000D_ "dial_status": "no-answer",_x000D_ "is_new_caller": false,_x000D_ "indexed_at": 1.7714336E+09,_x000D_ "agent_insights": false,_x000D_ "duration_period": {_x000D_ "gte": 1771433062000,_x000D_ "lte": 1771433062000_x000D_ },_x000D_ "inbound_rate_center": {_x000D_ "country": "US",_x000D_ "prefix": "1",_x000D_ "tollfree": false_x000D_ },_x000D_ "business_number": null,_x000D_ "business_label": null,_x000D_ "receiving_number_id": null,_x000D_ "receiving_number_sid": null,_x000D_ "billed_amount": 0,_x000D_ "billed_at": "0001-01-01T00:00:00",_x000D_ "excluded": false,_x000D_ "redacted": false,_x000D_ "tracking_number_format": "(435) 254-1043",_x000D_ "business_number_format": null,_x000D_ "alternative_number": "2087182653",_x000D_ "tracking_number_bare": "4352541043",_x000D_ "caller_number_format": "(208) 718-2653",_x000D_ "caller_number_complete": "\u002B12087182653",_x000D_ "caller_number_bare": "2087182653",_x000D_ "caller_number": "\u002B12087182653",_x000D_ "caller_number_split": [_x000D_ "1",_x000D_ "208",_x000D_ "718",_x000D_ "2653"_x000D_ ],_x000D_ "contact_number": "\u002B12087182653",_x000D_ "visitor": false,_x000D_ "call_path": [_x000D_ {_x000D_ "route_name": "_OnHangup_CallSync",_x000D_ "route_id": "640990",_x000D_ "route_type": "RoutingRule",_x000D_ "started_at": "2026-02-18T09:44:23Z"_x000D_ }_x000D_ ],_x000D_ "left_talk_time": 0,_x000D_ "right_talk_time": 0,_x000D_ "transfers": [],_x000D_ "call_status": "completed",_x000D_ "status": "completed",_x000D_ "spotted": [],_x000D_ "salesforce": {},_x000D_ "audio": null,_x000D_ "is_s3_link": false,_x000D_ "callbacks": [],_x000D_ "emails": [],_x000D_ "day": "Wednesday",_x000D_ "month": "February",_x000D_ "hour": "09AM",_x000D_ "paid": {_x000D_ "source": null,_x000D_ "medium": null_x000D_ },_x000D_ "ga": {_x000D_ "cid": "441826.4032590039",_x000D_ "ga4": []_x000D_ },_x000D_ "tag_list": [],_x000D_ "latitude": 44.2486,_x000D_ "longitude": -116.97,_x000D_ "extended_lookup_on": true,_x000D_ "form": {_x000D_ "number_to_call": "log-call-no-answer-2db57f3807cf8a42",_x000D_ "customer_number_to_dial": "\u002B12087182653",_x000D_ "name": "Mike Price",_x000D_ "email": "test@boldelite.com",_x000D_ "trackback_id": "trackback-441826.1771433062.2579894",_x000D_ "form_id": 213071,_x000D_ "form_name": "Contact Us",_x000D_ "custom": [_x000D_ {_x000D_ "label": "Referral Source",_x000D_ "value": "",_x000D_ "id": "referral_source"_x000D_ },_x000D_ {_x000D_ "label": "UTM Source",_x000D_ "value": "",_x000D_ "id": "utm_source"_x000D_ },_x000D_ {_x000D_ "label": "UTM Medium",_x000D_ "value": "",_x000D_ "id": "utm_medium"_x000D_ },_x000D_ {_x000D_ "label": "UTM Campaign",_x000D_ "value": "",_x000D_ "id": "utm_campaign"_x000D_ },_x000D_ {_x000D_ "label": "UTM Term",_x000D_ "value": "",_x000D_ "id": "utm_term"_x000D_ },_x000D_ {_x000D_ "label": "UTM Content",_x000D_ "value": "",_x000D_ "id": "utm_content"_x000D_ }_x000D_ ]_x000D_ },_x000D_ "legs": [],_x000D_ "touchpoints": [_x000D_ {_x000D_ "call_id": 4032590039,_x000D_ "time": "2026-02-18T16:44:22Z",_x000D_ "touch_type": "form",_x000D_ "clickid": null,_x000D_ "type": null,_x000D_ "source": "Sandbox",_x000D_ "medium": null,_x000D_ "position": "last",_x000D_ "weight": 100_x000D_ }_x000D_ ],_x000D_ "last_touch": "Sandbox/",_x000D_ "geo": {_x000D_ "lon": -116.97,_x000D_ "lat": 44.2486_x000D_ },_x000D_ "timestamp": "0001-01-01T00:00:00"_x000D_ } | E16: 0 | F16: 1 | Q16: 0 | R16: 4032590039 | S16: 2 | T16: 2026
A17: 2173816152 | B17: 46073.112 | C17: {_x000D_ "id": 4037105750,_x000D_ "sid": "log-call-no-answer-b2dc1475021eb5bc",_x000D_ "account_id": 441826,_x000D_ "name": "Jacob Wiltshire",_x000D_ "cnam": "Jacob Wiltshire",_x000D_ "search": "",_x000D_ "referrer": "",_x000D_ "visitor_sid": "",_x000D_ "location": "",_x000D_ "source": "Sandbox",_x000D_ "source_id": 1814974,_x000D_ "source_sid": "TSOF6FC2D2594D22C5288F2F91D669A9D5B9BE7FEE3C6EF44F4A9EA1A63913ECD83",_x000D_ "tgid": 5681974,_x000D_ "likelihood": null,_x000D_ "duration": 0,_x000D_ "direction": "form",_x000D_ "talk_time": 0,_x000D_ "ring_time": 0,_x000D_ "hold_time": 0,_x000D_ "wait_time": 0,_x000D_ "parent_id": null,_x000D_ "email": "belmonteandsons@gmail.com",_x000D_ "street": null,_x000D_ "city": null,_x000D_ "state": null,_x000D_ "country": null,_x000D_ "postal_code": "62677",_x000D_ "called_at": "2026-02-19 08:41 PM -06:00",_x000D_ "unix_time": 1771558878,_x000D_ "tracking_number_id": 3476065,_x000D_ "tracking_number_sid": "TPNC3C4B23C348AEC2EE54EFD301979CD2EFFBA32881B159867D3F4ED59E6F0B56367EFF2993536685F",_x000D_ "tracking_number": "\u002B14352541043",_x000D_ "tracking_label": "Testing Number",_x000D_ "dial_status": "no-answer",_x000D_ "is_new_caller": true,_x000D_ "indexed_at": 1.7715594E+09,_x000D_ "agent_insights": false,_x000D_ "duration_period": {_x000D_ "gte": 1771558878000,_x000D_ "lte": 1771558878000_x000D_ },_x000D_ "inbound_rate_center": {_x000D_ "country": "US",_x000D_ "prefix": "1",_x000D_ "tollfree": false_x000D_ },_x000D_ "business_number": null,_x000D_ "business_label": null,_x000D_ "receiving_number_id": null,_x000D_ "receiving_number_sid": null,_x000D_ "billed_amount": 0,_x000D_ "billed_at": "0001-01-01T00:00:00",_x000D_ "excluded": false,_x000D_ "redacted": false,_x000D_ "tracking_number_format": "(435) 254-1043",_x000D_ "business_number_format": null,_x000D_ "alternative_number": "2173816152",_x000D_ "tracking_number_bare": "4352541043",_x000D_ "caller_number_format": "(217) 381-6152",_x000D_ "caller_number_complete": "\u002B12173816152",_x000D_ "caller_number_bare": "2173816152",_x000D_ "caller_number": "\u002B12173816152",_x000D_ "caller_number_split": [_x000D_ "1",_x000D_ "217",_x000D_ "381",_x000D_ "6152"_x000D_ ],_x000D_ "contact_number": "\u002B12173816152",_x000D_ "visitor": false,_x000D_ "call_path": [_x000D_ {_x000D_ "route_name": "_OnHangup_CallSync",_x000D_ "route_id": "640990",_x000D_ "route_type": "RoutingRule",_x000D_ "started_at": "2026-02-19T20:41:19Z"_x000D_ }_x000D_ ],_x000D_ "left_talk_time": 0,_x000D_ "right_talk_time": 0,_x000D_ "transfers": [],_x000D_ "call_status": "completed",_x000D_ "status": "completed",_x000D_ "spotted": [],_x000D_ "salesforce": {},_x000D_ "audio": null,_x000D_ "is_s3_link": false,_x000D_ "callbacks": [],_x000D_ "emails": [],_x000D_ "day": "Thursday",_x000D_ "month": "February",_x000D_ "hour": "08PM",_x000D_ "paid": {_x000D_ "source": null,_x000D_ "medium": null_x000D_ },_x000D_ "ga": {_x000D_ "cid": "441826.4037105750",_x000D_ "ga4": []_x000D_ },_x000D_ "tag_list": [],_x000D_ "latitude": 39.7867,_x000D_ "longitude": -89.6538,_x000D_ "extended_lookup_on": true,_x000D_ "form": {_x000D_ "number_to_call": "log-call-no-answer-c6ef3268db440001",_x000D_ "customer_number_to_dial": "\u002B12173816152",_x000D_ "name": "Jacob Wiltshire",_x000D_ "email": "belmonteandsons@gmail.com",_x000D_ "trackback_id": "trackback-441826.1771558878.1161532",_x000D_ "form_id": 213071,_x000D_ "form_name": "Contact Us",_x000D_ "custom": [_x000D_ {_x000D_ "label": "Referral Source",_x000D_ "value": "",_x000D_ "id": "referral_source"_x000D_ },_x000D_ {_x000D_ "label": "UTM Source",_x000D_ "value": "",_x000D_ "id": "utm_source"_x000D_ },_x000D_ {_x000D_ "label": "UTM Medium",_x000D_ "value": "",_x000D_ "id": "utm_medium"_x000D_ },_x000D_ {_x000D_ "label": "UTM Campaign",_x000D_ "value": "",_x000D_ "id": "utm_campaign"_x000D_ },_x000D_ {_x000D_ "label": "UTM Term",_x000D_ "value": "",_x000D_ "id": "utm_term"_x000D_ },_x000D_ {_x000D_ "label": "UTM Content",_x000D_ "value": "",_x000D_ "id": "utm_content"_x000D_ }_x000D_ ]_x000D_ },_x000D_ "legs": [],_x000D_ "touchpoints": null,_x000D_ "last_touch": null,_x000D_ "geo": {_x000D_ "lon": -89.6538,_x000D_ "lat": 39.7867_x000D_ },_x000D_ "timestamp": "0001-01-01T00:00:00"_x000D_ } | E17: 0 | F17: 1 | G17: 1528254 | I17: 46101.878 | Q17: 0 | R17: 4037105750 | S17: 2 | T17: 2026
A18: 2173816152 | B18: 46077.712 | C18: {_x000D_ "id": 4045111976,_x000D_ "sid": "log-call-no-answer-897f21be2a1bcb56",_x000D_ "account_id": 441826,_x000D_ "name": "Jacob Wiltshire",_x000D_ "cnam": "Jacob Wiltshire",_x000D_ "search": "",_x000D_ "referrer": "",_x000D_ "visitor_sid": "",_x000D_ "location": "",_x000D_ "source": "Sandbox",_x000D_ "source_id": 1814974,_x000D_ "source_sid": "TSOF6FC2D2594D22C5288F2F91D669A9D5B9BE7FEE3C6EF44F4A9EA1A63913ECD83",_x000D_ "tgid": 5681974,_x000D_ "likelihood": null,_x000D_ "duration": 0,_x000D_ "direction": "form",_x000D_ "talk_time": 0,_x000D_ "ring_time": 0,_x000D_ "hold_time": 0,_x000D_ "wait_time": 0,_x000D_ "parent_id": null,_x000D_ "email": "wiltshirejacob@outlook.com",_x000D_ "street": null,_x000D_ "city": "Springfield",_x000D_ "state": "IL",_x000D_ "country": null,_x000D_ "postal_code": "62677",_x000D_ "called_at": "2026-02-24 11:05 AM -06:00",_x000D_ "unix_time": 1771956308,_x000D_ "tracking_number_id": 3476065,_x000D_ "tracking_number_sid": "TPNC3C4B23C348AEC2EE54EFD301979CD2EFFBA32881B159867D3F4ED59E6F0B56367EFF2993536685F",_x000D_ "tracking_number": "\u002B14352541043",_x000D_ "tracking_label": "Testing Number",_x000D_ "dial_status": "no-answer",_x000D_ "is_new_caller": false,_x000D_ "indexed_at": 1.7719569E+09,_x000D_ "agent_insights": false,_x000D_ "duration_period": {_x000D_ "gte": 1771956308000,_x000D_ "lte": 1771956308000_x000D_ },_x000D_ "inbound_rate_center": {_x000D_ "country": "US",_x000D_ "prefix": "1",_x000D_ "tollfree": false_x000D_ },_x000D_ "business_number": null,_x000D_ "business_label": null,_x000D_ "receiving_number_id": null,_x000D_ "receiving_number_sid": null,_x000D_ "billed_amount": 0,_x000D_ "billed_at": "0001-01-01T00:00:00",_x000D_ "excluded": false,_x000D_ "redacted": false,_x000D_ "tracking_number_format": "(435) 254-1043",_x000D_ "business_number_format": null,_x000D_ "alternative_number": "2173816152",_x000D_ "tracking_number_bare": "4352541043",_x000D_ "caller_number_format": "(217) 381-6152",_x000D_ "caller_number_complete": "\u002B12173816152",_x000D_ "caller_number_bare": "2173816152",_x000D_ "caller_number": "\u002B12173816152",_x000D_ "caller_number_split": [_x000D_ "1",_x000D_ "217",_x000D_ "381",_x000D_ "6152"_x000D_ ],_x000D_ "contact_number": "\u002B12173816152",_x000D_ "visitor": false,_x000D_ "call_path": [_x000D_ {_x000D_ "route_name": "_OnHangup_CallSync",_x000D_ "route_id": "640990",_x000D_ "route_type": "RoutingRule",_x000D_ "started_at": "2026-02-24T11:05:09Z"_x000D_ }_x000D_ ],_x000D_ "left_talk_time": 0,_x000D_ "right_talk_time": 0,_x000D_ "transfers": [],_x000D_ "call_status": "completed",_x000D_ "status": "completed",_x000D_ "spotted": [],_x000D_ "salesforce": {},_x000D_ "audio": null,_x000D_ "is_s3_link": false,_x000D_ "callbacks": [],_x000D_ "emails": [],_x000D_ "day": "Tuesday",_x000D_ "month": "February",_x000D_ "hour": "11AM",_x000D_ "paid": {_x000D_ "source": null,_x000D_ "medium": null_x000D_ },_x000D_ "ga": {_x000D_ "cid": "441826.4045111976",_x000D_ "ga4": []_x000D_ },_x000D_ "tag_list": [],_x000D_ "latitude": 39.7867,_x000D_ "longitude": -89.6538,_x000D_ "extended_lookup_on": true,_x000D_ "form": {_x000D_ "number_to_call": "log-call-no-answer-a1fff8c6e1d70c2b",_x000D_ "customer_number_to_dial": "\u002B12173816152",_x000D_ "name": "Jacob Wiltshire",_x000D_ "email": "wiltshirejacob@outlook.com",_x000D_ "trackback_id": "trackback-441826.1771956307.3007052",_x000D_ "form_id": 213071,_x000D_ "form_name": "Contact Us",_x000D_ "custom": [_x000D_ {_x000D_ "label": "Referral Source",_x000D_ "value": "",_x000D_ "id": "referral_source"_x000D_ },_x000D_ {_x000D_ "label": "UTM Source",_x000D_ "value": "",_x000D_ "id": "utm_source"_x000D_ },_x000D_ {_x000D_ "label": "UTM Medium",_x000D_ "value": "",_x000D_ "id": "utm_medium"_x000D_ },_x000D_ {_x000D_ "label": "UTM Campaign",_x000D_ "value": "",_x000D_ "id": "utm_campaign"_x000D_ },_x000D_ {_x000D_ "label": "UTM Term",_x000D_ "value": "",_x000D_ "id": "utm_term"_x000D_ },_x000D_ {_x000D_ "label": "UTM Content",_x000D_ "value": "",_x000D_ "id": "utm_content"_x000D_ }_x000D_ ]_x000D_ },_x000D_ "legs": [],_x000D_ "touchpoints": null,_x000D_ "last_touch": null,_x000D_ "geo": {_x000D_ "lon": -89.6538,_x000D_ "lat": 39.7867_x000D_ },_x000D_ "timestamp": "0001-01-01T00:00:00"_x000D_ } | E18: 0 | F18: 1 | G18: 1528254 | I18: 46101.878 | Q18: 0 | R18: 4045111976 | S18: 2 | T18: 2026
A19: 2233583356 | B19: 46079.576 | C19: {_x000D_ "id": 4049608745,_x000D_ "sid": "log-call-no-answer-0becbaa812d65bad",_x000D_ "account_id": 441826,_x000D_ "name": "Kayla Smith",_x000D_ "cnam": "Kayla Smith",_x000D_ "search": "",_x000D_ "referrer": "",_x000D_ "visitor_sid": "",_x000D_ "location": "",_x000D_ "source": "Sandbox",_x000D_ "source_id": 1814974,_x000D_ "source_sid": "TSOF6FC2D2594D22C5288F2F91D669A9D5B9BE7FEE3C6EF44F4A9EA1A63913ECD83",_x000D_ "tgid": 5681974,_x000D_ "likelihood": null,_x000D_ "duration": 0,_x000D_ "direction": "form",_x000D_ "talk_time": 0,_x000D_ "ring_time": 0,_x000D_ "hold_time": 0,_x000D_ "wait_time": 0,_x000D_ "parent_id": null,_x000D_ "email": "Kaybethliese7@gmail.com",_x000D_ "street": null,_x000D_ "city": null,_x000D_ "state": null,_x000D_ "country": null,_x000D_ "postal_code": null,_x000D_ "called_at": "2026-02-26 07:50 AM -06:00",_x000D_ "unix_time": 1772117413,_x000D_ "tracking_number_id": 3476065,_x000D_ "tracking_number_sid": "TPNC3C4B23C348AEC2EE54EFD301979CD2EFFBA32881B159867D3F4ED59E6F0B56367EFF2993536685F",_x000D_ "tracking_number": "\u002B14352541043",_x000D_ "tracking_label": "Testing Number",_x000D_ "dial_status": "no-answer",_x000D_ "is_new_caller": true,_x000D_ "indexed_at": 1.772118E+09,_x000D_ "agent_insights": false,_x000D_ "duration_period": {_x000D_ "gte": 1772117413000,_x000D_ "lte": 1772117413000_x000D_ },_x000D_ "inbound_rate_center": {_x000D_ "country": "US",_x000D_ "prefix": "1",_x000D_ "tollfree": false_x000D_ },_x000D_ "business_number": null,_x000D_ "business_label": null,_x000D_ "receiving_number_id": null,_x000D_ "receiving_number_sid": null,_x000D_ "billed_amount": 0,_x000D_ "billed_at": "0001-01-01T00:00:00",_x000D_ "excluded": false,_x000D_ "redacted": false,_x000D_ "tracking_number_format": "(435) 254-1043",_x000D_ "business_number_format": null,_x000D_ "alternative_number": "2233583356",_x000D_ "tracking_number_bare": "4352541043",_x000D_ "caller_number_format": "(223) 358-3356",_x000D_ "caller_number_complete": "\u002B12233583356",_x000D_ "caller_number_bare": "2233583356",_x000D_ "caller_number": "\u002B12233583356",_x000D_ "caller_number_split": [_x000D_ "1",_x000D_ "223",_x000D_ "358",_x000D_ "3356"_x000D_ ],_x000D_ "contact_number": "\u002B12233583356",_x000D_ "visitor": false,_x000D_ "call_path": [_x000D_ {_x000D_ "route_name": "_OnHangup_CallSync",_x000D_ "route_id": "640990",_x000D_ "route_type": "RoutingRule",_x000D_ "started_at": "2026-02-26T07:50:14Z"_x000D_ }_x000D_ ],_x000D_ "left_talk_time": 0,_x000D_ "right_talk_time": 0,_x000D_ "transfers": [],_x000D_ "call_status": "completed",_x000D_ "status": "completed",_x000D_ "spotted": [],_x000D_ "salesforce": {},_x000D_ "audio": null,_x000D_ "is_s3_link": false,_x000D_ "callbacks": [],_x000D_ "emails": [],_x000D_ "day": "Thursday",_x000D_ "month": "February",_x000D_ "hour": "07AM",_x000D_ "paid": {_x000D_ "source": null,_x000D_ "medium": null_x000D_ },_x000D_ "ga": {_x000D_ "cid": "441826.4049608745",_x000D_ "ga4": []_x000D_ },_x000D_ "tag_list": [],_x000D_ "latitude": null,_x000D_ "longitude": null,_x000D_ "extended_lookup_on": true,_x000D_ "form": {_x000D_ "number_to_call": "log-call-no-answer-f936a0e55117aec9",_x000D_ "customer_number_to_dial": "\u002B12233583356",_x000D_ "name": "Kayla Smith",_x000D_ "email": "Kaybethliese7@gmail.com",_x000D_ "trackback_id": "trackback-441826.1772117413.2933156",_x000D_ "form_id": 213071,_x000D_ "form_name": "Contact Us",_x000D_ "custom": [_x000D_ {_x000D_ "label": "Referral Source",_x000D_ "value": "",_x000D_ "id": "referral_source"_x000D_ },_x000D_ {_x000D_ "label": "UTM Source",_x000D_ "value": "",_x000D_ "id": "utm_source"_x000D_ },_x000D_ {_x000D_ "label": "UTM Medium",_x000D_ "value": "",_x000D_ "id": "utm_medium"_x000D_ },_x000D_ {_x000D_ "label": "UTM Campaign",_x000D_ "value": "",_x000D_ "id": "utm_campaign"_x000D_ },_x000D_ {_x000D_ "label": "UTM Term",_x000D_ "value": "",_x000D_ "id": "utm_term"_x000D_ },_x000D_ {_x000D_ "label": "UTM Content",_x000D_ "value": "",_x000D_ "id": "utm_content"_x000D_ }_x000D_ ]_x000D_ },_x000D_ "legs": [],_x000D_ "touchpoints": null,_x000D_ "last_touch": null,_x000D_ "geo": null,_x000D_ "timestamp": "0001-01-01T00:00:00"_x000D_ } | E19: 0 | F19: 1 | G19: 1522641 | I19: 46063.643 | J19: 1773847353000 | Q19: 0 | R19: 4049608745 | S19: 2 | T19: 2026
A20: 2252663068 | B20: 46075.515 | C20: {_x000D_ "id": 4040607116,_x000D_ "sid": "log-call-no-answer-22d25f67c1e00e0e",_x000D_ "account_id": 441826,_x000D_ "name": "Clyneisa Huff",_x000D_ "cnam": "Clyneisa Huff",_x000D_ "search": "",_x000D_ "referrer": "",_x000D_ "visitor_sid": "",_x000D_ "location": "",_x000D_ "source": "Sandbox",_x000D_ "source_id": 1814974,_x000D_ "source_sid": "TSOF6FC2D2594D22C5288F2F91D669A9D5B9BE7FEE3C6EF44F4A9EA1A63913ECD83",_x000D_ "tgid": 5681974,_x000D_ "likelihood": null,_x000D_ "duration": 0,_x000D_ "direction": "form",_x000D_ "talk_time": 0,_x000D_ "ring_time": 0,_x000D_ "hold_time": 0,_x000D_ "wait_time": 0,_x000D_ "parent_id": null,_x000D_ "email": "nesi1297@outlook.com",_x000D_ "street": null,_x000D_ "city": null,_x000D_ "state": null,_x000D_ "country": null,_x000D_ "postal_code": "70704",_x000D_ "called_at": "2026-02-22 06:22 AM -06:00",_x000D_ "unix_time": 1771766522,_x000D_ "tracking_number_id": 3476065,_x000D_ "tracking_number_sid": "TPNC3C4B23C348AEC2EE54EFD301979CD2EFFBA32881B159867D3F4ED59E6F0B56367EFF2993536685F",_x000D_ "tracking_number": "\u002B14352541043",_x000D_ "tracking_label": "Testing Number",_x000D_ "dial_status": "no-answer",_x000D_ "is_new_caller": true,_x000D_ "indexed_at": 1.7717672E+09,_x000D_ "agent_insights": false,_x000D_ "duration_period": {_x000D_ "gte": 1771766522000,_x000D_ "lte": 1771766522000_x000D_ },_x000D_ "inbound_rate_center": {_x000D_ "country": "US",_x000D_ "prefix": "1",_x000D_ "tollfree": false_x000D_ },_x000D_ "business_number": null,_x000D_ "business_label": null,_x000D_ "receiving_number_id": null,_x000D_ "receiving_number_sid": null,_x000D_ "billed_amount": 0,_x000D_ "billed_at": "0001-01-01T00:00:00",_x000D_ "excluded": false,_x000D_ "redacted": false,_x000D_ "tracking_number_format": "(435) 254-1043",_x000D_ "business_number_format": null,_x000D_ "alternative_number": "2252663068",_x000D_ "tracking_number_bare": "4352541043",_x000D_ "caller_number_format": "(225) 266-3068",_x000D_ "caller_number_complete": "\u002B12252663068",_x000D_ "caller_number_bare": "2252663068",_x000D_ "caller_number": "\u002B12252663068",_x000D_ "caller_number_split": [_x000D_ "1",_x000D_ "225",_x000D_ "266",_x000D_ "3068"_x000D_ ],_x000D_ "contact_number": "\u002B12252663068",_x000D_ "visitor": false,_x000D_ "call_path": [_x000D_ {_x000D_ "route_name": "_OnHangup_CallSync",_x000D_ "route_id": "640990",_x000D_ "route_type": "RoutingRule",_x000D_ "started_at": "2026-02-22T06:22:03Z"_x000D_ }_x000D_ ],_x000D_ "left_talk_time": 0,_x000D_ "right_talk_time": 0,_x000D_ "transfers": [],_x000D_ "call_status": "completed",_x000D_ "status": "completed",_x000D_ "spotted": [],_x000D_ "salesforce": {},_x000D_ "audio": null,_x000D_ "is_s3_link": false,_x000D_ "callbacks": [],_x000D_ "emails": [],_x000D_ "day": "Sunday",_x000D_ "month": "February",_x000D_ "hour": "06AM",_x000D_ "paid": {_x000D_ "source": null,_x000D_ "medium": null_x000D_ },_x000D_ "ga": {_x000D_ "cid": "441826.4040607116",_x000D_ "ga4": []_x000D_ },_x000D_ "tag_list": [],_x000D_ "latitude": 30.4581,_x000D_ "longitude": -91.1463,_x000D_ "extended_lookup_on": true,_x000D_ "form": {_x000D_ "number_to_call": "log-call-no-answer-b5e09ee6623059da",_x000D_ "customer_number_to_dial": "\u002B12252663068",_x000D_ "name": "Clyneisa Huff",_x000D_ "email": "nesi1297@outlook.com",_x000D_ "trackback_id": "trackback-441826.1771766522.5595393",_x000D_ "form_id": 213071,_x000D_ "form_name": "Contact Us",_x000D_ "custom": [_x000D_ {_x000D_ "label": "Referral Source",_x000D_ "value": "",_x000D_ "id": "referral_source"_x000D_ },_x000D_ {_x000D_ "label": "UTM Source",_x000D_ "value": "",_x000D_ "id": "utm_source"_x000D_ },_x000D_ {_x000D_ "label": "UTM Medium",_x000D_ "value": "",_x000D_ "id": "utm_medium"_x000D_ },_x000D_ {_x000D_ "label": "UTM Campaign",_x000D_ "value": "",_x000D_ "id": "utm_campaign"_x000D_ },_x000D_ {_x000D_ "label": "UTM Term",_x000D_ "value": "",_x000D_ "id": "utm_term"_x000D_ },_x000D_ {_x000D_ "label": "UTM Content",_x000D_ "value": "",_x000D_ "id": "utm_content"_x000D_ }_x000D_ ]_x000D_ },_x000D_ "legs": [],_x000D_ "touchpoints": [_x000D_ {_x000D_ "call_id": 4040607116,_x000D_ "time": "2026-02-22T13:22:02Z",_x000D_ "touch_type": "form",_x000D_ "clickid": null,_x000D_ "type": null,_x000D_ "source": "Sandbox",_x000D_ "medium": null,_x000D_ "position": "last",_x000D_ "weight": 100_x000D_ }_x000D_ ],_x000D_ "last_touch": "Sandbox/",_x000D_ "geo": {_x000D_ "lon": -91.1463,_x000D_ "lat": 30.4581_x000D_ },_x000D_ "timestamp": "0001-01-01T00:00:00"_x000D_ } | E20: 0 | F20: 1 | G20: 1352642 | H20: 1 | I20: 45730.798 | K20: 1508182 | L20: 1 | M20: 593 | N20: 45730.798 | P20: Fox Home Protection Plan | Q20: 0 | R20: 4040607116 | S20: 2 | T20: 2026
A21: 2252663068 | B21: 46075.515 | C21: {_x000D_ "id": 4040607116,_x000D_ "sid": "log-call-no-answer-22d25f67c1e00e0e",_x000D_ "account_id": 441826,_x000D_ "name": "Clyneisa Huff",_x000D_ "cnam": "Clyneisa Huff",_x000D_ "search": "",_x000D_ "referrer": "",_x000D_ "visitor_sid": "",_x000D_ "location": "",_x000D_ "source": "Sandbox",_x000D_ "source_id": 1814974,_x000D_ "source_sid": "TSOF6FC2D2594D22C5288F2F91D669A9D5B9BE7FEE3C6EF44F4A9EA1A63913ECD83",_x000D_ "tgid": 5681974,_x000D_ "likelihood": null,_x000D_ "duration": 0,_x000D_ "direction": "form",_x000D_ "talk_time": 0,_x000D_ "ring_time": 0,_x000D_ "hold_time": 0,_x000D_ "wait_time": 0,_x000D_ "parent_id": null,_x000D_ "email": "nesi1297@outlook.com",_x000D_ "street": null,_x000D_ "city": null,_x000D_ "state": null,_x000D_ "country": null,_x000D_ "postal_code": "70704",_x000D_ "called_at": "2026-02-22 06:22 AM -06:00",_x000D_ "unix_time": 1771766522,_x000D_ "tracking_number_id": 3476065,_x000D_ "tracking_number_sid": "TPNC3C4B23C348AEC2EE54EFD301979CD2EFFBA32881B159867D3F4ED59E6F0B56367EFF2993536685F",_x000D_ "tracking_number": "\u002B14352541043",_x000D_ "tracking_label": "Testing Number",_x000D_ "dial_status": "no-answer",_x000D_ "is_new_caller": true,_x000D_ "indexed_at": 1.7717672E+09,_x000D_ "agent_insights": false,_x000D_ "duration_period": {_x000D_ "gte": 1771766522000,_x000D_ "lte": 1771766522000_x000D_ },_x000D_ "inbound_rate_center": {_x000D_ "country": "US",_x000D_ "prefix": "1",_x000D_ "tollfree": false_x000D_ },_x000D_ "business_number": null,_x000D_ "business_label": null,_x000D_ "receiving_number_id": null,_x000D_ "receiving_number_sid": null,_x000D_ "billed_amount": 0,_x000D_ "billed_at": "0001-01-01T00:00:00",_x000D_ "excluded": false,_x000D_ "redacted": false,_x000D_ "tracking_number_format": "(435) 254-1043",_x000D_ "business_number_format": null,_x000D_ "alternative_number": "2252663068",_x000D_ "tracking_number_bare": "4352541043",_x000D_ "caller_number_format": "(225) 266-3068",_x000D_ "caller_number_complete": "\u002B12252663068",_x000D_ "caller_number_bare": "2252663068",_x000D_ "caller_number": "\u002B12252663068",_x000D_ "caller_number_split": [_x000D_ "1",_x000D_ "225",_x000D_ "266",_x000D_ "3068"_x000D_ ],_x000D_ "contact_number": "\u002B12252663068",_x000D_ "visitor": false,_x000D_ "call_path": [_x000D_ {_x000D_ "route_name": "_OnHangup_CallSync",_x000D_ "route_id": "640990",_x000D_ "route_type": "RoutingRule",_x000D_ "started_at": "2026-02-22T06:22:03Z"_x000D_ }_x000D_ ],_x000D_ "left_talk_time": 0,_x000D_ "right_talk_time": 0,_x000D_ "transfers": [],_x000D_ "call_status": "completed",_x000D_ "status": "completed",_x000D_ "spotted": [],_x000D_ "salesforce": {},_x000D_ "audio": null,_x000D_ "is_s3_link": false,_x000D_ "callbacks": [],_x000D_ "emails": [],_x000D_ "day": "Sunday",_x000D_ "month": "February",_x000D_ "hour": "06AM",_x000D_ "paid": {_x000D_ "source": null,_x000D_ "medium": null_x000D_ },_x000D_ "ga": {_x000D_ "cid": "441826.4040607116",_x000D_ "ga4": []_x000D_ },_x000D_ "tag_list": [],_x000D_ "latitude": 30.4581,_x000D_ "longitude": -91.1463,_x000D_ "extended_lookup_on": true,_x000D_ "form": {_x000D_ "number_to_call": "log-call-no-answer-b5e09ee6623059da",_x000D_ "customer_number_to_dial": "\u002B12252663068",_x000D_ "name": "Clyneisa Huff",_x000D_ "email": "nesi1297@outlook.com",_x000D_ "trackback_id": "trackback-441826.1771766522.5595393",_x000D_ "form_id": 213071,_x000D_ "form_name": "Contact Us",_x000D_ "custom": [_x000D_ {_x000D_ "label": "Referral Source",_x000D_ "value": "",_x000D_ "id": "referral_source"_x000D_ },_x000D_ {_x000D_ "label": "UTM Source",_x000D_ "value": "",_x000D_ "id": "utm_source"_x000D_ },_x000D_ {_x000D_ "label": "UTM Medium",_x000D_ "value": "",_x000D_ "id": "utm_medium"_x000D_ },_x000D_ {_x000D_ "label": "UTM Campaign",_x000D_ "value": "",_x000D_ "id": "utm_campaign"_x000D_ },_x000D_ {_x000D_ "label": "UTM Term",_x000D_ "value": "",_x000D_ "id": "utm_term"_x000D_ },_x000D_ {_x000D_ "label": "UTM Content",_x000D_ "value": "",_x000D_ "id": "utm_content"_x000D_ }_x000D_ ]_x000D_ },_x000D_ "legs": [],_x000D_ "touchpoints": [_x000D_ {_x000D_ "call_id": 4040607116,_x000D_ "time": "2026-02-22T13:22:02Z",_x000D_ "touch_type": "form",_x000D_ "clickid": null,_x000D_ "type": null,_x000D_ "source": "Sandbox",_x000D_ "medium": null,_x000D_ "position": "last",_x000D_ "weight": 100_x000D_ }_x000D_ ],_x000D_ "last_touch": "Sandbox/",_x000D_ "geo": {_x000D_ "lon": -91.1463,_x000D_ "lat": 30.4581_x000D_ },_x000D_ "timestamp": "0001-01-01T00:00:00"_x000D_ } | E21: 1 | F21: 1 | G21: 1524151 | H21: 1 | I21: 46079.63 | K21: 1772330 | L21: 1 | M21: 516 | N21: 46079.63 | P21: Fox Home Protection Plan | Q21: 1 | R21: 4040607116 | S21: 2 | T21: 2026
A22: 2252806340 | B22: 46078.594 | C22: {_x000D_ "id": 4047032636,_x000D_ "sid": "log-call-no-answer-5e824baea6681ace",_x000D_ "account_id": 441826,_x000D_ "name": "Markaylia Griffin",_x000D_ "cnam": "Markaylia Griffin",_x000D_ "search": "",_x000D_ "referrer": "",_x000D_ "visitor_sid": "",_x000D_ "location": "",_x000D_ "source": "Sandbox",_x000D_ "source_id": 1814974,_x000D_ "source_sid": "TSOF6FC2D2594D22C5288F2F91D669A9D5B9BE7FEE3C6EF44F4A9EA1A63913ECD83",_x000D_ "tgid": 5681974,_x000D_ "likelihood": null,_x000D_ "duration": 0,_x000D_ "direction": "form",_x000D_ "talk_time": 0,_x000D_ "ring_time": 0,_x000D_ "hold_time": 0,_x000D_ "wait_time": 0,_x000D_ "parent_id": null,_x000D_ "email": "kayliagriffin@gmail.com",_x000D_ "street": null,_x000D_ "city": "Baton Rouge",_x000D_ "state": "LA",_x000D_ "country": null,_x000D_ "postal_code": "70704",_x000D_ "called_at": "2026-02-25 08:16 AM -06:00",_x000D_ "unix_time": 1772032613,_x000D_ "tracking_number_id": 3476065,_x000D_ "tracking_number_sid": "TPNC3C4B23C348AEC2EE54EFD301979CD2EFFBA32881B159867D3F4ED59E6F0B56367EFF2993536685F",_x000D_ "tracking_number": "\u002B14352541043",_x000D_ "tracking_label": "Testing Number",_x000D_ "dial_status": "no-answer",_x000D_ "is_new_caller": true,_x000D_ "indexed_at": 1.7720332E+09,_x000D_ "agent_insights": false,_x000D_ "duration_period": {_x000D_ "gte": 1772032613000,_x000D_ "lte": 1772032613000_x000D_ },_x000D_ "inbound_rate_center": {_x000D_ "country": "US",_x000D_ "prefix": "1",_x000D_ "tollfree": false_x000D_ },_x000D_ "business_number": null,_x000D_ "business_label": null,_x000D_ "receiving_number_id": null,_x000D_ "receiving_number_sid": null,_x000D_ "billed_amount": 0,_x000D_ "billed_at": "0001-01-01T00:00:00",_x000D_ "excluded": false,_x000D_ "redacted": false,_x000D_ "tracking_number_format": "(435) 254-1043",_x000D_ "business_number_format": null,_x000D_ "alternative_number": "2252806340",_x000D_ "tracking_number_bare": "4352541043",_x000D_ "caller_number_format": "(225) 280-6340",_x000D_ "caller_number_complete": "\u002B12252806340",_x000D_ "caller_number_bare": "2252806340",_x000D_ "caller_number": "\u002B12252806340",_x000D_ "caller_number_split": [_x000D_ "1",_x000D_ "225",_x000D_ "280",_x000D_ "6340"_x000D_ ],_x000D_ "contact_number": "\u002B12252806340",_x000D_ "visitor": false,_x000D_ "call_path": [_x000D_ {_x000D_ "route_name": "_OnHangup_CallSync",_x000D_ "route_id": "640990",_x000D_ "route_type": "RoutingRule",_x000D_ "started_at": "2026-02-25T08:16:54Z"_x000D_ }_x000D_ ],_x000D_ "left_talk_time": 0,_x000D_ "right_talk_time": 0,_x000D_ "transfers": [],_x000D_ "call_status": "completed",_x000D_ "status": "completed",_x000D_ "spotted": [],_x000D_ "salesforce": {},_x000D_ "audio": null,_x000D_ "is_s3_link": false,_x000D_ "callbacks": [],_x000D_ "emails": [],_x000D_ "day": "Wednesday",_x000D_ "month": "February",_x000D_ "hour": "08AM",_x000D_ "paid": {_x000D_ "source": null,_x000D_ "medium": null_x000D_ },_x000D_ "ga": {_x000D_ "cid": "441826.4047032636",_x000D_ "ga4": []_x000D_ },_x000D_ "tag_list": [],_x000D_ "latitude": 30.4581,_x000D_ "longitude": -91.1463,_x000D_ "extended_lookup_on": true,_x000D_ "form": {_x000D_ "number_to_call": "log-call-no-answer-06d4e18461d9c66f",_x000D_ "customer_number_to_dial": "\u002B12252806340",_x000D_ "name": "Markaylia Griffin",_x000D_ "email": "kayliagriffin@gmail.com",_x000D_ "trackback_id": "trackback-441826.1772032613.106528",_x000D_ "form_id": 213071,_x000D_ "form_name": "Contact Us",_x000D_ "custom": [_x000D_ {_x000D_ "label": "Referral Source",_x000D_ "value": "",_x000D_ "id": "referral_source"_x000D_ },_x000D_ {_x000D_ "label": "UTM Source",_x000D_ "value": "",_x000D_ "id": "utm_source"_x000D_ },_x000D_ {_x000D_ "label": "UTM Medium",_x000D_ "value": "",_x000D_ "id": "utm_medium"_x000D_ },_x000D_ {_x000D_ "label": "UTM Campaign",_x000D_ "value": "",_x000D_ "id": "utm_campaign"_x000D_ },_x000D_ {_x000D_ "label": "UTM Term",_x000D_ "value": "",_x000D_ "id": "utm_term"_x000D_ },_x000D_ {_x000D_ "label": "UTM Content",_x000D_ "value": "",_x000D_ "id": "utm_content"_x000D_ }_x000D_ ]_x000D_ },_x000D_ "legs": [],_x000D_ "touchpoints": null,_x000D_ "last_touch": null,_x000D_ "geo": {_x000D_ "lon": -91.1463,_x000D_ "lat": 30.4581_x000D_ },_x000D_ "timestamp": "0001-01-01T00:00:00"_x000D_ } | E22: 1 | F22: 1 | G22: 1524023 | H22: 1 | I22: 46078.643 | K22: 1771732 | L22: 1 | M22: 694 | N22: 46078.643 | P22: Fox Home Protection Plan | Q22: 1 | R22: 4047032636 | S22: 2 | T22: 2026
A23: 2252806340 | B23: 46078.594 | C23: {_x000D_ "id": 4047032636,_x000D_ "sid": "log-call-no-answer-5e824baea6681ace",_x000D_ "account_id": 441826,_x000D_ "name": "Markaylia Griffin",_x000D_ "cnam": "Markaylia Griffin",_x000D_ "search": "",_x000D_ "referrer": "",_x000D_ "visitor_sid": "",_x000D_ "location": "",_x000D_ "source": "Sandbox",_x000D_ "source_id": 1814974,_x000D_ "source_sid": "TSOF6FC2D2594D22C5288F2F91D669A9D5B9BE7FEE3C6EF44F4A9EA1A63913ECD83",_x000D_ "tgid": 5681974,_x000D_ "likelihood": null,_x000D_ "duration": 0,_x000D_ "direction": "form",_x000D_ "talk_time": 0,_x000D_ "ring_time": 0,_x000D_ "hold_time": 0,_x000D_ "wait_time": 0,_x000D_ "parent_id": null,_x000D_ "email": "kayliagriffin@gmail.com",_x000D_ "street": null,_x000D_ "city": "Baton Rouge",_x000D_ "state": "LA",_x000D_ "country": null,_x000D_ "postal_code": "70704",_x000D_ "called_at": "2026-02-25 08:16 AM -06:00",_x000D_ "unix_time": 1772032613,_x000D_ "tracking_number_id": 3476065,_x000D_ "tracking_number_sid": "TPNC3C4B23C348AEC2EE54EFD301979CD2EFFBA32881B159867D3F4ED59E6F0B56367EFF2993536685F",_x000D_ "tracking_number": "\u002B14352541043",_x000D_ "tracking_label": "Testing Number",_x000D_ "dial_status": "no-answer",_x000D_ "is_new_caller": true,_x000D_ "indexed_at": 1.7720332E+09,_x000D_ "agent_insights": false,_x000D_ "duration_period": {_x000D_ "gte": 1772032613000,_x000D_ "lte": 1772032613000_x000D_ },_x000D_ "inbound_rate_center": {_x000D_ "country": "US",_x000D_ "prefix": "1",_x000D_ "tollfree": false_x000D_ },_x000D_ "business_number": null,_x000D_ "business_label": null,_x000D_ "receiving_number_id": null,_x000D_ "receiving_number_sid": null,_x000D_ "billed_amount": 0,_x000D_ "billed_at": "0001-01-01T00:00:00",_x000D_ "excluded": false,_x000D_ "redacted": false,_x000D_ "tracking_number_format": "(435) 254-1043",_x000D_ "business_number_format": null,_x000D_ "alternative_number": "2252806340",_x000D_ "tracking_number_bare": "4352541043",_x000D_ "caller_number_format": "(225) 280-6340",_x000D_ "caller_number_complete": "\u002B12252806340",_x000D_ "caller_number_bare": "2252806340",_x000D_ "caller_number": "\u002B12252806340",_x000D_ "caller_number_split": [_x000D_ "1",_x000D_ "225",_x000D_ "280",_x000D_ "6340"_x000D_ ],_x000D_ "contact_number": "\u002B12252806340",_x000D_ "visitor": false,_x000D_ "call_path": [_x000D_ {_x000D_ "route_name": "_OnHangup_CallSync",_x000D_ "route_id": "640990",_x000D_ "route_type": "RoutingRule",_x000D_ "started_at": "2026-02-25T08:16:54Z"_x000D_ }_x000D_ ],_x000D_ "left_talk_time": 0,_x000D_ "right_talk_time": 0,_x000D_ "transfers": [],_x000D_ "call_status": "completed",_x000D_ "status": "completed",_x000D_ "spotted": [],_x000D_ "salesforce": {},_x000D_ "audio": null,_x000D_ "is_s3_link": false,_x000D_ "callbacks": [],_x000D_ "emails": [],_x000D_ "day": "Wednesday",_x000D_ "month": "February",_x000D_ "hour": "08AM",_x000D_ "paid": {_x000D_ "source": null,_x000D_ "medium": null_x000D_ },_x000D_ "ga": {_x000D_ "cid": "441826.4047032636",_x000D_ "ga4": []_x000D_ },_x000D_ "tag_list": [],_x000D_ "latitude": 30.4581,_x000D_ "longitude": -91.1463,_x000D_ "extended_lookup_on": true,_x000D_ "form": {_x000D_ "number_to_call": "log-call-no-answer-06d4e18461d9c66f",_x000D_ "customer_number_to_dial": "\u002B12252806340",_x000D_ "name": "Markaylia Griffin",_x000D_ "email": "kayliagriffin@gmail.com",_x000D_ "trackback_id": "trackback-441826.1772032613.106528",_x000D_ "form_id": 213071,_x000D_ "form_name": "Contact Us",_x000D_ "custom": [_x000D_ {_x000D_ "label": "Referral Source",_x000D_ "value": "",_x000D_ "id": "referral_source"_x000D_ },_x000D_ {_x000D_ "label": "UTM Source",_x000D_ "value": "",_x000D_ "id": "utm_source"_x000D_ },_x000D_ {_x000D_ "label": "UTM Medium",_x000D_ "value": "",_x000D_ "id": "utm_medium"_x000D_ },_x000D_ {_x000D_ "label": "UTM Campaign",_x000D_ "value": "",_x000D_ "id": "utm_campaign"_x000D_ },_x000D_ {_x000D_ "label": "UTM Term",_x000D_ "value": "",_x000D_ "id": "utm_term"_x000D_ },_x000D_ {_x000D_ "label": "UTM Content",_x000D_ "value": "",_x000D_ "id": "utm_content"_x000D_ }_x000D_ ]_x000D_ },_x000D_ "legs": [],_x000D_ "touchpoints": null,_x000D_ "last_touch": null,_x000D_ "geo": {_x000D_ "lon": -91.1463,_x000D_ "lat": 30.4581_x000D_ },_x000D_ "timestamp": "0001-01-01T00:00:00"_x000D_ } | E23: 0 | F23: 1 | G23: 1524027 | I23: 46078.651 | J23: 1774466270000 | Q23: 0 | R23: 4047032636 | S23: 2 | T23: 2026
A24: 2253286705 | B24: 46077.059 | C24: {_x000D_ "id": 4043923745,_x000D_ "sid": "log-call-no-answer-5fbe9afd453bf074",_x000D_ "account_id": 441826,_x000D_ "name": "Stephany Lewis",_x000D_ "cnam": "Stephany Lewis",_x000D_ "search": "",_x000D_ "referrer": "",_x000D_ "visitor_sid": "",_x000D_ "location": "",_x000D_ "source": "Sandbox",_x000D_ "source_id": 1814974,_x000D_ "source_sid": "TSOF6FC2D2594D22C5288F2F91D669A9D5B9BE7FEE3C6EF44F4A9EA1A63913ECD83",_x000D_ "tgid": 5681974,_x000D_ "likelihood": null,_x000D_ "duration": 0,_x000D_ "direction": "form",_x000D_ "talk_time": 0,_x000D_ "ring_time": 0,_x000D_ "hold_time": 0,_x000D_ "wait_time": 0,_x000D_ "parent_id": null,_x000D_ "email": "snlewis01@gmail.com",_x000D_ "street": null,_x000D_ "city": null,_x000D_ "state": null,_x000D_ "country": null,_x000D_ "postal_code": "70704",_x000D_ "called_at": "2026-02-23 07:25 PM -06:00",_x000D_ "unix_time": 1771899933,_x000D_ "tracking_number_id": 3476065,_x000D_ "tracking_number_sid": "TPNC3C4B23C348AEC2EE54EFD301979CD2EFFBA32881B159867D3F4ED59E6F0B56367EFF2993536685F",_x000D_ "tracking_number": "\u002B14352541043",_x000D_ "tracking_label": "Testing Number",_x000D_ "dial_status": "no-answer",_x000D_ "is_new_caller": true,_x000D_ "indexed_at": 1.7719005E+09,_x000D_ "agent_insights": false,_x000D_ "duration_period": {_x000D_ "gte": 1771899933000,_x000D_ "lte": 1771899933000_x000D_ },_x000D_ "inbound_rate_center": {_x000D_ "country": "US",_x000D_ "prefix": "1",_x000D_ "tollfree": false_x000D_ },_x000D_ "business_number": null,_x000D_ "business_label": null,_x000D_ "receiving_number_id": null,_x000D_ "receiving_number_sid": null,_x000D_ "billed_amount": 0,_x000D_ "billed_at": "0001-01-01T00:00:00",_x000D_ "excluded": false,_x000D_ "redacted": false,_x000D_ "tracking_number_format": "(435) 254-1043",_x000D_ "business_number_format": null,_x000D_ "alternative_number": "2253286705",_x000D_ "tracking_number_bare": "4352541043",_x000D_ "caller_number_format": "(225) 328-6705",_x000D_ "caller_number_complete": "\u002B12253286705",_x000D_ "caller_number_bare": "2253286705",_x000D_ "caller_number": "\u002B12253286705",_x000D_ "caller_number_split": [_x000D_ "1",_x000D_ "225",_x000D_ "328",_x000D_ "6705"_x000D_ ],_x000D_ "contact_number": "\u002B12253286705",_x000D_ "visitor": false,_x000D_ "call_path": [_x000D_ {_x000D_ "route_name": "_OnHangup_CallSync",_x000D_ "route_id": "640990",_x000D_ "route_type": "RoutingRule",_x000D_ "started_at": "2026-02-23T19:25:34Z"_x000D_ }_x000D_ ],_x000D_ "left_talk_time": 0,_x000D_ "right_talk_time": 0,_x000D_ "transfers": [],_x000D_ "call_status": "completed",_x000D_ "status": "completed",_x000D_ "spotted": [],_x000D_ "salesforce": {},_x000D_ "audio": null,_x000D_ "is_s3_link": false,_x000D_ "callbacks": [],_x000D_ "emails": [],_x000D_ "day": "Monday",_x000D_ "month": "February",_x000D_ "hour": "07PM",_x000D_ "paid": {_x000D_ "source": null,_x000D_ "medium": null_x000D_ },_x000D_ "ga": {_x000D_ "cid": "441826.4043923745",_x000D_ "ga4": []_x000D_ },_x000D_ "tag_list": [],_x000D_ "latitude": 30.4581,_x000D_ "longitude": -91.1463,_x000D_ "extended_lookup_on": true,_x000D_ "form": {_x000D_ "number_to_call": "log-call-no-answer-cab3b3fb87bd8452",_x000D_ "customer_number_to_dial": "\u002B12253286705",_x000D_ "name": "Stephany Lewis",_x000D_ "email": "snlewis01@gmail.com",_x000D_ "trackback_id": "trackback-441826.1771899933.1613147",_x000D_ "form_id": 213071,_x000D_ "form_name": "Contact Us",_x000D_ "custom": [_x000D_ {_x000D_ "label": "Referral Source",_x000D_ "value": "",_x000D_ "id": "referral_source"_x000D_ },_x000D_ {_x000D_ "label": "UTM Source",_x000D_ "value": "",_x000D_ "id": "utm_source"_x000D_ },_x000D_ {_x000D_ "label": "UTM Medium",_x000D_ "value": "",_x000D_ "id": "utm_medium"_x000D_ },_x000D_ {_x000D_ "label": "UTM Campaign",_x000D_ "value": "",_x000D_ "id": "utm_campaign"_x000D_ },_x000D_ {_x000D_ "label": "UTM Term",_x000D_ "value": "",_x000D_ "id": "utm_term"_x000D_ },_x000D_ {_x000D_ "label": "UTM Content",_x000D_ "value": "",_x000D_ "id": "utm_content"_x000D_ }_x000D_ ]_x000D_ },_x000D_ "legs": [],_x000D_ "touchpoints": null,_x000D_ "last_touch": null,_x000D_ "geo": {_x000D_ "lon": -91.1463,_x000D_ "lat": 30.4581_x000D_ },_x000D_ "timestamp": "0001-01-01T00:00:00"_x000D_ } | E24: 1 | F24: 1 | G24: 1523952 | H24: 1 | I24: 46077.809 | K24: 1771439 | L24: 1 | M24: 696 | N24: 46077.809 | P24: Fox Home Protection Plan | Q24: 1 | R24: 4043923745 | S24: 2 | T24: 2026
A25: 2257150992 | B25: 46071.792 | C25: {_x000D_ "id": 4033467854,_x000D_ "sid": "log-call-no-answer-4421a7478226626e",_x000D_ "account_id": 441826,_x000D_ "name": "Kendra Davis",_x000D_ "cnam": "Kendra Davis",_x000D_ "search": "",_x000D_ "referrer": "",_x000D_ "visitor_sid": "",_x000D_ "location": "",_x000D_ "source": "Sandbox",_x000D_ "source_id": 1814974,_x000D_ "source_sid": "TSOF6FC2D2594D22C5288F2F91D669A9D5B9BE7FEE3C6EF44F4A9EA1A63913ECD83",_x000D_ "tgid": 5681974,_x000D_ "likelihood": null,_x000D_ "duration": 0,_x000D_ "direction": "form",_x000D_ "talk_time": 0,_x000D_ "ring_time": 0,_x000D_ "hold_time": 0,_x000D_ "wait_time": 0,_x000D_ "parent_id": null,_x000D_ "email": "mskdavis@yahoo.com",_x000D_ "street": null,_x000D_ "city": null,_x000D_ "state": null,_x000D_ "country": null,_x000D_ "postal_code": "70704",_x000D_ "called_at": "2026-02-18 01:01 PM -06:00",_x000D_ "unix_time": 1771444877,_x000D_ "tracking_number_id": 3476065,_x000D_ "tracking_number_sid": "TPNC3C4B23C348AEC2EE54EFD301979CD2EFFBA32881B159867D3F4ED59E6F0B56367EFF2993536685F",_x000D_ "tracking_number": "\u002B14352541043",_x000D_ "tracking_label": "Testing Number",_x000D_ "dial_status": "no-answer",_x000D_ "is_new_caller": true,_x000D_ "indexed_at": 1.7714455E+09,_x000D_ "agent_insights": false,_x000D_ "duration_period": {_x000D_ "gte": 1771444877000,_x000D_ "lte": 1771444877000_x000D_ },_x000D_ "inbound_rate_center": {_x000D_ "country": "US",_x000D_ "prefix": "1",_x000D_ "tollfree": false_x000D_ },_x000D_ "business_number": null,_x000D_ "business_label": null,_x000D_ "receiving_number_id": null,_x000D_ "receiving_number_sid": null,_x000D_ "billed_amount": 0,_x000D_ "billed_at": "0001-01-01T00:00:00",_x000D_ "excluded": false,_x000D_ "redacted": false,_x000D_ "tracking_number_format": "(435) 254-1043",_x000D_ "business_number_format": null,_x000D_ "alternative_number": "2257150992",_x000D_ "tracking_number_bare": "4352541043",_x000D_ "caller_number_format": "(225) 715-0992",_x000D_ "caller_number_complete": "\u002B12257150992",_x000D_ "caller_number_bare": "2257150992",_x000D_ "caller_number": "\u002B12257150992",_x000D_ "caller_number_split": [_x000D_ "1",_x000D_ "225",_x000D_ "715",_x000D_ "0992"_x000D_ ],_x000D_ "contact_number": "\u002B12257150992",_x000D_ "visitor": false,_x000D_ "call_path": [_x000D_ {_x000D_ "route_name": "_OnHangup_CallSync",_x000D_ "route_id": "640990",_x000D_ "route_type": "RoutingRule",_x000D_ "started_at": "2026-02-18T13:01:19Z"_x000D_ }_x000D_ ],_x000D_ "left_talk_time": 0,_x000D_ "right_talk_time": 0,_x000D_ "transfers": [],_x000D_ "call_status": "completed",_x000D_ "status": "completed",_x000D_ "spotted": [],_x000D_ "salesforce": {},_x000D_ "audio": null,_x000D_ "is_s3_link": false,_x000D_ "callbacks": [],_x000D_ "emails": [],_x000D_ "day": "Wednesday",_x000D_ "month": "February",_x000D_ "hour": "01PM",_x000D_ "paid": {_x000D_ "source": null,_x000D_ "medium": null_x000D_ },_x000D_ "ga": {_x000D_ "cid": "441826.4033467854",_x000D_ "ga4": []_x000D_ },_x000D_ "tag_list": [],_x000D_ "latitude": 30.4581,_x000D_ "longitude": -91.1463,_x000D_ "extended_lookup_on": true,_x000D_ "form": {_x000D_ "number_to_call": "log-call-no-answer-3cf66b6cdf441c6b",_x000D_ "customer_number_to_dial": "\u002B12257150992",_x000D_ "name": "Kendra Davis",_x000D_ "email": "mskdavis@yahoo.com",_x000D_ "trackback_id": "trackback-441826.1771444877.8696756",_x000D_ "form_id": 213071,_x000D_ "form_name": "Contact Us",_x000D_ "custom": [_x000D_ {_x000D_ "label": "Referral Source",_x000D_ "value": "",_x000D_ "id": "referral_source"_x000D_ },_x000D_ {_x000D_ "label": "UTM Source",_x000D_ "value": "",_x000D_ "id": "utm_source"_x000D_ },_x000D_ {_x000D_ "label": "UTM Medium",_x000D_ "value": "",_x000D_ "id": "utm_medium"_x000D_ },_x000D_ {_x000D_ "label": "UTM Campaign",_x000D_ "value": "",_x000D_ "id": "utm_campaign"_x000D_ },_x000D_ {_x000D_ "label": "UTM Term",_x000D_ "value": "",_x000D_ "id": "utm_term"_x000D_ },_x000D_ {_x000D_ "label": "UTM Content",_x000D_ "value": "",_x000D_ "id": "utm_content"_x000D_ }_x000D_ ]_x000D_ },_x000D_ "legs": [],_x000D_ "touchpoints": null,_x000D_ "last_touch": null,_x000D_ "geo": {_x000D_ "lon": -91.1463,_x000D_ "lat": 30.4581_x000D_ },_x000D_ "timestamp": "0001-01-01T00:00:00"_x000D_ } | E25: 0 | F25: 1 | G25: 1523822 | I25: 46076.745 | J25: 1772661559000 | Q25: 0 | R25: 4033467854 | S25: 2 | T25: 2026
A26: 2259388998 | B26: 46072.945 | C26: {_x000D_ "id": 4036878413,_x000D_ "sid": "log-call-no-answer-600f746f5a8c0170",_x000D_ "account_id": 441826,_x000D_ "name": "Sheila Rabalais",_x000D_ "cnam": "Sheila Rabalais",_x000D_ "search": "",_x000D_ "referrer": "",_x000D_ "visitor_sid": "",_x000D_ "location": "",_x000D_ "source": "Sandbox",_x000D_ "source_id": 1814974,_x000D_ "source_sid": "TSOF6FC2D2594D22C5288F2F91D669A9D5B9BE7FEE3C6EF44F4A9EA1A63913ECD83",_x000D_ "tgid": 5681974,_x000D_ "likelihood": null,_x000D_ "duration": 0,_x000D_ "direction": "form",_x000D_ "talk_time": 0,_x000D_ "ring_time": 0,_x000D_ "hold_time": 0,_x000D_ "wait_time": 0,_x000D_ "parent_id": null,_x000D_ "email": "losk22p8@gmail.com",_x000D_ "street": null,_x000D_ "city": null,_x000D_ "state": null,_x000D_ "country": null,_x000D_ "postal_code": "70704",_x000D_ "called_at": "2026-02-19 04:41 PM -06:00",_x000D_ "unix_time": 1771544506,_x000D_ "tracking_number_id": 3476065,_x000D_ "tracking_number_sid": "TPNC3C4B23C348AEC2EE54EFD301979CD2EFFBA32881B159867D3F4ED59E6F0B56367EFF2993536685F",_x000D_ "tracking_number": "\u002B14352541043",_x000D_ "tracking_label": "Testing Number",_x000D_ "dial_status": "no-answer",_x000D_ "is_new_caller": true,_x000D_ "indexed_at": 1.7715451E+09,_x000D_ "agent_insights": false,_x000D_ "duration_period": {_x000D_ "gte": 1771544506000,_x000D_ "lte": 1771544506000_x000D_ },_x000D_ "inbound_rate_center": {_x000D_ "country": "US",_x000D_ "prefix": "1",_x000D_ "tollfree": false_x000D_ },_x000D_ "business_number": null,_x000D_ "business_label": null,_x000D_ "receiving_number_id": null,_x000D_ "receiving_number_sid": null,_x000D_ "billed_amount": 0,_x000D_ "billed_at": "0001-01-01T00:00:00",_x000D_ "excluded": false,_x000D_ "redacted": false,_x000D_ "tracking_number_format": "(435) 254-1043",_x000D_ "business_number_format": null,_x000D_ "alternative_number": "2259388998",_x000D_ "tracking_number_bare": "4352541043",_x000D_ "caller_number_format": "(225) 938-8998",_x000D_ "caller_number_complete": "\u002B12259388998",_x000D_ "caller_number_bare": "2259388998",_x000D_ "caller_number": "\u002B12259388998",_x000D_ "caller_number_split": [_x000D_ "1",_x000D_ "225",_x000D_ "938",_x000D_ "8998"_x000D_ ],_x000D_ "contact_number": "\u002B12259388998",_x000D_ "visitor": false,_x000D_ "call_path": [_x000D_ {_x000D_ "route_name": "_OnHangup_CallSync",_x000D_ "route_id": "640990",_x000D_ "route_type": "RoutingRule",_x000D_ "started_at": "2026-02-19T16:41:47Z"_x000D_ }_x000D_ ],_x000D_ "left_talk_time": 0,_x000D_ "right_talk_time": 0,_x000D_ "transfers": [],_x000D_ "call_status": "completed",_x000D_ "status": "completed",_x000D_ "spotted": [],_x000D_ "salesforce": {},_x000D_ "audio": null,_x000D_ "is_s3_link": false,_x000D_ "callbacks": [],_x000D_ "emails": [],_x000D_ "day": "Thursday",_x000D_ "month": "February",_x000D_ "hour": "04PM",_x000D_ "paid": {_x000D_ "source": null,_x000D_ "medium": null_x000D_ },_x000D_ "ga": {_x000D_ "cid": "441826.4036878413",_x000D_ "ga4": []_x000D_ },_x000D_ "tag_list": [],_x000D_ "latitude": 30.4581,_x000D_ "longitude": -91.1463,_x000D_ "extended_lookup_on": true,_x000D_ "form": {_x000D_ "number_to_call": "log-call-no-answer-f7cdfb7f4f002686",_x000D_ "customer_number_to_dial": "\u002B12259388998",_x000D_ "name": "Sheila Rabalais",_x000D_ "email": "losk22p8@gmail.com",_x000D_ "trackback_id": "trackback-441826.1771544506.0336905",_x000D_ "form_id": 213071,_x000D_ "form_name": "Contact Us",_x000D_ "custom": [_x000D_ {_x000D_ "label": "Referral Source",_x000D_ "value": "",_x000D_ "id": "referral_source"_x000D_ },_x000D_ {_x000D_ "label": "UTM Source",_x000D_ "value": "",_x000D_ "id": "utm_source"_x000D_ },_x000D_ {_x000D_ "label": "UTM Medium",_x000D_ "value": "",_x000D_ "id": "utm_medium"_x000D_ },_x000D_ {_x000D_ "label": "UTM Campaign",_x000D_ "value": "",_x000D_ "id": "utm_campaign"_x000D_ },_x000D_ {_x000D_ "label": "UTM Term",_x000D_ "value": "",_x000D_ "id": "utm_term"_x000D_ },_x000D_ {_x000D_ "label": "UTM Content",_x000D_ "value": "",_x000D_ "id": "utm_content"_x000D_ }_x000D_ ]_x000D_ },_x000D_ "legs": [],_x000D_ "touchpoints": null,_x000D_ "last_touch": null,_x000D_ "geo": {_x000D_ "lon": -91.1463,_x000D_ "lat": 30.4581_x000D_ },_x000D_ "timestamp": "0001-01-01T00:00:00"_x000D_ } | E26: 0 | F26: 1 | G26: 943903 | H26: 0 | I26: 44352.708 | J26: 1731601298000 | K26: 947916 | L26: 1 | M26: 669.45 | N26: 44352.708 | O26: 1731601298000 | P26: Fox Home Protection Plan | Q26: 0 | R26: 4036878413 | S26: 2 | T26: 2026
A27: 2259388998 | B27: 46072.945 | C27: {_x000D_ "id": 4036878413,_x000D_ "sid": "log-call-no-answer-600f746f5a8c0170",_x000D_ "account_id": 441826,_x000D_ "name": "Sheila Rabalais",_x000D_ "cnam": "Sheila Rabalais",_x000D_ "search": "",_x000D_ "referrer": "",_x000D_ "visitor_sid": "",_x000D_ "location": "",_x000D_ "source": "Sandbox",_x000D_ "source_id": 1814974,_x000D_ "source_sid": "TSOF6FC2D2594D22C5288F2F91D669A9D5B9BE7FEE3C6EF44F4A9EA1A63913ECD83",_x000D_ "tgid": 5681974,_x000D_ "likelihood": null,_x000D_ "duration": 0,_x000D_ "direction": "form",_x000D_ "talk_time": 0,_x000D_ "ring_time": 0,_x000D_ "hold_time": 0,_x000D_ "wait_time": 0,_x000D_ "parent_id": null,_x000D_ "email": "losk22p8@gmail.com",_x000D_ "street": null,_x000D_ "city": null,_x000D_ "state": null,_x000D_ "country": null,_x000D_ "postal_code": "70704",_x000D_ "called_at": "2026-02-19 04:41 PM -06:00",_x000D_ "unix_time": 1771544506,_x000D_ "tracking_number_id": 3476065,_x000D_ "tracking_number_sid": "TPNC3C4B23C348AEC2EE54EFD301979CD2EFFBA32881B159867D3F4ED59E6F0B56367EFF2993536685F",_x000D_ "tracking_number": "\u002B14352541043",_x000D_ "tracking_label": "Testing Number",_x000D_ "dial_status": "no-answer",_x000D_ "is_new_caller": true,_x000D_ "indexed_at": 1.7715451E+09,_x000D_ "agent_insights": false,_x000D_ "duration_period": {_x000D_ "gte": 1771544506000,_x000D_ "lte": 1771544506000_x000D_ },_x000D_ "inbound_rate_center": {_x000D_ "country": "US",_x000D_ "prefix": "1",_x000D_ "tollfree": false_x000D_ },_x000D_ "business_number": null,_x000D_ "business_label": null,_x000D_ "receiving_number_id": null,_x000D_ "receiving_number_sid": null,_x000D_ "billed_amount": 0,_x000D_ "billed_at": "0001-01-01T00:00:00",_x000D_ "excluded": false,_x000D_ "redacted": false,_x000D_ "tracking_number_format": "(435) 254-1043",_x000D_ "business_number_format": null,_x000D_ "alternative_number": "2259388998",_x000D_ "tracking_number_bare": "4352541043",_x000D_ "caller_number_format": "(225) 938-8998",_x000D_ "caller_number_complete": "\u002B12259388998",_x000D_ "caller_number_bare": "2259388998",_x000D_ "caller_number": "\u002B12259388998",_x000D_ "caller_number_split": [_x000D_ "1",_x000D_ "225",_x000D_ "938",_x000D_ "8998"_x000D_ ],_x000D_ "contact_number": "\u002B12259388998",_x000D_ "visitor": false,_x000D_ "call_path": [_x000D_ {_x000D_ "route_name": "_OnHangup_CallSync",_x000D_ "route_id": "640990",_x000D_ "route_type": "RoutingRule",_x000D_ "started_at": "2026-02-19T16:41:47Z"_x000D_ }_x000D_ ],_x000D_ "left_talk_time": 0,_x000D_ "right_talk_time": 0,_x000D_ "transfers": [],_x000D_ "call_status": "completed",_x000D_ "status": "completed",_x000D_ "spotted": [],_x000D_ "salesforce": {},_x000D_ "audio": null,_x000D_ "is_s3_link": false,_x000D_ "callbacks": [],_x000D_ "emails": [],_x000D_ "day": "Thursday",_x000D_ "month": "February",_x000D_ "hour": "04PM",_x000D_ "paid": {_x000D_ "source": null,_x000D_ "medium": null_x000D_ },_x000D_ "ga": {_x000D_ "cid": "441826.4036878413",_x000D_ "ga4": []_x000D_ },_x000D_ "tag_list": [],_x000D_ "latitude": 30.4581,_x000D_ "longitude": -91.1463,_x000D_ "extended_lookup_on": true,_x000D_ "form": {_x000D_ "number_to_call": "log-call-no-answer-f7cdfb7f4f002686",_x000D_ "customer_number_to_dial": "\u002B12259388998",_x000D_ "name": "Sheila Rabalais",_x000D_ "email": "losk22p8@gmail.com",_x000D_ "trackback_id": "trackback-441826.1771544506.0336905",_x000D_ "form_id": 213071,_x000D_ "form_name": "Contact Us",_x000D_ "custom": [_x000D_ {_x000D_ "label": "Referral Source",_x000D_ "value": "",_x000D_ "id": "referral_source"_x000D_ },_x000D_ {_x000D_ "label": "UTM Source",_x000D_ "value": "",_x000D_ "id": "utm_source"_x000D_ },_x000D_ {_x000D_ "label": "UTM Medium",_x000D_ "value": "",_x000D_ "id": "utm_medium"_x000D_ },_x000D_ {_x000D_ "label": "UTM Campaign",_x000D_ "value": "",_x000D_ "id": "utm_campaign"_x000D_ },_x000D_ {_x000D_ "label": "UTM Term",_x000D_ "value": "",_x000D_ "id": "utm_term"_x000D_ },_x000D_ {_x000D_ "label": "UTM Content",_x000D_ "value": "",_x000D_ "id": "utm_content"_x000D_ }_x000D_ ]_x000D_ },_x000D_ "legs": [],_x000D_ "touchpoints": null,_x000D_ "last_touch": null,_x000D_ "geo": {_x000D_ "lon": -91.1463,_x000D_ "lat": 30.4581_x000D_ },_x000D_ "timestamp": "0001-01-01T00:00:00"_x000D_ } | E27: 1 | F27: 1 | G27: 1523570 | H27: 1 | I27: 46072.985 | K27: 1769997 | L27: 1 | M27: 635 | N27: 46072.985 | P27: Fox Home Protection Plan | Q27: 1 | R27: 4036878413 | S27: 2 | T27: 2026
A28: 2403383254 | B28: 46073.467 | C28: {_x000D_ "id": 4037299595,_x000D_ "sid": "log-call-no-answer-4263afd61d287fa6",_x000D_ "account_id": 441826,_x000D_ "name": "Marilu Vargas-Lane",_x000D_ "cnam": "Marilu Vargas-Lane",_x000D_ "search": "",_x000D_ "referrer": "",_x000D_ "visitor_sid": "",_x000D_ "location": "",_x000D_ "source": "Sandbox",_x000D_ "source_id": 1814974,_x000D_ "source_sid": "TSOF6FC2D2594D22C5288F2F91D669A9D5B9BE7FEE3C6EF44F4A9EA1A63913ECD83",_x000D_ "tgid": 5681974,_x000D_ "likelihood": null,_x000D_ "duration": 0,_x000D_ "direction": "form",_x000D_ "talk_time": 0,_x000D_ "ring_time": 0,_x000D_ "hold_time": 0,_x000D_ "wait_time": 0,_x000D_ "parent_id": null,_x000D_ "email": "marilumvs@gmail.com",_x000D_ "street": null,_x000D_ "city": null,_x000D_ "state": null,_x000D_ "country": null,_x000D_ "postal_code": "20747",_x000D_ "called_at": "2026-02-20 05:12 AM -06:00",_x000D_ "unix_time": 1771589574,_x000D_ "tracking_number_id": 3476065,_x000D_ "tracking_number_sid": "TPNC3C4B23C348AEC2EE54EFD301979CD2EFFBA32881B159867D3F4ED59E6F0B56367EFF2993536685F",_x000D_ "tracking_number": "\u002B14352541043",_x000D_ "tracking_label": "Testing Number",_x000D_ "dial_status": "no-answer",_x000D_ "is_new_caller": true,_x000D_ "indexed_at": 1.7715901E+09,_x000D_ "agent_insights": false,_x000D_ "duration_period": {_x000D_ "gte": 1771589574000,_x000D_ "lte": 1771589574000_x000D_ },_x000D_ "inbound_rate_center": {_x000D_ "country": "US",_x000D_ "prefix": "1",_x000D_ "tollfree": false_x000D_ },_x000D_ "business_number": null,_x000D_ "business_label": null,_x000D_ "receiving_number_id": null,_x000D_ "receiving_number_sid": null,_x000D_ "billed_amount": 0,_x000D_ "billed_at": "0001-01-01T00:00:00",_x000D_ "excluded": false,_x000D_ "redacted": false,_x000D_ "tracking_number_format": "(435) 254-1043",_x000D_ "business_number_format": null,_x000D_ "alternative_number": "2403383254",_x000D_ "tracking_number_bare": "4352541043",_x000D_ "caller_number_format": "(240) 338-3254",_x000D_ "caller_number_complete": "\u002B12403383254",_x000D_ "caller_number_bare": "2403383254",_x000D_ "caller_number": "\u002B12403383254",_x000D_ "caller_number_split": [_x000D_ "1",_x000D_ "240",_x000D_ "338",_x000D_ "3254"_x000D_ ],_x000D_ "contact_number": "\u002B12403383254",_x000D_ "visitor": false,_x000D_ "call_path": [_x000D_ {_x000D_ "route_name": "_OnHangup_CallSync",_x000D_ "route_id": "640990",_x000D_ "route_type": "RoutingRule",_x000D_ "started_at": "2026-02-20T05:12:56Z"_x000D_ }_x000D_ ],_x000D_ "left_talk_time": 0,_x000D_ "right_talk_time": 0,_x000D_ "transfers": [],_x000D_ "call_status": "completed",_x000D_ "status": "completed",_x000D_ "spotted": [],_x000D_ "salesforce": {},_x000D_ "audio": null,_x000D_ "is_s3_link": false,_x000D_ "callbacks": [],_x000D_ "emails": [],_x000D_ "day": "Friday",_x000D_ "month": "February",_x000D_ "hour": "05AM",_x000D_ "paid": {_x000D_ "source": null,_x000D_ "medium": null_x000D_ },_x000D_ "ga": {_x000D_ "cid": "441826.4037299595",_x000D_ "ga4": []_x000D_ },_x000D_ "tag_list": [],_x000D_ "latitude": 39.0103,_x000D_ "longitude": -77.0405,_x000D_ "extended_lookup_on": true,_x000D_ "form": {_x000D_ "number_to_call": "log-call-no-answer-8c9f11beb67b0774",_x000D_ "customer_number_to_dial": "\u002B12403383254",_x000D_ "name": "Marilu Vargas-Lane",_x000D_ "email": "marilumvs@gmail.com",_x000D_ "trackback_id": "trackback-441826.1771589574.820691",_x000D_ "form_id": 213071,_x000D_ "form_name": "Contact Us",_x000D_ "custom": [_x000D_ {_x000D_ "label": "Referral Source",_x000D_ "value": "",_x000D_ "id": "referral_source"_x000D_ },_x000D_ {_x000D_ "label": "UTM Source",_x000D_ "value": "",_x000D_ "id": "utm_source"_x000D_ },_x000D_ {_x000D_ "label": "UTM Medium",_x000D_ "value": "",_x000D_ "id": "utm_medium"_x000D_ },_x000D_ {_x000D_ "label": "UTM Campaign",_x000D_ "value": "",_x000D_ "id": "utm_campaign"_x000D_ },_x000D_ {_x000D_ "label": "UTM Term",_x000D_ "value": "",_x000D_ "id": "utm_term"_x000D_ },_x000D_ {_x000D_ "label": "UTM Content",_x000D_ "value": "",_x000D_ "id": "utm_content"_x000D_ }_x000D_ ]_x000D_ },_x000D_ "legs": [],_x000D_ "touchpoints": [_x000D_ {_x000D_ "call_id": 4037299595,_x000D_ "time": "2026-02-20T12:12:54Z",_x000D_ "touch_type": "form",_x000D_ "clickid": null,_x000D_ "type": null,_x000D_ "source": "Sandbox",_x000D_ "medium": null,_x000D_ "position": "last",_x000D_ "weight": 100_x000D_ }_x000D_ ],_x000D_ "last_touch": "Sandbox/",_x000D_ "geo": {_x000D_ "lon": -77.0405,_x000D_ "lat": 39.0103_x000D_ },_x000D_ "timestamp": "0001-01-01T00:00:00"_x000D_ } | E28: 0 | F28: 1 | G28: 999949 | H28: 0 | I28: 44424.704 | J28: 1700242302000 | K28: 1010719 | L28: 1 | M28: 795 | N28: 44424.706 | O28: 1700242302000 | P28: Fox Home Protection Plan | Q28: 0 | R28: 4037299595 | S28: 2 | T28: 2026
A29: 2407568518 | B29: 46074.794 | C29: {_x000D_ "id": 4040161904,_x000D_ "sid": "log-call-no-answer-80b0c4d30789800e",_x000D_ "account_id": 441826,_x000D_ "name": "Johanna Conselatore",_x000D_ "cnam": "Johanna Conselatore",_x000D_ "search": "",_x000D_ "referrer": "",_x000D_ "visitor_sid": "",_x000D_ "location": "",_x000D_ "source": "Sandbox",_x000D_ "source_id": 1814974,_x000D_ "source_sid": "TSOF6FC2D2594D22C5288F2F91D669A9D5B9BE7FEE3C6EF44F4A9EA1A63913ECD83",_x000D_ "tgid": 5681974,_x000D_ "likelihood": null,_x000D_ "duration": 0,_x000D_ "direction": "form",_x000D_ "talk_time": 0,_x000D_ "ring_time": 0,_x000D_ "hold_time": 0,_x000D_ "wait_time": 0,_x000D_ "parent_id": null,_x000D_ "email": "joconselatore@gmail.com",_x000D_ "street": null,_x000D_ "city": null,_x000D_ "state": null,_x000D_ "country": null,_x000D_ "postal_code": "20818",_x000D_ "called_at": "2026-02-21 01:04 PM -06:00",_x000D_ "unix_time": 1771704261,_x000D_ "tracking_number_id": 3476065,_x000D_ "tracking_number_sid": "TPNC3C4B23C348AEC2EE54EFD301979CD2EFFBA32881B159867D3F4ED59E6F0B56367EFF2993536685F",_x000D_ "tracking_number": "\u002B14352541043",_x000D_ "tracking_label": "Testing Number",_x000D_ "dial_status": "no-answer",_x000D_ "is_new_caller": true,_x000D_ "indexed_at": 1.7717048E+09,_x000D_ "agent_insights": false,_x000D_ "duration_period": {_x000D_ "gte": 1771704261000,_x000D_ "lte": 1771704261000_x000D_ },_x000D_ "inbound_rate_center": {_x000D_ "country": "US",_x000D_ "prefix": "1",_x000D_ "tollfree": false_x000D_ },_x000D_ "business_number": null,_x000D_ "business_label": null,_x000D_ "receiving_number_id": null,_x000D_ "receiving_number_sid": null,_x000D_ "billed_amount": 0,_x000D_ "billed_at": "0001-01-01T00:00:00",_x000D_ "excluded": false,_x000D_ "redacted": false,_x000D_ "tracking_number_format": "(435) 254-1043",_x000D_ "business_number_format": null,_x000D_ "alternative_number": "2407568518",_x000D_ "tracking_number_bare": "4352541043",_x000D_ "caller_number_format": "(240) 756-8518",_x000D_ "caller_number_complete": "\u002B12407568518",_x000D_ "caller_number_bare": "2407568518",_x000D_ "caller_number": "\u002B12407568518",_x000D_ "caller_number_split": [_x000D_ "1",_x000D_ "240",_x000D_ "756",_x000D_ "8518"_x000D_ ],_x000D_ "contact_number": "\u002B12407568518",_x000D_ "visitor": false,_x000D_ "call_path": [_x000D_ {_x000D_ "route_name": "_OnHangup_CallSync",_x000D_ "route_id": "640990",_x000D_ "route_type": "RoutingRule",_x000D_ "started_at": "2026-02-21T13:04:22Z"_x000D_ }_x000D_ ],_x000D_ "left_talk_time": 0,_x000D_ "right_talk_time": 0,_x000D_ "transfers": [],_x000D_ "call_status": "completed",_x000D_ "status": "completed",_x000D_ "spotted": [],_x000D_ "salesforce": {},_x000D_ "audio": null,_x000D_ "is_s3_link": false,_x000D_ "callbacks": [],_x000D_ "emails": [],_x000D_ "day": "Saturday",_x000D_ "month": "February",_x000D_ "hour": "01PM",_x000D_ "paid": {_x000D_ "source": null,_x000D_ "medium": null_x000D_ },_x000D_ "ga": {_x000D_ "cid": "441826.4040161904",_x000D_ "ga4": []_x000D_ },_x000D_ "tag_list": [],_x000D_ "latitude": 39.0855,_x000D_ "longitude": -77.1599,_x000D_ "extended_lookup_on": true,_x000D_ "form": {_x000D_ "number_to_call": "log-call-no-answer-22a5bd5282af89db",_x000D_ "customer_number_to_dial": "\u002B12407568518",_x000D_ "name": "Johanna Conselatore",_x000D_ "email": "joconselatore@gmail.com",_x000D_ "trackback_id": "trackback-441826.1771704261.3866847",_x000D_ "form_id": 213071,_x000D_ "form_name": "Contact Us",_x000D_ "custom": [_x000D_ {_x000D_ "label": "Referral Source",_x000D_ "value": "",_x000D_ "id": "referral_source"_x000D_ },_x000D_ {_x000D_ "label": "UTM Source",_x000D_ "value": "",_x000D_ "id": "utm_source"_x000D_ },_x000D_ {_x000D_ "label": "UTM Medium",_x000D_ "value": "",_x000D_ "id": "utm_medium"_x000D_ },_x000D_ {_x000D_ "label": "UTM Campaign",_x000D_ "value": "",_x000D_ "id": "utm_campaign"_x000D_ },_x000D_ {_x000D_ "label": "UTM Term",_x000D_ "value": "",_x000D_ "id": "utm_term"_x000D_ },_x000D_ {_x000D_ "label": "UTM Content",_x000D_ "value": "",_x000D_ "id": "utm_content"_x000D_ }_x000D_ ]_x000D_ },_x000D_ "legs": [],_x000D_ "touchpoints": null,_x000D_ "last_touch": null,_x000D_ "geo": {_x000D_ "lon": -77.1599,_x000D_ "lat": 39.0855_x000D_ },_x000D_ "timestamp": "0001-01-01T00:00:00"_x000D_ } | E29: 1 | F29: 1 | G29: 1523858 | H29: 1 | I29: 46076.921 | K29: 1771063 | L29: 1 | M29: 801 | N29: 46076.921 | P29: Yard Enjoyment Plan | Q29: 1 | R29: 4040161904 | S29: 2 | T29: 2026
A30: 3019974535 | B30: 46077.876 | C30: {_x000D_ "id": 4046120906,_x000D_ "sid": "log-call-no-answer-bd34c54d28ffe406",_x000D_ "account_id": 441826,_x000D_ "name": "Allen Truhn",_x000D_ "cnam": "Allen Truhn",_x000D_ "search": "",_x000D_ "referrer": "",_x000D_ "visitor_sid": "",_x000D_ "location": "",_x000D_ "source": "Sandbox",_x000D_ "source_id": 1814974,_x000D_ "source_sid": "TSOF6FC2D2594D22C5288F2F91D669A9D5B9BE7FEE3C6EF44F4A9EA1A63913ECD83",_x000D_ "tgid": 5681974,_x000D_ "likelihood": null,_x000D_ "duration": 0,_x000D_ "direction": "form",_x000D_ "talk_time": 0,_x000D_ "ring_time": 0,_x000D_ "hold_time": 0,_x000D_ "wait_time": 0,_x000D_ "parent_id": null,_x000D_ "email": "marytruhn@yahoo.com",_x000D_ "street": null,_x000D_ "city": "Leonardtown",_x000D_ "state": "MD",_x000D_ "country": null,_x000D_ "postal_code": "20606",_x000D_ "called_at": "2026-02-24 03:01 PM -06:00",_x000D_ "unix_time": 1771970492,_x000D_ "tracking_number_id": 3476065,_x000D_ "tracking_number_sid": "TPNC3C4B23C348AEC2EE54EFD301979CD2EFFBA32881B159867D3F4ED59E6F0B56367EFF2993536685F",_x000D_ "tracking_number": "\u002B14352541043",_x000D_ "tracking_label": "Testing Number",_x000D_ "dial_status": "no-answer",_x000D_ "is_new_caller": true,_x000D_ "indexed_at": 1.7719711E+09,_x000D_ "agent_insights": false,_x000D_ "duration_period": {_x000D_ "gte": 1771970492000,_x000D_ "lte": 1771970492000_x000D_ },_x000D_ "inbound_rate_center": {_x000D_ "country": "US",_x000D_ "prefix": "1",_x000D_ "tollfree": false_x000D_ },_x000D_ "business_number": null,_x000D_ "business_label": null,_x000D_ "receiving_number_id": null,_x000D_ "receiving_number_sid": null,_x000D_ "billed_amount": 0,_x000D_ "billed_at": "0001-01-01T00:00:00",_x000D_ "excluded": false,_x000D_ "redacted": false,_x000D_ "tracking_number_format": "(435) 254-1043",_x000D_ "business_number_format": null,_x000D_ "alternative_number": "3019974535",_x000D_ "tracking_number_bare": "4352541043",_x000D_ "caller_number_format": "(301) 997-4535",_x000D_ "caller_number_complete": "\u002B13019974535",_x000D_ "caller_number_bare": "3019974535",_x000D_ "caller_number": "\u002B13019974535",_x000D_ "caller_number_split": [_x000D_ "1",_x000D_ "301",_x000D_ "997",_x000D_ "4535"_x000D_ ],_x000D_ "contact_number": "\u002B13019974535",_x000D_ "visitor": false,_x000D_ "call_path": [_x000D_ {_x000D_ "route_name": "_OnHangup_CallSync",_x000D_ "route_id": "640990",_x000D_ "route_type": "RoutingRule",_x000D_ "started_at": "2026-02-24T15:01:33Z"_x000D_ }_x000D_ ],_x000D_ "left_talk_time": 0,_x000D_ "right_talk_time": 0,_x000D_ "transfers": [],_x000D_ "call_status": "completed",_x000D_ "status": "completed",_x000D_ "spotted": [],_x000D_ "salesforce": {},_x000D_ "audio": null,_x000D_ "is_s3_link": false,_x000D_ "callbacks": [],_x000D_ "emails": [],_x000D_ "day": "Tuesday",_x000D_ "month": "February",_x000D_ "hour": "03PM",_x000D_ "paid": {_x000D_ "source": null,_x000D_ "medium": null_x000D_ },_x000D_ "ga": {_x000D_ "cid": "441826.4046120906",_x000D_ "ga4": []_x000D_ },_x000D_ "tag_list": [],_x000D_ "latitude": 38.2916,_x000D_ "longitude": -76.6352,_x000D_ "extended_lookup_on": true,_x000D_ "form": {_x000D_ "number_to_call": "log-call-no-answer-198950643118af01",_x000D_ "customer_number_to_dial": "\u002B13019974535",_x000D_ "name": "Allen Truhn",_x000D_ "email": "marytruhn@yahoo.com",_x000D_ "trackback_id": "trackback-441826.1771970492.1963472",_x000D_ "form_id": 213071,_x000D_ "form_name": "Contact Us",_x000D_ "custom": [_x000D_ {_x000D_ "label": "Referral Source",_x000D_ "value": "",_x000D_ "id": "referral_source"_x000D_ },_x000D_ {_x000D_ "label": "UTM Source",_x000D_ "value": "",_x000D_ "id": "utm_source"_x000D_ },_x000D_ {_x000D_ "label": "UTM Medium",_x000D_ "value": "",_x000D_ "id": "utm_medium"_x000D_ },_x000D_ {_x000D_ "label": "UTM Campaign",_x000D_ "value": "",_x000D_ "id": "utm_campaign"_x000D_ },_x000D_ {_x000D_ "label": "UTM Term",_x000D_ "value": "",_x000D_ "id": "utm_term"_x000D_ },_x000D_ {_x000D_ "label": "UTM Content",_x000D_ "value": "",_x000D_ "id": "utm_content"_x000D_ }_x000D_ ]_x000D_ },_x000D_ "legs": [],_x000D_ "touchpoints": null,_x000D_ "last_touch": null,_x000D_ "geo": {_x000D_ "lon": -76.6352,_x000D_ "lat": 38.2916_x000D_ },_x000D_ "timestamp": "0001-01-01T00:00:00"_x000D_ } | E30: 0 | F30: 1 | G30: 1379704 | H30: 1 | I30: 45792.828 | K30: 1550595 | L30: 1 | M30: 650 | N30: 45792.838 | P30: Home Protection Plan | Q30: 0 | R30: 4046120906 | S30: 2 | T30: 2026
A31: 3053950810 | B31: 46079.576 | C31: {_x000D_ "id": 4049609150,_x000D_ "sid": "log-call-no-answer-874430a632905946",_x000D_ "account_id": 441826,_x000D_ "name": "Brian Tichenor",_x000D_ "cnam": "Brian Tichenor",_x000D_ "search": "",_x000D_ "referrer": "",_x000D_ "visitor_sid": "",_x000D_ "location": "",_x000D_ "source": "Sandbox",_x000D_ "source_id": 1814974,_x000D_ "source_sid": "TSOF6FC2D2594D22C5288F2F91D669A9D5B9BE7FEE3C6EF44F4A9EA1A63913ECD83",_x000D_ "tgid": 5681974,_x000D_ "likelihood": null,_x000D_ "duration": 0,_x000D_ "direction": "form",_x000D_ "talk_time": 0,_x000D_ "ring_time": 0,_x000D_ "hold_time": 0,_x000D_ "wait_time": 0,_x000D_ "parent_id": null,_x000D_ "email": "BRIANTICHENOR17@GMAIL.COM",_x000D_ "street": null,_x000D_ "city": null,_x000D_ "state": null,_x000D_ "country": null,_x000D_ "postal_code": "33001",_x000D_ "called_at": "2026-02-26 07:50 AM -06:00",_x000D_ "unix_time": 1772117423,_x000D_ "tracking_number_id": 3476065,_x000D_ "tracking_number_sid": "TPNC3C4B23C348AEC2EE54EFD301979CD2EFFBA32881B159867D3F4ED59E6F0B56367EFF2993536685F",_x000D_ "tracking_number": "\u002B14352541043",_x000D_ "tracking_label": "Testing Number",_x000D_ "dial_status": "no-answer",_x000D_ "is_new_caller": true,_x000D_ "indexed_at": 1.772118E+09,_x000D_ "agent_insights": false,_x000D_ "duration_period": {_x000D_ "gte": 1772117423000,_x000D_ "lte": 1772117423000_x000D_ },_x000D_ "inbound_rate_center": {_x000D_ "country": "US",_x000D_ "prefix": "1",_x000D_ "tollfree": false_x000D_ },_x000D_ "business_number": null,_x000D_ "business_label": null,_x000D_ "receiving_number_id": null,_x000D_ "receiving_number_sid": null,_x000D_ "billed_amount": 0,_x000D_ "billed_at": "0001-01-01T00:00:00",_x000D_ "excluded": false,_x000D_ "redacted": false,_x000D_ "tracking_number_format": "(435) 254-1043",_x000D_ "business_number_format": null,_x000D_ "alternative_number": "3053950810",_x000D_ "tracking_number_bare": "4352541043",_x000D_ "caller_number_format": "(305) 395-0810",_x000D_ "caller_number_complete": "\u002B13053950810",_x000D_ "caller_number_bare": "3053950810",_x000D_ "caller_number": "\u002B13053950810",_x000D_ "caller_number_split": [_x000D_ "1",_x000D_ "305",_x000D_ "395",_x000D_ "0810"_x000D_ ],_x000D_ "contact_number": "\u002B13053950810",_x000D_ "visitor": false,_x000D_ "call_path": [_x000D_ {_x000D_ "route_name": "_OnHangup_CallSync",_x000D_ "route_id": "640990",_x000D_ "route_type": "RoutingRule",_x000D_ "started_at": "2026-02-26T07:50:24Z"_x000D_ }_x000D_ ],_x000D_ "left_talk_time": 0,_x000D_ "right_talk_time": 0,_x000D_ "transfers": [],_x000D_ "call_status": "completed",_x000D_ "status": "completed",_x000D_ "spotted": [],_x000D_ "salesforce": {},_x000D_ "audio": null,_x000D_ "is_s3_link": false,_x000D_ "callbacks": [],_x000D_ "emails": [],_x000D_ "day": "Thursday",_x000D_ "month": "February",_x000D_ "hour": "07AM",_x000D_ "paid": {_x000D_ "source": null,_x000D_ "medium": null_x000D_ },_x000D_ "ga": {_x000D_ "cid": "441826.4049609150",_x000D_ "ga4": []_x000D_ },_x000D_ "tag_list": [],_x000D_ "latitude": 24.7149,_x000D_ "longitude": -81.0842,_x000D_ "extended_lookup_on": true,_x000D_ "form": {_x000D_ "number_to_call": "log-call-no-answer-6a0e774aaf9cd063",_x000D_ "customer_number_to_dial": "\u002B13053950810",_x000D_ "name": "Brian Tichenor",_x000D_ "email": "BRIANTICHENOR17@GMAIL.COM",_x000D_ "trackback_id": "trackback-441826.1772117423.4334946",_x000D_ "form_id": 213071,_x000D_ "form_name": "Contact Us",_x000D_ "custom": [_x000D_ {_x000D_ "label": "Referral Source",_x000D_ "value": "",_x000D_ "id": "referral_source"_x000D_ },_x000D_ {_x000D_ "label": "UTM Source",_x000D_ "value": "",_x000D_ "id": "utm_source"_x000D_ },_x000D_ {_x000D_ "label": "UTM Medium",_x000D_ "value": "",_x000D_ "id": "utm_medium"_x000D_ },_x000D_ {_x000D_ "label": "UTM Campaign",_x000D_ "value": "",_x000D_ "id": "utm_campaign"_x000D_ },_x000D_ {_x000D_ "label": "UTM Term",_x000D_ "value": "",_x000D_ "id": "utm_term"_x000D_ },_x000D_ {_x000D_ "label": "UTM Content",_x000D_ "value": "",_x000D_ "id": "utm_content"_x000D_ }_x000D_ ]_x000D_ },_x000D_ "legs": [],_x000D_ "touchpoints": null,_x000D_ "last_touch": null,_x000D_ "geo": {_x000D_ "lon": -81.0842,_x000D_ "lat": 24.7149_x000D_ },_x000D_ "timestamp": "0001-01-01T00:00:00"_x000D_ } | E31: 0 | F31: 1 | G31: 1026575 | H31: 1 | I31: 44637.642 | K31: 1059191 | L31: 1 | M31: 1014.53 | N31: 44637.642 | P31: Fox Home Protection Plan | Q31: 0 | R31: 4049609150 | S31: 2 | T31: 2026
A32: 3053950810 | B32: 46079.576 | C32: {_x000D_ "id": 4049609150,_x000D_ "sid": "log-call-no-answer-874430a632905946",_x000D_ "account_id": 441826,_x000D_ "name": "Brian Tichenor",_x000D_ "cnam": "Brian Tichenor",_x000D_ "search": "",_x000D_ "referrer": "",_x000D_ "visitor_sid": "",_x000D_ "location": "",_x000D_ "source": "Sandbox",_x000D_ "source_id": 1814974,_x000D_ "source_sid": "TSOF6FC2D2594D22C5288F2F91D669A9D5B9BE7FEE3C6EF44F4A9EA1A63913ECD83",_x000D_ "tgid": 5681974,_x000D_ "likelihood": null,_x000D_ "duration": 0,_x000D_ "direction": "form",_x000D_ "talk_time": 0,_x000D_ "ring_time": 0,_x000D_ "hold_time": 0,_x000D_ "wait_time": 0,_x000D_ "parent_id": null,_x000D_ "email": "BRIANTICHENOR17@GMAIL.COM",_x000D_ "street": null,_x000D_ "city": null,_x000D_ "state": null,_x000D_ "country": null,_x000D_ "postal_code": "33001",_x000D_ "called_at": "2026-02-26 07:50 AM -06:00",_x000D_ "unix_time": 1772117423,_x000D_ "tracking_number_id": 3476065,_x000D_ "tracking_number_sid": "TPNC3C4B23C348AEC2EE54EFD301979CD2EFFBA32881B159867D3F4ED59E6F0B56367EFF2993536685F",_x000D_ "tracking_number": "\u002B14352541043",_x000D_ "tracking_label": "Testing Number",_x000D_ "dial_status": "no-answer",_x000D_ "is_new_caller": true,_x000D_ "indexed_at": 1.772118E+09,_x000D_ "agent_insights": false,_x000D_ "duration_period": {_x000D_ "gte": 1772117423000,_x000D_ "lte": 1772117423000_x000D_ },_x000D_ "inbound_rate_center": {_x000D_ "country": "US",_x000D_ "prefix": "1",_x000D_ "tollfree": false_x000D_ },_x000D_ "business_number": null,_x000D_ "business_label": null,_x000D_ "receiving_number_id": null,_x000D_ "receiving_number_sid": null,_x000D_ "billed_amount": 0,_x000D_ "billed_at": "0001-01-01T00:00:00",_x000D_ "excluded": false,_x000D_ "redacted": false,_x000D_ "tracking_number_format": "(435) 254-1043",_x000D_ "business_number_format": null,_x000D_ "alternative_number": "3053950810",_x000D_ "tracking_number_bare": "4352541043",_x000D_ "caller_number_format": "(305) 395-0810",_x000D_ "caller_number_complete": "\u002B13053950810",_x000D_ "caller_number_bare": "3053950810",_x000D_ "caller_number": "\u002B13053950810",_x000D_ "caller_number_split": [_x000D_ "1",_x000D_ "305",_x000D_ "395",_x000D_ "0810"_x000D_ ],_x000D_ "contact_number": "\u002B13053950810",_x000D_ "visitor": false,_x000D_ "call_path": [_x000D_ {_x000D_ "route_name": "_OnHangup_CallSync",_x000D_ "route_id": "640990",_x000D_ "route_type": "RoutingRule",_x000D_ "started_at": "2026-02-26T07:50:24Z"_x000D_ }_x000D_ ],_x000D_ "left_talk_time": 0,_x000D_ "right_talk_time": 0,_x000D_ "transfers": [],_x000D_ "call_status": "completed",_x000D_ "status": "completed",_x000D_ "spotted": [],_x000D_ "salesforce": {},_x000D_ "audio": null,_x000D_ "is_s3_link": false,_x000D_ "callbacks": [],_x000D_ "emails": [],_x000D_ "day": "Thursday",_x000D_ "month": "February",_x000D_ "hour": "07AM",_x000D_ "paid": {_x000D_ "source": null,_x000D_ "medium": null_x000D_ },_x000D_ "ga": {_x000D_ "cid": "441826.4049609150",_x000D_ "ga4": []_x000D_ },_x000D_ "tag_list": [],_x000D_ "latitude": 24.7149,_x000D_ "longitude": -81.0842,_x000D_ "extended_lookup_on": true,_x000D_ "form": {_x000D_ "number_to_call": "log-call-no-answer-6a0e774aaf9cd063",_x000D_ "customer_number_to_dial": "\u002B13053950810",_x000D_ "name": "Brian Tichenor",_x000D_ "email": "BRIANTICHENOR17@GMAIL.COM",_x000D_ "trackback_id": "trackback-441826.1772117423.4334946",_x000D_ "form_id": 213071,_x000D_ "form_name": "Contact Us",_x000D_ "custom": [_x000D_ {_x000D_ "label": "Referral Source",_x000D_ "value": "",_x000D_ "id": "referral_source"_x000D_ },_x000D_ {_x000D_ "label": "UTM Source",_x000D_ "value": "",_x000D_ "id": "utm_source"_x000D_ },_x000D_ {_x000D_ "label": "UTM Medium",_x000D_ "value": "",_x000D_ "id": "utm_medium"_x000D_ },_x000D_ {_x000D_ "label": "UTM Campaign",_x000D_ "value": "",_x000D_ "id": "utm_campaign"_x000D_ },_x000D_ {_x000D_ "label": "UTM Term",_x000D_ "value": "",_x000D_ "id": "utm_term"_x000D_ },_x000D_ {_x000D_ "label": "UTM Content",_x000D_ "value": "",_x000D_ "id": "utm_content"_x000D_ }_x000D_ ]_x000D_ },_x000D_ "legs": [],_x000D_ "touchpoints": null,_x000D_ "last_touch": null,_x000D_ "geo": {_x000D_ "lon": -81.0842,_x000D_ "lat": 24.7149_x000D_ },_x000D_ "timestamp": "0001-01-01T00:00:00"_x000D_ } | E32: 0 | F32: 1 | G32: 1026575 | H32: 1 | I32: 44637.642 | K32: 1059195 | L32: 1 | M32: 1018.22 | N32: 44637.648 | P32: Sentricon | Q32: 0 | R32: 4049609150 | S32: 2 | T32: 2026
A33: 3096969411 | B33: 46077.717 | C33: {_x000D_ "id": 4045148684,_x000D_ "sid": "log-call-no-answer-c3d2229b35f13a91",_x000D_ "account_id": 441826,_x000D_ "name": "Toni Martiens",_x000D_ "cnam": "Toni Martiens",_x000D_ "search": "",_x000D_ "referrer": "",_x000D_ "visitor_sid": "",_x000D_ "location": "",_x000D_ "source": "Sandbox",_x000D_ "source_id": 1814974,_x000D_ "source_sid": "TSOF6FC2D2594D22C5288F2F91D669A9D5B9BE7FEE3C6EF44F4A9EA1A63913ECD83",_x000D_ "tgid": 5681974,_x000D_ "likelihood": null,_x000D_ "duration": 0,_x000D_ "direction": "form",_x000D_ "talk_time": 0,_x000D_ "ring_time": 0,_x000D_ "hold_time": 0,_x000D_ "wait_time": 0,_x000D_ "parent_id": null,_x000D_ "email": "tamartiens@gmail.com",_x000D_ "street": null,_x000D_ "city": null,_x000D_ "state": null,_x000D_ "country": null,_x000D_ "postal_code": "61528",_x000D_ "called_at": "2026-02-24 11:13 AM -06:00",_x000D_ "unix_time": 1771956784,_x000D_ "tracking_number_id": 3476065,_x000D_ "tracking_number_sid": "TPNC3C4B23C348AEC2EE54EFD301979CD2EFFBA32881B159867D3F4ED59E6F0B56367EFF2993536685F",_x000D_ "tracking_number": "\u002B14352541043",_x000D_ "tracking_label": "Testing Number",_x000D_ "dial_status": "no-answer",_x000D_ "is_new_caller": true,_x000D_ "indexed_at": 1.7719574E+09,_x000D_ "agent_insights": false,_x000D_ "duration_period": {_x000D_ "gte": 1771956784000,_x000D_ "lte": 1771956784000_x000D_ },_x000D_ "inbound_rate_center": {_x000D_ "country": "US",_x000D_ "prefix": "1",_x000D_ "tollfree": false_x000D_ },_x000D_ "business_number": null,_x000D_ "business_label": null,_x000D_ "receiving_number_id": null,_x000D_ "receiving_number_sid": null,_x000D_ "billed_amount": 0,_x000D_ "billed_at": "0001-01-01T00:00:00",_x000D_ "excluded": false,_x000D_ "redacted": false,_x000D_ "tracking_number_format": "(435) 254-1043",_x000D_ "business_number_format": null,_x000D_ "alternative_number": "3096969411",_x000D_ "tracking_number_bare": "4352541043",_x000D_ "caller_number_format": "(309) 696-9411",_x000D_ "caller_number_complete": "\u002B13096969411",_x000D_ "caller_number_bare": "3096969411",_x000D_ "caller_number": "\u002B13096969411",_x000D_ "caller_number_split": [_x000D_ "1",_x000D_ "309",_x000D_ "696",_x000D_ "9411"_x000D_ ],_x000D_ "contact_number": "\u002B13096969411",_x000D_ "visitor": false,_x000D_ "call_path": [_x000D_ {_x000D_ "route_name": "_OnHangup_CallSync",_x000D_ "route_id": "640990",_x000D_ "route_type": "RoutingRule",_x000D_ "started_at": "2026-02-24T11:13:06Z"_x000D_ }_x000D_ ],_x000D_ "left_talk_time": 0,_x000D_ "right_talk_time": 0,_x000D_ "transfers": [],_x000D_ "call_status": "completed",_x000D_ "status": "completed",_x000D_ "spotted": [],_x000D_ "salesforce": {},_x000D_ "audio": null,_x000D_ "is_s3_link": false,_x000D_ "callbacks": [],_x000D_ "emails": [],_x000D_ "day": "Tuesday",_x000D_ "month": "February",_x000D_ "hour": "11AM",_x000D_ "paid": {_x000D_ "source": null,_x000D_ "medium": null_x000D_ },_x000D_ "ga": {_x000D_ "cid": "441826.4045148684",_x000D_ "ga4": []_x000D_ },_x000D_ "tag_list": [],_x000D_ "latitude": 40.6931,_x000D_ "longitude": -89.5919,_x000D_ "extended_lookup_on": true,_x000D_ "form": {_x000D_ "number_to_call": "log-call-no-answer-c3aadffb17f50d7f",_x000D_ "customer_number_to_dial": "\u002B13096969411",_x000D_ "name": "Toni Martiens",_x000D_ "email": "tamartiens@gmail.com",_x000D_ "trackback_id": "trackback-441826.1771956784.6810956",_x000D_ "form_id": 213071,_x000D_ "form_name": "Contact Us",_x000D_ "custom": [_x000D_ {_x000D_ "label": "Referral Source",_x000D_ "value": "",_x000D_ "id": "referral_source"_x000D_ },_x000D_ {_x000D_ "label": "UTM Source",_x000D_ "value": "",_x000D_ "id": "utm_source"_x000D_ },_x000D_ {_x000D_ "label": "UTM Medium",_x000D_ "value": "",_x000D_ "id": "utm_medium"_x000D_ },_x000D_ {_x000D_ "label": "UTM Campaign",_x000D_ "value": "",_x000D_ "id": "utm_campaign"_x000D_ },_x000D_ {_x000D_ "label": "UTM Term",_x000D_ "value": "",_x000D_ "id": "utm_term"_x000D_ },_x000D_ {_x000D_ "label": "UTM Content",_x000D_ "value": "",_x000D_ "id": "utm_content"_x000D_ }_x000D_ ]_x000D_ },_x000D_ "legs": [],_x000D_ "touchpoints": null,_x000D_ "last_touch": null,_x000D_ "geo": {_x000D_ "lon": -89.5919,_x000D_ "lat": 40.6931_x000D_ },_x000D_ "timestamp": "0001-01-01T00:00:00"_x000D_ } | E33: 0 | F33: 1 | G33: 866423 | H33: 1 | I33: 44051.771 | K33: 851748 | L33: 1 | M33: 850.08 | N33: 44051.774 | P33: Home Protection Plan | Q33: 0 | R33: 4045148684 | S33: 2 | T33: 2026
A34: 3103862993 | B34: 46069.568 | C34: {_x000D_ "id": 4026725423,_x000D_ "sid": "log-call-no-answer-8f5912ce36b93931",_x000D_ "account_id": 441826,_x000D_ "name": "Anthony Diaz",_x000D_ "cnam": "Anthony Diaz",_x000D_ "search": "",_x000D_ "referrer": "",_x000D_ "visitor_sid": "",_x000D_ "location": "",_x000D_ "source": "Sandbox",_x000D_ "source_id": 1814974,_x000D_ "source_sid": "TSOF6FC2D2594D22C5288F2F91D669A9D5B9BE7FEE3C6EF44F4A9EA1A63913ECD83",_x000D_ "tgid": 5681974,_x000D_ "likelihood": null,_x000D_ "duration": 0,_x000D_ "direction": "form",_x000D_ "talk_time": 0,_x000D_ "ring_time": 0,_x000D_ "hold_time": 0,_x000D_ "wait_time": 0,_x000D_ "parent_id": null,_x000D_ "email": "lakerfan@gmail.com",_x000D_ "street": null,_x000D_ "city": null,_x000D_ "state": null,_x000D_ "country": null,_x000D_ "postal_code": "90247",_x000D_ "called_at": "2026-02-16 07:38 AM -06:00",_x000D_ "unix_time": 1771252680,_x000D_ "tracking_number_id": 3476065,_x000D_ "tracking_number_sid": "TPNC3C4B23C348AEC2EE54EFD301979CD2EFFBA32881B159867D3F4ED59E6F0B56367EFF2993536685F",_x000D_ "tracking_number": "\u002B14352541043",_x000D_ "tracking_label": "Testing Number",_x000D_ "dial_status": "no-answer",_x000D_ "is_new_caller": true,_x000D_ "indexed_at": 1.7712532E+09,_x000D_ "agent_insights": false,_x000D_ "duration_period": {_x000D_ "gte": 1771252680000,_x000D_ "lte": 1771252680000_x000D_ },_x000D_ "inbound_rate_center": {_x000D_ "country": "US",_x000D_ "prefix": "1",_x000D_ "tollfree": false_x000D_ },_x000D_ "business_number": null,_x000D_ "business_label": null,_x000D_ "receiving_number_id": null,_x000D_ "receiving_number_sid": null,_x000D_ "billed_amount": 0,_x000D_ "billed_at": "0001-01-01T00:00:00",_x000D_ "excluded": false,_x000D_ "redacted": false,_x000D_ "tracking_number_format": "(435) 254-1043",_x000D_ "business_number_format": null,_x000D_ "alternative_number": "3103862993",_x000D_ "tracking_number_bare": "4352541043",_x000D_ "caller_number_format": "(310) 386-2993",_x000D_ "caller_number_complete": "\u002B13103862993",_x000D_ "caller_number_bare": "3103862993",_x000D_ "caller_number": "\u002B13103862993",_x000D_ "caller_number_split": [_x000D_ "1",_x000D_ "310",_x000D_ "386",_x000D_ "2993"_x000D_ ],_x000D_ "contact_number": "\u002B13103862993",_x000D_ "visitor": false,_x000D_ "call_path": [_x000D_ {_x000D_ "route_name": "_OnHangup_CallSync",_x000D_ "route_id": "640990",_x000D_ "route_type": "RoutingRule",_x000D_ "started_at": "2026-02-16T07:38:01Z"_x000D_ }_x000D_ ],_x000D_ "left_talk_time": 0,_x000D_ "right_talk_time": 0,_x000D_ "transfers": [],_x000D_ "call_status": "completed",_x000D_ "status": "completed",_x000D_ "spotted": [],_x000D_ "salesforce": {},_x000D_ "audio": null,_x000D_ "is_s3_link": false,_x000D_ "callbacks": [],_x000D_ "emails": [],_x000D_ "day": "Monday",_x000D_ "month": "February",_x000D_ "hour": "07AM",_x000D_ "paid": {_x000D_ "source": null,_x000D_ "medium": null_x000D_ },_x000D_ "ga": {_x000D_ "cid": "441826.4026725423",_x000D_ "ga4": []_x000D_ },_x000D_ "tag_list": [],_x000D_ "latitude": 33.8865,_x000D_ "longitude": -118.307,_x000D_ "extended_lookup_on": true,_x000D_ "form": {_x000D_ "number_to_call": "log-call-no-answer-179b84cb89146a61",_x000D_ "customer_number_to_dial": "\u002B13103862993",_x000D_ "name": "Anthony Diaz",_x000D_ "email": "lakerfan@gmail.com",_x000D_ "trackback_id": "trackback-441826.1771252680.429366",_x000D_ "form_id": 213071,_x000D_ "form_name": "Contact Us",_x000D_ "custom": [_x000D_ {_x000D_ "label": "referral-source",_x000D_ "value": "",_x000D_ "id": "referralsource"_x000D_ },_x000D_ {_x000D_ "label": "utm_source",_x000D_ "value": "",_x000D_ "id": "utm_source"_x000D_ }_x000D_ ]_x000D_ },_x000D_ "legs": [],_x000D_ "touchpoints": null,_x000D_ "last_touch": null,_x000D_ "geo": {_x000D_ "lon": -118.307,_x000D_ "lat": 33.8865_x000D_ },_x000D_ "timestamp": "0001-01-01T00:00:00"_x000D_ } | E34: 0 | F34: 1 | G34: 1035401 | H34: 1 | I34: 44683.824 | K34: 1073196 | L34: 1 | M34: 797.46 | N34: 44683.831 | P34: Fox Home Protection Plan | Q34: 0 | R34: 4026725423 | S34: 2 | T34: 2026
A35: 3125051615 | B35: 46071.882 | C35: {_x000D_ "id": 4033989029,_x000D_ "sid": "log-call-no-answer-572e3a3e17563da6",_x000D_ "account_id": 441826,_x000D_ "name": "Karen johnson",_x000D_ "cnam": "Karen johnson",_x000D_ "search": "",_x000D_ "referrer": "",_x000D_ "visitor_sid": "",_x000D_ "location": "",_x000D_ "source": "Sandbox",_x000D_ "source_id": 1814974,_x000D_ "source_sid": "TSOF6FC2D2594D22C5288F2F91D669A9D5B9BE7FEE3C6EF44F4A9EA1A63913ECD83",_x000D_ "tgid": 5681974,_x000D_ "likelihood": null,_x000D_ "duration": 0,_x000D_ "direction": "form",_x000D_ "talk_time": 0,_x000D_ "ring_time": 0,_x000D_ "hold_time": 0,_x000D_ "wait_time": 0,_x000D_ "parent_id": null,_x000D_ "email": "klsj@me.com",_x000D_ "street": null,_x000D_ "city": null,_x000D_ "state": null,_x000D_ "country": null,_x000D_ "postal_code": "60601",_x000D_ "called_at": "2026-02-18 03:10 PM -06:00",_x000D_ "unix_time": 1771452610,_x000D_ "tracking_number_id": 3476065,_x000D_ "tracking_number_sid": "TPNC3C4B23C348AEC2EE54EFD301979CD2EFFBA32881B159867D3F4ED59E6F0B56367EFF2993536685F",_x000D_ "tracking_number": "\u002B14352541043",_x000D_ "tracking_label": "Testing Number",_x000D_ "dial_status": "no-answer",_x000D_ "is_new_caller": true,_x000D_ "indexed_at": 1.7714532E+09,_x000D_ "agent_insights": false,_x000D_ "duration_period": {_x000D_ "gte": 1771452610000,_x000D_ "lte": 1771452610000_x000D_ },_x000D_ "inbound_rate_center": {_x000D_ "country": "US",_x000D_ "prefix": "1",_x000D_ "tollfree": false_x000D_ },_x000D_ "business_number": null,_x000D_ "business_label": null,_x000D_ "receiving_number_id": null,_x000D_ "receiving_number_sid": null,_x000D_ "billed_amount": 0,_x000D_ "billed_at": "0001-01-01T00:00:00",_x000D_ "excluded": false,_x000D_ "redacted": false,_x000D_ "tracking_number_format": "(435) 254-1043",_x000D_ "business_number_format": null,_x000D_ "alternative_number": "3125051615",_x000D_ "tracking_number_bare": "4352541043",_x000D_ "caller_number_format": "(312) 505-1615",_x000D_ "caller_number_complete": "\u002B13125051615",_x000D_ "caller_number_bare": "3125051615",_x000D_ "caller_number": "\u002B13125051615",_x000D_ "caller_number_split": [_x000D_ "1",_x000D_ "312",_x000D_ "505",_x000D_ "1615"_x000D_ ],_x000D_ "contact_number": "\u002B13125051615",_x000D_ "visitor": false,_x000D_ "call_path": [_x000D_ {_x000D_ "route_name": "_OnHangup_CallSync",_x000D_ "route_id": "640990",_x000D_ "route_type": "RoutingRule",_x000D_ "started_at": "2026-02-18T15:10:11Z"_x000D_ }_x000D_ ],_x000D_ "left_talk_time": 0,_x000D_ "right_talk_time": 0,_x000D_ "transfers": [],_x000D_ "call_status": "completed",_x000D_ "status": "completed",_x000D_ "spotted": [],_x000D_ "salesforce": {},_x000D_ "audio": null,_x000D_ "is_s3_link": false,_x000D_ "callbacks": [],_x000D_ "emails": [],_x000D_ "day": "Wednesday",_x000D_ "month": "February",_x000D_ "hour": "03PM",_x000D_ "paid": {_x000D_ "source": null,_x000D_ "medium": null_x000D_ },_x000D_ "ga": {_x000D_ "cid": "441826.4033989029",_x000D_ "ga4": []_x000D_ },_x000D_ "tag_list": [],_x000D_ "latitude": 41.8835,_x000D_ "longitude": -87.6352,_x000D_ "extended_lookup_on": true,_x000D_ "form": {_x000D_ "number_to_call": "log-call-no-answer-3f3202bc7bf57ecb",_x000D_ "customer_number_to_dial": "\u002B13125051615",_x000D_ "name": "Karen johnson",_x000D_ "email": "klsj@me.com",_x000D_ "trackback_id": "trackback-441826.1771452610.2131455",_x000D_ "form_id": 213071,_x000D_ "form_name": "Contact Us",_x000D_ "custom": [_x000D_ {_x000D_ "label": "Referral Source",_x000D_ "value": "",_x000D_ "id": "referral_source"_x000D_ },_x000D_ {_x000D_ "label": "UTM Source",_x000D_ "value": "",_x000D_ "id": "utm_source"_x000D_ },_x000D_ {_x000D_ "label": "UTM Medium",_x000D_ "value": "",_x000D_ "id": "utm_medium"_x000D_ },_x000D_ {_x000D_ "label": "UTM Campaign",_x000D_ "value": "",_x000D_ "id": "utm_campaign"_x000D_ },_x000D_ {_x000D_ "label": "UTM Term",_x000D_ "value": "",_x000D_ "id": "utm_term"_x000D_ },_x000D_ {_x000D_ "label": "UTM Content",_x000D_ "value": "",_x000D_ "id": "utm_content"_x000D_ }_x000D_ ]_x000D_ },_x000D_ "legs": [],_x000D_ "touchpoints": null,_x000D_ "last_touch": null,_x000D_ "geo": {_x000D_ "lon": -87.6352,_x000D_ "lat": 41.8835_x000D_ },_x000D_ "timestamp": "0001-01-01T00:00:00"_x000D_ } | E35: 0 | F35: 1 | Q35: 0 | R35: 4033989029 | S35: 2 | T35: 2026
A36: 3152639548 | B36: 46078.672 | C36: {_x000D_ "id": 4047509627,_x000D_ "sid": "log-call-no-answer-3c5e4686ca7e9c4d",_x000D_ "account_id": 441826,_x000D_ "name": "Julie Valentine",_x000D_ "cnam": "Julie Valentine",_x000D_ "search": "",_x000D_ "referrer": "",_x000D_ "visitor_sid": "",_x000D_ "location": "",_x000D_ "source": "Sandbox",_x000D_ "source_id": 1814974,_x000D_ "source_sid": "TSOF6FC2D2594D22C5288F2F91D669A9D5B9BE7FEE3C6EF44F4A9EA1A63913ECD83",_x000D_ "tgid": 5681974,_x000D_ "likelihood": null,_x000D_ "duration": 0,_x000D_ "direction": "form",_x000D_ "talk_time": 0,_x000D_ "ring_time": 0,_x000D_ "hold_time": 0,_x000D_ "wait_time": 0,_x000D_ "parent_id": null,_x000D_ "email": "jvalentine9@gmail.com",_x000D_ "street": null,_x000D_ "city": null,_x000D_ "state": null,_x000D_ "country": null,_x000D_ "postal_code": "13031",_x000D_ "called_at": "2026-02-25 10:07 AM -06:00",_x000D_ "unix_time": 1772039241,_x000D_ "tracking_number_id": 3476065,_x000D_ "tracking_number_sid": "TPNC3C4B23C348AEC2EE54EFD301979CD2EFFBA32881B159867D3F4ED59E6F0B56367EFF2993536685F",_x000D_ "tracking_number": "\u002B14352541043",_x000D_ "tracking_label": "Testing Number",_x000D_ "dial_status": "no-answer",_x000D_ "is_new_caller": true,_x000D_ "indexed_at": 1.7720398E+09,_x000D_ "agent_insights": false,_x000D_ "duration_period": {_x000D_ "gte": 1772039241000,_x000D_ "lte": 1772039241000_x000D_ },_x000D_ "inbound_rate_center": {_x000D_ "country": "US",_x000D_ "prefix": "1",_x000D_ "tollfree": false_x000D_ },_x000D_ "business_number": null,_x000D_ "business_label": null,_x000D_ "receiving_number_id": null,_x000D_ "receiving_number_sid": null,_x000D_ "billed_amount": 0,_x000D_ "billed_at": "0001-01-01T00:00:00",_x000D_ "excluded": false,_x000D_ "redacted": false,_x000D_ "tracking_number_format": "(435) 254-1043",_x000D_ "business_number_format": null,_x000D_ "alternative_number": "3152639548",_x000D_ "tracking_number_bare": "4352541043",_x000D_ "caller_number_format": "(315) 263-9548",_x000D_ "caller_number_complete": "\u002B13152639548",_x000D_ "caller_number_bare": "3152639548",_x000D_ "caller_number": "\u002B13152639548",_x000D_ "caller_number_split": [_x000D_ "1",_x000D_ "315",_x000D_ "263",_x000D_ "9548"_x000D_ ],_x000D_ "contact_number": "\u002B13152639548",_x000D_ "visitor": false,_x000D_ "call_path": [_x000D_ {_x000D_ "route_name": "_OnHangup_CallSync",_x000D_ "route_id": "640990",_x000D_ "route_type": "RoutingRule",_x000D_ "started_at": "2026-02-25T10:07:23Z"_x000D_ }_x000D_ ],_x000D_ "left_talk_time": 0,_x000D_ "right_talk_time": 0,_x000D_ "transfers": [],_x000D_ "call_status": "completed",_x000D_ "status": "completed",_x000D_ "spotted": [],_x000D_ "salesforce": {},_x000D_ "audio": null,_x000D_ "is_s3_link": false,_x000D_ "callbacks": [],_x000D_ "emails": [],_x000D_ "day": "Wednesday",_x000D_ "month": "February",_x000D_ "hour": "10AM",_x000D_ "paid": {_x000D_ "source": null,_x000D_ "medium": null_x000D_ },_x000D_ "ga": {_x000D_ "cid": "441826.4047509627",_x000D_ "ga4": []_x000D_ },_x000D_ "tag_list": [],_x000D_ "latitude": 43.0465,_x000D_ "longitude": -76.1508,_x000D_ "extended_lookup_on": true,_x000D_ "form": {_x000D_ "number_to_call": "log-call-no-answer-32df592993d58d15",_x000D_ "customer_number_to_dial": "\u002B13152639548",_x000D_ "name": "Julie Valentine",_x000D_ "email": "jvalentine9@gmail.com",_x000D_ "trackback_id": "trackback-441826.1772039241.7861614",_x000D_ "form_id": 213071,_x000D_ "form_name": "Contact Us",_x000D_ "custom": [_x000D_ {_x000D_ "label": "Referral Source",_x000D_ "value": "",_x000D_ "id": "referral_source"_x000D_ },_x000D_ {_x000D_ "label": "UTM Source",_x000D_ "value": "",_x000D_ "id": "utm_source"_x000D_ },_x000D_ {_x000D_ "label": "UTM Medium",_x000D_ "value": "",_x000D_ "id": "utm_medium"_x000D_ },_x000D_ {_x000D_ "label": "UTM Campaign",_x000D_ "value": "",_x000D_ "id": "utm_campaign"_x000D_ },_x000D_ {_x000D_ "label": "UTM Term",_x000D_ "value": "",_x000D_ "id": "utm_term"_x000D_ },_x000D_ {_x000D_ "label": "UTM Content",_x000D_ "value": "",_x000D_ "id": "utm_content"_x000D_ }_x000D_ ]_x000D_ },_x000D_ "legs": [],_x000D_ "touchpoints": null,_x000D_ "last_touch": null,_x000D_ "geo": {_x000D_ "lon": -76.1508,_x000D_ "lat": 43.0465_x000D_ },_x000D_ "timestamp": "0001-01-01T00:00:00"_x000D_ } | E36: 0 | F36: 1 | Q36: 0 | R36: 4047509627 | S36: 2 | T36: 2026
A37: 3152893643 | B37: 46071.961 | C37: {_x000D_ "id": 4034287838,_x000D_ "sid": "log-call-no-answer-ba79cad7b259d236",_x000D_ "account_id": 441826,_x000D_ "name": "D e e n a Stevenson - Schwab",_x000D_ "cnam": "D e e n a Stevenson - Schwab",_x000D_ "search": "",_x000D_ "referrer": "",_x000D_ "visitor_sid": "",_x000D_ "location": "",_x000D_ "source": "Sandbox",_x000D_ "source_id": 1814974,_x000D_ "source_sid": "TSOF6FC2D2594D22C5288F2F91D669A9D5B9BE7FEE3C6EF44F4A9EA1A63913ECD83",_x000D_ "tgid": 5681974,_x000D_ "likelihood": null,_x000D_ "duration": 0,_x000D_ "direction": "form",_x000D_ "talk_time": 0,_x000D_ "ring_time": 0,_x000D_ "hold_time": 0,_x000D_ "wait_time": 0,_x000D_ "parent_id": null,_x000D_ "email": "Sadiesch@aol.com",_x000D_ "street": null,_x000D_ "city": null,_x000D_ "state": null,_x000D_ "country": null,_x000D_ "postal_code": "13031",_x000D_ "called_at": "2026-02-18 05:04 PM -06:00",_x000D_ "unix_time": 1771459458,_x000D_ "tracking_number_id": 3476065,_x000D_ "tracking_number_sid": "TPNC3C4B23C348AEC2EE54EFD301979CD2EFFBA32881B159867D3F4ED59E6F0B56367EFF2993536685F",_x000D_ "tracking_number": "\u002B14352541043",_x000D_ "tracking_label": "Testing Number",_x000D_ "dial_status": "no-answer",_x000D_ "is_new_caller": true,_x000D_ "indexed_at": 1.7714601E+09,_x000D_ "agent_insights": false,_x000D_ "duration_period": {_x000D_ "gte": 1771459458000,_x000D_ "lte": 1771459458000_x000D_ },_x000D_ "inbound_rate_center": {_x000D_ "country": "US",_x000D_ "prefix": "1",_x000D_ "tollfree": false_x000D_ },_x000D_ "business_number": null,_x000D_ "business_label": null,_x000D_ "receiving_number_id": null,_x000D_ "receiving_number_sid": null,_x000D_ "billed_amount": 0,_x000D_ "billed_at": "0001-01-01T00:00:00",_x000D_ "excluded": false,_x000D_ "redacted": false,_x000D_ "tracking_number_format": "(435) 254-1043",_x000D_ "business_number_format": null,_x000D_ "alternative_number": "3152893643",_x000D_ "tracking_number_bare": "4352541043",_x000D_ "caller_number_format": "(315) 289-3643",_x000D_ "caller_number_complete": "\u002B13152893643",_x000D_ "caller_number_bare": "3152893643",_x000D_ "caller_number": "\u002B13152893643",_x000D_ "caller_number_split": [_x000D_ "1",_x000D_ "315",_x000D_ "289",_x000D_ "3643"_x000D_ ],_x000D_ "contact_number": "\u002B13152893643",_x000D_ "visitor": false,_x000D_ "call_path": [_x000D_ {_x000D_ "route_name": "_OnHangup_CallSync",_x000D_ "route_id": "640990",_x000D_ "route_type": "RoutingRule",_x000D_ "started_at": "2026-02-18T17:04:19Z"_x000D_ }_x000D_ ],_x000D_ "left_talk_time": 0,_x000D_ "right_talk_time": 0,_x000D_ "transfers": [],_x000D_ "call_status": "completed",_x000D_ "status": "completed",_x000D_ "spotted": [],_x000D_ "salesforce": {},_x000D_ "audio": null,_x000D_ "is_s3_link": false,_x000D_ "callbacks": [],_x000D_ "emails": [],_x000D_ "day": "Wednesday",_x000D_ "month": "February",_x000D_ "hour": "05PM",_x000D_ "paid": {_x000D_ "source": null,_x000D_ "medium": null_x000D_ },_x000D_ "ga": {_x000D_ "cid": "441826.4034287838",_x000D_ "ga4": []_x000D_ },_x000D_ "tag_list": [],_x000D_ "latitude": 43.0465,_x000D_ "longitude": -76.1508,_x000D_ "extended_lookup_on": true,_x000D_ "form": {_x000D_ "number_to_call": "log-call-no-answer-e18239416591a7dc",_x000D_ "customer_number_to_dial": "\u002B13152893643",_x000D_ "name": "D e e n a Stevenson - Schwab",_x000D_ "email": "Sadiesch@aol.com",_x000D_ "trackback_id": "trackback-441826.1771459458.3476863",_x000D_ "form_id": 213071,_x000D_ "form_name": "Contact Us",_x000D_ "custom": [_x000D_ {_x000D_ "label": "Referral Source",_x000D_ "value": "",_x000D_ "id": "referral_source"_x000D_ },_x000D_ {_x000D_ "label": "UTM Source",_x000D_ "value": "",_x000D_ "id": "utm_source"_x000D_ },_x000D_ {_x000D_ "label": "UTM Medium",_x000D_ "value": "",_x000D_ "id": "utm_medium"_x000D_ },_x000D_ {_x000D_ "label": "UTM Campaign",_x000D_ "value": "",_x000D_ "id": "utm_campaign"_x000D_ },_x000D_ {_x000D_ "label": "UTM Term",_x000D_ "value": "",_x000D_ "id": "utm_term"_x000D_ },_x000D_ {_x000D_ "label": "UTM Content",_x000D_ "value": "",_x000D_ "id": "utm_content"_x000D_ }_x000D_ ]_x000D_ },_x000D_ "legs": [],_x000D_ "touchpoints": [_x000D_ {_x000D_ "call_id": 4034287838,_x000D_ "time": "2026-02-19T00:04:18Z",_x000D_ "touch_type": "form",_x000D_ "clickid": null,_x000D_ "type": null,_x000D_ "source": "Sandbox",_x000D_ "medium": null,_x000D_ "position": "last",_x000D_ "weight": 100_x000D_ }_x000D_ ],_x000D_ "last_touch": "Sandbox/",_x000D_ "geo": {_x000D_ "lon": -76.1508,_x000D_ "lat": 43.0465_x000D_ },_x000D_ "timestamp": "0001-01-01T00:00:00"_x000D_ } | E37: 0 | F37: 1 | G37: 1326707 | H37: 1 | I37: 45534.797 | K37: 1461034 | L37: 1 | M37: 860 | N37: 45534.797 | P37: Fox Home Protection Plan | Q37: 0 | R37: 4034287838 | S37: 2 | T37: 2026
A38: 3155295032 | B38: 46078.992 | C38: {_x000D_ "id": 4049184926,_x000D_ "sid": "log-call-no-answer-3348d47844107b60",_x000D_ "account_id": 441826,_x000D_ "name": "Michael Lee",_x000D_ "cnam": "Michael Lee",_x000D_ "search": "",_x000D_ "referrer": "",_x000D_ "visitor_sid": "",_x000D_ "location": "",_x000D_ "source": "Sandbox",_x000D_ "source_id": 1814974,_x000D_ "source_sid": "TSOF6FC2D2594D22C5288F2F91D669A9D5B9BE7FEE3C6EF44F4A9EA1A63913ECD83",_x000D_ "tgid": 5681974,_x000D_ "likelihood": null,_x000D_ "duration": 0,_x000D_ "direction": "form",_x000D_ "talk_time": 0,_x000D_ "ring_time": 0,_x000D_ "hold_time": 0,_x000D_ "wait_time": 0,_x000D_ "parent_id": null,_x000D_ "email": "mike.patlee@gmail.com",_x000D_ "street": null,_x000D_ "city": null,_x000D_ "state": null,_x000D_ "country": null,_x000D_ "postal_code": "13093",_x000D_ "called_at": "2026-02-25 05:48 PM -06:00",_x000D_ "unix_time": 1772066936,_x000D_ "tracking_number_id": 3476065,_x000D_ "tracking_number_sid": "TPNC3C4B23C348AEC2EE54EFD301979CD2EFFBA32881B159867D3F4ED59E6F0B56367EFF2993536685F",_x000D_ "tracking_number": "\u002B14352541043",_x000D_ "tracking_label": "Testing Number",_x000D_ "dial_status": "no-answer",_x000D_ "is_new_caller": true,_x000D_ "indexed_at": 1.7720676E+09,_x000D_ "agent_insights": false,_x000D_ "duration_period": {_x000D_ "gte": 1772066936000,_x000D_ "lte": 1772066936000_x000D_ },_x000D_ "inbound_rate_center": {_x000D_ "country": "US",_x000D_ "prefix": "1",_x000D_ "tollfree": false_x000D_ },_x000D_ "business_number": null,_x000D_ "business_label": null,_x000D_ "receiving_number_id": null,_x000D_ "receiving_number_sid": null,_x000D_ "billed_amount": 0,_x000D_ "billed_at": "0001-01-01T00:00:00",_x000D_ "excluded": false,_x000D_ "redacted": false,_x000D_ "tracking_number_format": "(435) 254-1043",_x000D_ "business_number_format": null,_x000D_ "alternative_number": "3155295032",_x000D_ "tracking_number_bare": "4352541043",_x000D_ "caller_number_format": "(315) 529-5032",_x000D_ "caller_number_complete": "\u002B13155295032",_x000D_ "caller_number_bare": "3155295032",_x000D_ "caller_number": "\u002B13155295032",_x000D_ "caller_number_split": [_x000D_ "1",_x000D_ "315",_x000D_ "529",_x000D_ "5032"_x000D_ ],_x000D_ "contact_number": "\u002B13155295032",_x000D_ "visitor": false,_x000D_ "call_path": [_x000D_ {_x000D_ "route_name": "_OnHangup_CallSync",_x000D_ "route_id": "640990",_x000D_ "route_type": "RoutingRule",_x000D_ "started_at": "2026-02-25T17:48:57Z"_x000D_ }_x000D_ ],_x000D_ "left_talk_time": 0,_x000D_ "right_talk_time": 0,_x000D_ "transfers": [],_x000D_ "call_status": "completed",_x000D_ "status": "completed",_x000D_ "spotted": [],_x000D_ "salesforce": {},_x000D_ "audio": null,_x000D_ "is_s3_link": false,_x000D_ "callbacks": [],_x000D_ "emails": [],_x000D_ "day": "Wednesday",_x000D_ "month": "February",_x000D_ "hour": "05PM",_x000D_ "paid": {_x000D_ "source": null,_x000D_ "medium": null_x000D_ },_x000D_ "ga": {_x000D_ "cid": "441826.4049184926",_x000D_ "ga4": []_x000D_ },_x000D_ "tag_list": [],_x000D_ "latitude": 43.4542,_x000D_ "longitude": -76.511,_x000D_ "extended_lookup_on": true,_x000D_ "form": {_x000D_ "number_to_call": "log-call-no-answer-47cea9aaad87e97f",_x000D_ "customer_number_to_dial": "\u002B13155295032",_x000D_ "name": "Michael Lee",_x000D_ "email": "mike.patlee@gmail.com",_x000D_ "trackback_id": "trackback-441826.1772066936.4993958",_x000D_ "form_id": 213071,_x000D_ "form_name": "Contact Us",_x000D_ "custom": [_x000D_ {_x000D_ "label": "Referral Source",_x000D_ "value": "",_x000D_ "id": "referral_source"_x000D_ },_x000D_ {_x000D_ "label": "UTM Source",_x000D_ "value": "",_x000D_ "id": "utm_source"_x000D_ },_x000D_ {_x000D_ "label": "UTM Medium",_x000D_ "value": "",_x000D_ "id": "utm_medium"_x000D_ },_x000D_ {_x000D_ "label": "UTM Campaign",_x000D_ "value": "",_x000D_ "id": "utm_campaign"_x000D_ },_x000D_ {_x000D_ "label": "UTM Term",_x000D_ "value": "",_x000D_ "id": "utm_term"_x000D_ },_x000D_ {_x000D_ "label": "UTM Content",_x000D_ "value": "",_x000D_ "id": "utm_content"_x000D_ }_x000D_ ]_x000D_ },_x000D_ "legs": [],_x000D_ "touchpoints": null,_x000D_ "last_touch": null,_x000D_ "geo": {_x000D_ "lon": -76.511,_x000D_ "lat": 43.4542_x000D_ },_x000D_ "timestamp": "0001-01-01T00:00:00"_x000D_ } | E38: 0 | F38: 1 | G38: 1033384 | H38: 1 | I38: 44676.893 | K38: 1069522 | L38: 1 | M38: 932.76 | N38: 44676.892 | P38: Fox Home Protection Plan | Q38: 0 | R38: 4049184926 | S38: 2 | T38: 2026
A39: 3155764464 | B39: 46074.702 | C39: {_x000D_ "id": 4039975898,_x000D_ "sid": "log-call-no-answer-5feca6abf6e635f4",_x000D_ "account_id": 441826,_x000D_ "name": "Marjorie Dalke",_x000D_ "cnam": "Marjorie Dalke",_x000D_ "search": "",_x000D_ "referrer": "",_x000D_ "visitor_sid": "",_x000D_ "location": "",_x000D_ "source": "Sandbox",_x000D_ "source_id": 1814974,_x000D_ "source_sid": "TSOF6FC2D2594D22C5288F2F91D669A9D5B9BE7FEE3C6EF44F4A9EA1A63913ECD83",_x000D_ "tgid": 5681974,_x000D_ "likelihood": null,_x000D_ "duration": 0,_x000D_ "direction": "form",_x000D_ "talk_time": 0,_x000D_ "ring_time": 0,_x000D_ "hold_time": 0,_x000D_ "wait_time": 0,_x000D_ "parent_id": null,_x000D_ "email": "maggie2136@gmail.com",_x000D_ "street": null,_x000D_ "city": null,_x000D_ "state": null,_x000D_ "country": null,_x000D_ "postal_code": "14505",_x000D_ "called_at": "2026-02-21 10:51 AM -06:00",_x000D_ "unix_time": 1771696295,_x000D_ "tracking_number_id": 3476065,_x000D_ "tracking_number_sid": "TPNC3C4B23C348AEC2EE54EFD301979CD2EFFBA32881B159867D3F4ED59E6F0B56367EFF2993536685F",_x000D_ "tracking_number": "\u002B14352541043",_x000D_ "tracking_label": "Testing Number",_x000D_ "dial_status": "no-answer",_x000D_ "is_new_caller": true,_x000D_ "indexed_at": 1.7716969E+09,_x000D_ "agent_insights": false,_x000D_ "duration_period": {_x000D_ "gte": 1771696295000,_x000D_ "lte": 1771696295000_x000D_ },_x000D_ "inbound_rate_center": {_x000D_ "country": "US",_x000D_ "prefix": "1",_x000D_ "tollfree": false_x000D_ },_x000D_ "business_number": null,_x000D_ "business_label": null,_x000D_ "receiving_number_id": null,_x000D_ "receiving_number_sid": null,_x000D_ "billed_amount": 0,_x000D_ "billed_at": "0001-01-01T00:00:00",_x000D_ "excluded": false,_x000D_ "redacted": false,_x000D_ "tracking_number_format": "(435) 254-1043",_x000D_ "business_number_format": null,_x000D_ "alternative_number": "3155764464",_x000D_ "tracking_number_bare": "4352541043",_x000D_ "caller_number_format": "(315) 576-4464",_x000D_ "caller_number_complete": "\u002B13155764464",_x000D_ "caller_number_bare": "3155764464",_x000D_ "caller_number": "\u002B13155764464",_x000D_ "caller_number_split": [_x000D_ "1",_x000D_ "315",_x000D_ "576",_x000D_ "4464"_x000D_ ],_x000D_ "contact_number": "\u002B13155764464",_x000D_ "visitor": false,_x000D_ "call_path": [_x000D_ {_x000D_ "route_name": "_OnHangup_CallSync",_x000D_ "route_id": "640990",_x000D_ "route_type": "RoutingRule",_x000D_ "started_at": "2026-02-21T10:51:36Z"_x000D_ }_x000D_ ],_x000D_ "left_talk_time": 0,_x000D_ "right_talk_time": 0,_x000D_ "transfers": [],_x000D_ "call_status": "completed",_x000D_ "status": "completed",_x000D_ "spotted": [],_x000D_ "salesforce": {},_x000D_ "audio": null,_x000D_ "is_s3_link": false,_x000D_ "callbacks": [],_x000D_ "emails": [],_x000D_ "day": "Saturday",_x000D_ "month": "February",_x000D_ "hour": "10AM",_x000D_ "paid": {_x000D_ "source": null,_x000D_ "medium": null_x000D_ },_x000D_ "ga": {_x000D_ "cid": "441826.4039975898",_x000D_ "ga4": []_x000D_ },_x000D_ "tag_list": [],_x000D_ "latitude": 43.1406,_x000D_ "longitude": -77.1892,_x000D_ "extended_lookup_on": true,_x000D_ "form": {_x000D_ "number_to_call": "log-call-no-answer-ea80a0e37ee49c43",_x000D_ "customer_number_to_dial": "\u002B13155764464",_x000D_ "name": "Marjorie Dalke",_x000D_ "email": "maggie2136@gmail.com",_x000D_ "trackback_id": "trackback-441826.1771696295.1032856",_x000D_ "form_id": 213071,_x000D_ "form_name": "Contact Us",_x000D_ "custom": [_x000D_ {_x000D_ "label": "Referral Source",_x000D_ "value": "",_x000D_ "id": "referral_source"_x000D_ },_x000D_ {_x000D_ "label": "UTM Source",_x000D_ "value": "",_x000D_ "id": "utm_source"_x000D_ },_x000D_ {_x000D_ "label": "UTM Medium",_x000D_ "value": "",_x000D_ "id": "utm_medium"_x000D_ },_x000D_ {_x000D_ "label": "UTM Campaign",_x000D_ "value": "",_x000D_ "id": "utm_campaign"_x000D_ },_x000D_ {_x000D_ "label": "UTM Term",_x000D_ "value": "",_x000D_ "id": "utm_term"_x000D_ },_x000D_ {_x000D_ "label": "UTM Content",_x000D_ "value": "",_x000D_ "id": "utm_content"_x000D_ }_x000D_ ]_x000D_ },_x000D_ "legs": [],_x000D_ "touchpoints": null,_x000D_ "last_touch": null,_x000D_ "geo": {_x000D_ "lon": -77.1892,_x000D_ "lat": 43.1406_x000D_ },_x000D_ "timestamp": "0001-01-01T00:00:00"_x000D_ } | E39: 0 | F39: 1 | Q39: 0 | R39: 4039975898 | S39: 2 | T39: 2026
A40: 3178282410 | B40: 46071.915 | C40: {_x000D_ "id": 4034149934,_x000D_ "sid": "log-call-no-answer-72f740532d3751b6",_x000D_ "account_id": 441826,_x000D_ "name": "Leigh Pauszek",_x000D_ "cnam": "Leigh Pauszek",_x000D_ "search": "",_x000D_ "referrer": "",_x000D_ "visitor_sid": "",_x000D_ "location": "",_x000D_ "source": "Sandbox",_x000D_ "source_id": 1814974,_x000D_ "source_sid": "TSOF6FC2D2594D22C5288F2F91D669A9D5B9BE7FEE3C6EF44F4A9EA1A63913ECD83",_x000D_ "tgid": 5681974,_x000D_ "likelihood": null,_x000D_ "duration": 0,_x000D_ "direction": "form",_x000D_ "talk_time": 0,_x000D_ "ring_time": 0,_x000D_ "hold_time": 0,_x000D_ "wait_time": 0,_x000D_ "parent_id": null,_x000D_ "email": "leighpauszek@icloud.com",_x000D_ "street": null,_x000D_ "city": null,_x000D_ "state": null,_x000D_ "country": null,_x000D_ "postal_code": "46107",_x000D_ "called_at": "2026-02-18 03:57 PM -06:00",_x000D_ "unix_time": 1771455430,_x000D_ "tracking_number_id": 3476065,_x000D_ "tracking_number_sid": "TPNC3C4B23C348AEC2EE54EFD301979CD2EFFBA32881B159867D3F4ED59E6F0B56367EFF2993536685F",_x000D_ "tracking_number": "\u002B14352541043",_x000D_ "tracking_label": "Testing Number",_x000D_ "dial_status": "no-answer",_x000D_ "is_new_caller": true,_x000D_ "indexed_at": 1.771456E+09,_x000D_ "agent_insights": false,_x000D_ "duration_period": {_x000D_ "gte": 1771455430000,_x000D_ "lte": 1771455430000_x000D_ },_x000D_ "inbound_rate_center": {_x000D_ "country": "US",_x000D_ "prefix": "1",_x000D_ "tollfree": false_x000D_ },_x000D_ "business_number": null,_x000D_ "business_label": null,_x000D_ "receiving_number_id": null,_x000D_ "receiving_number_sid": null,_x000D_ "billed_amount": 0,_x000D_ "billed_at": "0001-01-01T00:00:00",_x000D_ "excluded": false,_x000D_ "redacted": false,_x000D_ "tracking_number_format": "(435) 254-1043",_x000D_ "business_number_format": null,_x000D_ "alternative_number": "3178282410",_x000D_ "tracking_number_bare": "4352541043",_x000D_ "caller_number_format": "(317) 828-2410",_x000D_ "caller_number_complete": "\u002B13178282410",_x000D_ "caller_number_bare": "3178282410",_x000D_ "caller_number": "\u002B13178282410",_x000D_ "caller_number_split": [_x000D_ "1",_x000D_ "317",_x000D_ "828",_x000D_ "2410"_x000D_ ],_x000D_ "contact_number": "\u002B13178282410",_x000D_ "visitor": false,_x000D_ "call_path": [_x000D_ {_x000D_ "route_name": "_OnHangup_CallSync",_x000D_ "route_id": "640990",_x000D_ "route_type": "RoutingRule",_x000D_ "started_at": "2026-02-18T15:57:11Z"_x000D_ }_x000D_ ],_x000D_ "left_talk_time": 0,_x000D_ "right_talk_time": 0,_x000D_ "transfers": [],_x000D_ "call_status": "completed",_x000D_ "status": "completed",_x000D_ "spotted": [],_x000D_ "salesforce": {},_x000D_ "audio": null,_x000D_ "is_s3_link": false,_x000D_ "callbacks": [],_x000D_ "emails": [],_x000D_ "day": "Wednesday",_x000D_ "month": "February",_x000D_ "hour": "03PM",_x000D_ "paid": {_x000D_ "source": null,_x000D_ "medium": null_x000D_ },_x000D_ "ga": {_x000D_ "cid": "441826.4034149934",_x000D_ "ga4": []_x000D_ },_x000D_ "tag_list": [],_x000D_ "latitude": 39.7711,_x000D_ "longitude": -86.1574,_x000D_ "extended_lookup_on": true,_x000D_ "form": {_x000D_ "number_to_call": "log-call-no-answer-65ba97f4b06d379e",_x000D_ "customer_number_to_dial": "\u002B13178282410",_x000D_ "name": "Leigh Pauszek",_x000D_ "email": "leighpauszek@icloud.com",_x000D_ "trackback_id": "trackback-441826.1771455430.0720356",_x000D_ "form_id": 213071,_x000D_ "form_name": "Contact Us",_x000D_ "custom": [_x000D_ {_x000D_ "label": "Referral Source",_x000D_ "value": "",_x000D_ "id": "referral_source"_x000D_ },_x000D_ {_x000D_ "label": "UTM Source",_x000D_ "value": "",_x000D_ "id": "utm_source"_x000D_ },_x000D_ {_x000D_ "label": "UTM Medium",_x000D_ "value": "",_x000D_ "id": "utm_medium"_x000D_ },_x000D_ {_x000D_ "label": "UTM Campaign",_x000D_ "value": "",_x000D_ "id": "utm_campaign"_x000D_ },_x000D_ {_x000D_ "label": "UTM Term",_x000D_ "value": "",_x000D_ "id": "utm_term"_x000D_ },_x000D_ {_x000D_ "label": "UTM Content",_x000D_ "value": "",_x000D_ "id": "utm_content"_x000D_ }_x000D_ ]_x000D_ },_x000D_ "legs": [],_x000D_ "touchpoints": null,_x000D_ "last_touch": null,_x000D_ "geo": {_x000D_ "lon": -86.1574,_x000D_ "lat": 39.7711_x000D_ },_x000D_ "timestamp": "0001-01-01T00:00:00"_x000D_ } | E40: 0 | F40: 1 | Q40: 0 | R40: 4034149934 | S40: 2 | T40: 2026
A41: 3199302733 | B41: 46079.526 | C41: {_x000D_ "id": 4049439926,_x000D_ "sid": "log-call-no-answer-a303a8ac82f01cbf",_x000D_ "account_id": 441826,_x000D_ "name": "Michele Mason",_x000D_ "cnam": "Michele Mason",_x000D_ "search": "",_x000D_ "referrer": "",_x000D_ "visitor_sid": "",_x000D_ "location": "",_x000D_ "source": "Sandbox",_x000D_ "source_id": 1814974,_x000D_ "source_sid": "TSOF6FC2D2594D22C5288F2F91D669A9D5B9BE7FEE3C6EF44F4A9EA1A63913ECD83",_x000D_ "tgid": 5681974,_x000D_ "likelihood": null,_x000D_ "duration": 0,_x000D_ "direction": "form",_x000D_ "talk_time": 0,_x000D_ "ring_time": 0,_x000D_ "hold_time": 0,_x000D_ "wait_time": 0,_x000D_ "parent_id": null,_x000D_ "email": "themason4@mchsi.com",_x000D_ "street": null,_x000D_ "city": null,_x000D_ "state": null,_x000D_ "country": null,_x000D_ "postal_code": "52240",_x000D_ "called_at": "2026-02-26 06:37 AM -06:00",_x000D_ "unix_time": 1772113038,_x000D_ "tracking_number_id": 3476065,_x000D_ "tracking_number_sid": "TPNC3C4B23C348AEC2EE54EFD301979CD2EFFBA32881B159867D3F4ED59E6F0B56367EFF2993536685F",_x000D_ "tracking_number": "\u002B14352541043",_x000D_ "tracking_label": "Testing Number",_x000D_ "dial_status": "no-answer",_x000D_ "is_new_caller": true,_x000D_ "indexed_at": 1.7721137E+09,_x000D_ "agent_insights": false,_x000D_ "duration_period": {_x000D_ "gte": 1772113038000,_x000D_ "lte": 1772113038000_x000D_ },_x000D_ "inbound_rate_center": {_x000D_ "country": "US",_x000D_ "prefix": "1",_x000D_ "tollfree": false_x000D_ },_x000D_ "business_number": null,_x000D_ "business_label": null,_x000D_ "receiving_number_id": null,_x000D_ "receiving_number_sid": null,_x000D_ "billed_amount": 0,_x000D_ "billed_at": "0001-01-01T00:00:00",_x000D_ "excluded": false,_x000D_ "redacted": false,_x000D_ "tracking_number_format": "(435) 254-1043",_x000D_ "business_number_format": null,_x000D_ "alternative_number": "3199302733",_x000D_ "tracking_number_bare": "4352541043",_x000D_ "caller_number_format": "(319) 930-2733",_x000D_ "caller_number_complete": "\u002B13199302733",_x000D_ "caller_number_bare": "3199302733",_x000D_ "caller_number": "\u002B13199302733",_x000D_ "caller_number_split": [_x000D_ "1",_x000D_ "319",_x000D_ "930",_x000D_ "2733"_x000D_ ],_x000D_ "contact_number": "\u002B13199302733",_x000D_ "visitor": false,_x000D_ "call_path": [_x000D_ {_x000D_ "route_name": "_OnHangup_CallSync",_x000D_ "route_id": "640990",_x000D_ "route_type": "RoutingRule",_x000D_ "started_at": "2026-02-26T06:37:19Z"_x000D_ }_x000D_ ],_x000D_ "left_talk_time": 0,_x000D_ "right_talk_time": 0,_x000D_ "transfers": [],_x000D_ "call_status": "completed",_x000D_ "status": "completed",_x000D_ "spotted": [],_x000D_ "salesforce": {},_x000D_ "audio": null,_x000D_ "is_s3_link": false,_x000D_ "callbacks": [],_x000D_ "emails": [],_x000D_ "day": "Thursday",_x000D_ "month": "February",_x000D_ "hour": "06AM",_x000D_ "paid": {_x000D_ "source": null,_x000D_ "medium": null_x000D_ },_x000D_ "ga": {_x000D_ "cid": "441826.4049439926",_x000D_ "ga4": []_x000D_ },_x000D_ "tag_list": [],_x000D_ "latitude": 41.6583,_x000D_ "longitude": -91.5236,_x000D_ "extended_lookup_on": true,_x000D_ "form": {_x000D_ "number_to_call": "log-call-no-answer-2a5c7ae438094120",_x000D_ "customer_number_to_dial": "\u002B13199302733",_x000D_ "name": "Michele Mason",_x000D_ "email": "themason4@mchsi.com",_x000D_ "trackback_id": "trackback-441826.1772113038.8065274",_x000D_ "form_id": 213071,_x000D_ "form_name": "Contact Us",_x000D_ "custom": [_x000D_ {_x000D_ "label": "Referral Source",_x000D_ "value": "",_x000D_ "id": "referral_source"_x000D_ },_x000D_ {_x000D_ "label": "UTM Source",_x000D_ "value": "",_x000D_ "id": "utm_source"_x000D_ },_x000D_ {_x000D_ "label": "UTM Medium",_x000D_ "value": "",_x000D_ "id": "utm_medium"_x000D_ },_x000D_ {_x000D_ "label": "UTM Campaign",_x000D_ "value": "",_x000D_ "id": "utm_campaign"_x000D_ },_x000D_ {_x000D_ "label": "UTM Term",_x000D_ "value": "",_x000D_ "id": "utm_term"_x000D_ },_x000D_ {_x000D_ "label": "UTM Content",_x000D_ "value": "",_x000D_ "id": "utm_content"_x000D_ }_x000D_ ]_x000D_ },_x000D_ "legs": [],_x000D_ "touchpoints": null,_x000D_ "last_touch": null,_x000D_ "geo": {_x000D_ "lon": -91.5236,_x000D_ "lat": 41.6583_x000D_ },_x000D_ "timestamp": "0001-01-01T00:00:00"_x000D_ } | E41: 0 | F41: 1 | G41: 1399928 | H41: 1 | I41: 45811.007 | K41: 1577016 | L41: 1 | M41: 674 | N41: 45811.012 | P41: Home Protection Plan | Q41: 0 | R41: 4049439926 | S41: 2 | T41: 2026
A42: 3233855724 | B42: 46074.656 | C42: {_x000D_ "id": 4039875602,_x000D_ "sid": "log-call-no-answer-ab6732a8575d2067",_x000D_ "account_id": 441826,_x000D_ "name": "David Fontanese",_x000D_ "cnam": "David Fontanese",_x000D_ "search": "",_x000D_ "referrer": "",_x000D_ "visitor_sid": "",_x000D_ "location": "",_x000D_ "source": "Sandbox",_x000D_ "source_id": 1814974,_x000D_ "source_sid": "TSOF6FC2D2594D22C5288F2F91D669A9D5B9BE7FEE3C6EF44F4A9EA1A63913ECD83",_x000D_ "tgid": 5681974,_x000D_ "likelihood": null,_x000D_ "duration": 0,_x000D_ "direction": "form",_x000D_ "talk_time": 0,_x000D_ "ring_time": 0,_x000D_ "hold_time": 0,_x000D_ "wait_time": 0,_x000D_ "parent_id": null,_x000D_ "email": "dfontanese@yahoo.com",_x000D_ "street": null,_x000D_ "city": null,_x000D_ "state": null,_x000D_ "country": null,_x000D_ "postal_code": "90040",_x000D_ "called_at": "2026-02-21 09:44 AM -06:00",_x000D_ "unix_time": 1771692294,_x000D_ "tracking_number_id": 3476065,_x000D_ "tracking_number_sid": "TPNC3C4B23C348AEC2EE54EFD301979CD2EFFBA32881B159867D3F4ED59E6F0B56367EFF2993536685F",_x000D_ "tracking_number": "\u002B14352541043",_x000D_ "tracking_label": "Testing Number",_x000D_ "dial_status": "no-answer",_x000D_ "is_new_caller": true,_x000D_ "indexed_at": 1.7716929E+09,_x000D_ "agent_insights": false,_x000D_ "duration_period": {_x000D_ "gte": 1771692294000,_x000D_ "lte": 1771692294000_x000D_ },_x000D_ "inbound_rate_center": {_x000D_ "country": "US",_x000D_ "prefix": "1",_x000D_ "tollfree": false_x000D_ },_x000D_ "business_number": null,_x000D_ "business_label": null,_x000D_ "receiving_number_id": null,_x000D_ "receiving_number_sid": null,_x000D_ "billed_amount": 0,_x000D_ "billed_at": "0001-01-01T00:00:00",_x000D_ "excluded": false,_x000D_ "redacted": false,_x000D_ "tracking_number_format": "(435) 254-1043",_x000D_ "business_number_format": null,_x000D_ "alternative_number": "3233855724",_x000D_ "tracking_number_bare": "4352541043",_x000D_ "caller_number_format": "(323) 385-5724",_x000D_ "caller_number_complete": "\u002B13233855724",_x000D_ "caller_number_bare": "3233855724",_x000D_ "caller_number": "\u002B13233855724",_x000D_ "caller_number_split": [_x000D_ "1",_x000D_ "323",_x000D_ "385",_x000D_ "5724"_x000D_ ],_x000D_ "contact_number": "\u002B13233855724",_x000D_ "visitor": false,_x000D_ "call_path": [_x000D_ {_x000D_ "route_name": "_OnHangup_CallSync",_x000D_ "route_id": "640990",_x000D_ "route_type": "RoutingRule",_x000D_ "started_at": "2026-02-21T09:44:55Z"_x000D_ }_x000D_ ],_x000D_ "left_talk_time": 0,_x000D_ "right_talk_time": 0,_x000D_ "transfers": [],_x000D_ "call_status": "completed",_x000D_ "status": "completed",_x000D_ "spotted": [],_x000D_ "salesforce": {},_x000D_ "audio": null,_x000D_ "is_s3_link": false,_x000D_ "callbacks": [],_x000D_ "emails": [],_x000D_ "day": "Saturday",_x000D_ "month": "February",_x000D_ "hour": "09AM",_x000D_ "paid": {_x000D_ "source": null,_x000D_ "medium": null_x000D_ },_x000D_ "ga": {_x000D_ "cid": "441826.4039875602",_x000D_ "ga4": []_x000D_ },_x000D_ "tag_list": [],_x000D_ "latitude": 34.0156,_x000D_ "longitude": -118.112,_x000D_ "extended_lookup_on": true,_x000D_ "form": {_x000D_ "number_to_call": "log-call-no-answer-93a494e65c1e7fc7",_x000D_ "customer_number_to_dial": "\u002B13233855724",_x000D_ "name": "David Fontanese",_x000D_ "email": "dfontanese@yahoo.com",_x000D_ "trackback_id": "trackback-441826.1771692294.251765",_x000D_ "form_id": 213071,_x000D_ "form_name": "Contact Us",_x000D_ "custom": [_x000D_ {_x000D_ "label": "Referral Source",_x000D_ "value": "",_x000D_ "id": "referral_source"_x000D_ },_x000D_ {_x000D_ "label": "UTM Source",_x000D_ "value": "",_x000D_ "id": "utm_source"_x000D_ },_x000D_ {_x000D_ "label": "UTM Medium",_x000D_ "value": "",_x000D_ "id": "utm_medium"_x000D_ },_x000D_ {_x000D_ "label": "UTM Campaign",_x000D_ "value": "",_x000D_ "id": "utm_campaign"_x000D_ },_x000D_ {_x000D_ "label": "UTM Term",_x000D_ "value": "",_x000D_ "id": "utm_term"_x000D_ },_x000D_ {_x000D_ "label": "UTM Content",_x000D_ "value": "",_x000D_ "id": "utm_content"_x000D_ }_x000D_ ]_x000D_ },_x000D_ "legs": [],_x000D_ "touchpoints": null,_x000D_ "last_touch": null,_x000D_ "geo": {_x000D_ "lon": -118.112,_x000D_ "lat": 34.0156_x000D_ },_x000D_ "timestamp": "0001-01-01T00:00:00"_x000D_ } | E42: 0 | F42: 1 | G42: 1492086 | H42: 0 | I42: 45892.758 | J42: 1758896576000 | K42: 1699695 | L42: 1 | M42: 250 | N42: 45892.758 | O42: 1758541406000 | P42: Single Service | Q42: 0 | R42: 4039875602 | S42: 2 | T42: 2026
A43: 3377815239 | B43: 46072.803 | C43: {_x000D_ "id": 4036220144,_x000D_ "sid": "log-call-no-answer-019d02d08d05317b",_x000D_ "account_id": 441826,_x000D_ "name": "Luthen Francis",_x000D_ "cnam": "Luthen Francis",_x000D_ "search": "",_x000D_ "referrer": "",_x000D_ "visitor_sid": "",_x000D_ "location": "",_x000D_ "source": "Sandbox",_x000D_ "source_id": 1814974,_x000D_ "source_sid": "TSOF6FC2D2594D22C5288F2F91D669A9D5B9BE7FEE3C6EF44F4A9EA1A63913ECD83",_x000D_ "tgid": 5681974,_x000D_ "likelihood": null,_x000D_ "duration": 0,_x000D_ "direction": "form",_x000D_ "talk_time": 0,_x000D_ "ring_time": 0,_x000D_ "hold_time": 0,_x000D_ "wait_time": 0,_x000D_ "parent_id": null,_x000D_ "email": "bigglou6@gmail.com",_x000D_ "street": null,_x000D_ "city": null,_x000D_ "state": null,_x000D_ "country": null,_x000D_ "postal_code": "70501",_x000D_ "called_at": "2026-02-19 01:17 PM -06:00",_x000D_ "unix_time": 1771532226,_x000D_ "tracking_number_id": 3476065,_x000D_ "tracking_number_sid": "TPNC3C4B23C348AEC2EE54EFD301979CD2EFFBA32881B159867D3F4ED59E6F0B56367EFF2993536685F",_x000D_ "tracking_number": "\u002B14352541043",_x000D_ "tracking_label": "Testing Number",_x000D_ "dial_status": "no-answer",_x000D_ "is_new_caller": true,_x000D_ "indexed_at": 1.7715328E+09,_x000D_ "agent_insights": false,_x000D_ "duration_period": {_x000D_ "gte": 1771532226000,_x000D_ "lte": 1771532226000_x000D_ },_x000D_ "inbound_rate_center": {_x000D_ "country": "US",_x000D_ "prefix": "1",_x000D_ "tollfree": false_x000D_ },_x000D_ "business_number": null,_x000D_ "business_label": null,_x000D_ "receiving_number_id": null,_x000D_ "receiving_number_sid": null,_x000D_ "billed_amount": 0,_x000D_ "billed_at": "0001-01-01T00:00:00",_x000D_ "excluded": false,_x000D_ "redacted": false,_x000D_ "tracking_number_format": "(435) 254-1043",_x000D_ "business_number_format": null,_x000D_ "alternative_number": "3377815239",_x000D_ "tracking_number_bare": "4352541043",_x000D_ "caller_number_format": "(337) 781-5239",_x000D_ "caller_number_complete": "\u002B13377815239",_x000D_ "caller_number_bare": "3377815239",_x000D_ "caller_number": "\u002B13377815239",_x000D_ "caller_number_split": [_x000D_ "1",_x000D_ "337",_x000D_ "781",_x000D_ "5239"_x000D_ ],_x000D_ "contact_number": "\u002B13377815239",_x000D_ "visitor": false,_x000D_ "call_path": [_x000D_ {_x000D_ "route_name": "_OnHangup_CallSync",_x000D_ "route_id": "640990",_x000D_ "route_type": "RoutingRule",_x000D_ "started_at": "2026-02-19T13:17:07Z"_x000D_ }_x000D_ ],_x000D_ "left_talk_time": 0,_x000D_ "right_talk_time": 0,_x000D_ "transfers": [],_x000D_ "call_status": "completed",_x000D_ "status": "completed",_x000D_ "spotted": [],_x000D_ "salesforce": {},_x000D_ "audio": null,_x000D_ "is_s3_link": false,_x000D_ "callbacks": [],_x000D_ "emails": [],_x000D_ "day": "Thursday",_x000D_ "month": "February",_x000D_ "hour": "01PM",_x000D_ "paid": {_x000D_ "source": null,_x000D_ "medium": null_x000D_ },_x000D_ "ga": {_x000D_ "cid": "441826.4036220144",_x000D_ "ga4": []_x000D_ },_x000D_ "tag_list": [],_x000D_ "latitude": 30.2251,_x000D_ "longitude": -92.0158,_x000D_ "extended_lookup_on": true,_x000D_ "form": {_x000D_ "number_to_call": "log-call-no-answer-7a7d243a01dd44b6",_x000D_ "customer_number_to_dial": "\u002B13377815239",_x000D_ "name": "Luthen Francis",_x000D_ "email": "bigglou6@gmail.com",_x000D_ "trackback_id": "trackback-441826.1771532226.4210992",_x000D_ "form_id": 213071,_x000D_ "form_name": "Contact Us",_x000D_ "custom": [_x000D_ {_x000D_ "label": "Referral Source",_x000D_ "value": "",_x000D_ "id": "referral_source"_x000D_ },_x000D_ {_x000D_ "label": "UTM Source",_x000D_ "value": "",_x000D_ "id": "utm_source"_x000D_ },_x000D_ {_x000D_ "label": "UTM Medium",_x000D_ "value": "",_x000D_ "id": "utm_medium"_x000D_ },_x000D_ {_x000D_ "label": "UTM Campaign",_x000D_ "value": "",_x000D_ "id": "utm_campaign"_x000D_ },_x000D_ {_x000D_ "label": "UTM Term",_x000D_ "value": "",_x000D_ "id": "utm_term"_x000D_ },_x000D_ {_x000D_ "label": "UTM Content",_x000D_ "value": "",_x000D_ "id": "utm_content"_x000D_ }_x000D_ ]_x000D_ },_x000D_ "legs": [],_x000D_ "touchpoints": null,_x000D_ "last_touch": null,_x000D_ "geo": {_x000D_ "lon": -92.0158,_x000D_ "lat": 30.2251_x000D_ },_x000D_ "timestamp": "0001-01-01T00:00:00"_x000D_ } | E43: 0 | F43: 1 | G43: 1518883 | H43: 1 | I43: 46021.799 | K43: 1754244 | L43: 1 | M43: 686 | N43: 46021.799 | P43: Fox Home Protection Plan | Q43: 0 | R43: 4036220144 | S43: 2 | T43: 2026
A44: 3377815239 | B44: 46072.803 | C44: {_x000D_ "id": 4036220144,_x000D_ "sid": "log-call-no-answer-019d02d08d05317b",_x000D_ "account_id": 441826,_x000D_ "name": "Luthen Francis",_x000D_ "cnam": "Luthen Francis",_x000D_ "search": "",_x000D_ "referrer": "",_x000D_ "visitor_sid": "",_x000D_ "location": "",_x000D_ "source": "Sandbox",_x000D_ "source_id": 1814974,_x000D_ "source_sid": "TSOF6FC2D2594D22C5288F2F91D669A9D5B9BE7FEE3C6EF44F4A9EA1A63913ECD83",_x000D_ "tgid": 5681974,_x000D_ "likelihood": null,_x000D_ "duration": 0,_x000D_ "direction": "form",_x000D_ "talk_time": 0,_x000D_ "ring_time": 0,_x000D_ "hold_time": 0,_x000D_ "wait_time": 0,_x000D_ "parent_id": null,_x000D_ "email": "bigglou6@gmail.com",_x000D_ "street": null,_x000D_ "city": null,_x000D_ "state": null,_x000D_ "country": null,_x000D_ "postal_code": "70501",_x000D_ "called_at": "2026-02-19 01:17 PM -06:00",_x000D_ "unix_time": 1771532226,_x000D_ "tracking_number_id": 3476065,_x000D_ "tracking_number_sid": "TPNC3C4B23C348AEC2EE54EFD301979CD2EFFBA32881B159867D3F4ED59E6F0B56367EFF2993536685F",_x000D_ "tracking_number": "\u002B14352541043",_x000D_ "tracking_label": "Testing Number",_x000D_ "dial_status": "no-answer",_x000D_ "is_new_caller": true,_x000D_ "indexed_at": 1.7715328E+09,_x000D_ "agent_insights": false,_x000D_ "duration_period": {_x000D_ "gte": 1771532226000,_x000D_ "lte": 1771532226000_x000D_ },_x000D_ "inbound_rate_center": {_x000D_ "country": "US",_x000D_ "prefix": "1",_x000D_ "tollfree": false_x000D_ },_x000D_ "business_number": null,_x000D_ "business_label": null,_x000D_ "receiving_number_id": null,_x000D_ "receiving_number_sid": null,_x000D_ "billed_amount": 0,_x000D_ "billed_at": "0001-01-01T00:00:00",_x000D_ "excluded": false,_x000D_ "redacted": false,_x000D_ "tracking_number_format": "(435) 254-1043",_x000D_ "business_number_format": null,_x000D_ "alternative_number": "3377815239",_x000D_ "tracking_number_bare": "4352541043",_x000D_ "caller_number_format": "(337) 781-5239",_x000D_ "caller_number_complete": "\u002B13377815239",_x000D_ "caller_number_bare": "3377815239",_x000D_ "caller_number": "\u002B13377815239",_x000D_ "caller_number_split": [_x000D_ "1",_x000D_ "337",_x000D_ "781",_x000D_ "5239"_x000D_ ],_x000D_ "contact_number": "\u002B13377815239",_x000D_ "visitor": false,_x000D_ "call_path": [_x000D_ {_x000D_ "route_name": "_OnHangup_CallSync",_x000D_ "route_id": "640990",_x000D_ "route_type": "RoutingRule",_x000D_ "started_at": "2026-02-19T13:17:07Z"_x000D_ }_x000D_ ],_x000D_ "left_talk_time": 0,_x000D_ "right_talk_time": 0,_x000D_ "transfers": [],_x000D_ "call_status": "completed",_x000D_ "status": "completed",_x000D_ "spotted": [],_x000D_ "salesforce": {},_x000D_ "audio": null,_x000D_ "is_s3_link": false,_x000D_ "callbacks": [],_x000D_ "emails": [],_x000D_ "day": "Thursday",_x000D_ "month": "February",_x000D_ "hour": "01PM",_x000D_ "paid": {_x000D_ "source": null,_x000D_ "medium": null_x000D_ },_x000D_ "ga": {_x000D_ "cid": "441826.4036220144",_x000D_ "ga4": []_x000D_ },_x000D_ "tag_list": [],_x000D_ "latitude": 30.2251,_x000D_ "longitude": -92.0158,_x000D_ "extended_lookup_on": true,_x000D_ "form": {_x000D_ "number_to_call": "log-call-no-answer-7a7d243a01dd44b6",_x000D_ "customer_number_to_dial": "\u002B13377815239",_x000D_ "name": "Luthen Francis",_x000D_ "email": "bigglou6@gmail.com",_x000D_ "trackback_id": "trackback-441826.1771532226.4210992",_x000D_ "form_id": 213071,_x000D_ "form_name": "Contact Us",_x000D_ "custom": [_x000D_ {_x000D_ "label": "Referral Source",_x000D_ "value": "",_x000D_ "id": "referral_source"_x000D_ },_x000D_ {_x000D_ "label": "UTM Source",_x000D_ "value": "",_x000D_ "id": "utm_source"_x000D_ },_x000D_ {_x000D_ "label": "UTM Medium",_x000D_ "value": "",_x000D_ "id": "utm_medium"_x000D_ },_x000D_ {_x000D_ "label": "UTM Campaign",_x000D_ "value": "",_x000D_ "id": "utm_campaign"_x000D_ },_x000D_ {_x000D_ "label": "UTM Term",_x000D_ "value": "",_x000D_ "id": "utm_term"_x000D_ },_x000D_ {_x000D_ "label": "UTM Content",_x000D_ "value": "",_x000D_ "id": "utm_content"_x000D_ }_x000D_ ]_x000D_ },_x000D_ "legs": [],_x000D_ "touchpoints": null,_x000D_ "last_touch": null,_x000D_ "geo": {_x000D_ "lon": -92.0158,_x000D_ "lat": 30.2251_x000D_ },_x000D_ "timestamp": "0001-01-01T00:00:00"_x000D_ } | E44: 0 | F44: 1 | G44: 1522990 | H44: 1 | I44: 46067.617 | K44: 1767854 | L44: 1 | M44: 638 | N44: 46067.617 | P44: Fox Home Protection Plan | Q44: 0 | R44: 4036220144 | S44: 2 | T44: 2026
